Workbook

Sheet PASTE-DOWN-DL
C1: 1 | D1: 2 | E1: 3 | F1: 4 | G1: 5 | H1: 6 | I1: 7 | J1: 8 | K1: 9 | L1: 10 | M1: 11 | N1: 12 | O1: 13 | P1: 14 | Q1: 15 | R1: 16 | S1: 17 | T1: 18 | U1: 19 | V1: 20 | W1: 21 | X1: 22 | Y1: 23 | Z1: 24 | AA1: 25 | AB1: 26 | AC1: 27 | AD1: 28 | AE1: 29 | AF1: 30 | AG1: 31 | AH1: 32 | AI1: 33 | AJ1: 34 | AK1: 35 | AL1: 36 | AM1: 37 | AN1: 38 | AO1: 39 | AP1: 40 | AQ1: 41
A2: Don't do any change in GREY colored cells | U2: Paste here --- > CPAN DL FAIL REPORT
AL3: =TEXT(TODAY(),"dd-mm-yyyy") -> 15-05-2026
C4: Down | D4: =MAX(C10:C5000) -> 88 | U4: Choose Days DOWN | V4: 1
C8: 0 | I8: Name | J8: Media Type | K8: Bandwidth | L8: Signal Type | M8: Direction | N8: A End | O8: Z End | P8: Alarm Status | Q8: CIR Utilization Ratio(%) | R8: Bandwidth Utilization Ratio(%) | S8: Order Name | T8: Creator | U8: Client | V8: Cost | W8: Create Time | X8: Update Time | Y8: Description
C9: 0 | D9: ALARM | E9: SSA | F9: SSA TRIM | G9: SSA Sep | H9: Sr | I9: Name | J9: Media Type | K9: Bandwidth | L9: Signal Type | M9: Direction | N9: A End | O9: Z End | P9: Alarm Status | Q9: CIR Utilization Ratio(%) | R9: Bandwidth Utilization Ratio(%) | S9: Order Name | T9: Creator | U9: Client | V9: Cost | W9: Create Time | X9: Update Time | Y9: Description | Z9: DL name TRIM | AA9: A_Srch_ | AB9: A_SrchTN7 | AC9: Z_Srch_ | AD9: Z_SrchTN7 | AE9: A-END IP | AF9: Z-END IP | AG9: A-END Name | AH9: Z-END Name | AI9: A-END Port | AJ9: Z-END port | AK9: DOWN Date | AL9: DOWN time | AM9: A-END MIX | AN9: Z-END MIX | AO9: Down Days | AP9: Date-Time MIX
C10: =IF(D10="Critical",MAX($C$8:C9)+1,"") | D10: =TRIM(CLEAN(P10)) -> - | E10: =VLOOKUP('PASTE-DOWN-DL'!F10,'SSA-CODE'!$D$4:$E$56,2,FALSE) -> AHD | F10: =TRIM(CLEAN(SUBSTITUTE(G10,CHAR(160)," "))) -> SSA AM | G10: =MID(I10,1,SEARCH("-",I10)-1) -> SSA AM | H10: 1 | I10: SSA AM-10.121.18.249-Sector24_3/1-10.121.18.245-Sector11_3/1 | J10: Fiber | K10: 10GE | L10: Eth | M10: BI-DIR | N10: 10.121.18.245_SECTOR 11 GNE_TN725B_GJ_SSA AM_PH1\S3P1 | O10: 10.121.18.249_SECTOR 24_TN725B_GJ_SSA AM_PH3\S3P1 | P10: - | Q10: 34 | R10: 54 | T10: kanishk | V10: 1.0 | W10: 2019/05/20,18:42:34 | X10: 2026/04/18,11:21:46 | Z10: =TRIM(CLEAN(I10)) -> SSA AM-10.121.18.249-Sector24_3/1-10.121.18.245-Sector11_3/1 | AA10: =SEARCH("_",N10) -> 15 | AB10: =SEARCH("_TN7",N10) -> 29 | AC10: =SEARCH("_",O10) -> 15 | AD10: =SEARCH("_TN7",O10) -> 25 | AE10: =TRIM(CLEAN(MID(N10,1,SEARCH("_",N10)-1))) -> 10.121.18.245 | AF10: =TRIM(CLEAN(MID(O10,1,SEARCH("_",O10)-1))) -> 10.121.18.249 | AG10: =MID(N10,AA10+1,AB10-AA10-1) -> SECTOR 11 GNE | AH10: =MID(O10,AC10+1,AD10-AC10-1) -> SECTOR 24 | AI10: =RIGHT(N10,LEN(N10)-SEARCH("\",N10)) -> S3P1 | AJ10: =RIGHT(O10,LEN(O10)-SEARCH("\",O10)) -> S3P1 | AK10: =IFERROR(VLOOKUP(Z10,'PASTE-DL-ALARMS'!$Q$10:$W$2200,7,FALSE),"") | AL10: =IFERROR(VLOOKUP(Z10,'PASTE-DL-ALARMS'!$Q$10:$W$2200,3,FALSE),"") | AM10: =CONCATENATE(AE10,"_",AG10,"_",AI10) -> 10.121.18.245_SECTOR 11 GNE_S3P1 | AN10: =CONCATENATE(AF10,"_",AH10,"_",AJ10) -> 10.121.18.249_SECTOR 24_S3P1 | AO10: =$AL$3-AK10 -> #VALUE! | AP10: =IFERROR(VLOOKUP(Z10,'PASTE-DL-ALARMS'!$Q$10:$Z$2800,8,FALSE),"")
C11: =IF(D11="Critical",MAX($C$8:C10)+1,"") | D11: =TRIM(CLEAN(P11)) -> - | E11: =VLOOKUP('PASTE-DOWN-DL'!F11,'SSA-CODE'!$D$4:$E$56,2,FALSE) -> BCH | F11: =TRIM(CLEAN(SUBSTITUTE(G11,CHAR(160)," "))) -> SSA BCH | G11: =MID(I11,1,SEARCH("-",I11)-1) -> SSA BCH | H11: 2 | I11: SSA BCH-10.121.96.93-Grasim Chem Vilayat_2/5-10.121.96.94-Grasim Fibre Vilayat_1/5 | J11: Fiber | K11: GE | L11: Eth | M11: BI-DIR | N11: 10.121.96.93_Grasim Chem Vilayat_TN703B_GJ_SSA BCH_PH3\S2P5 | O11: 10.121.96.94_Grasim Fibre Vilayat_TN703B_GJ_SSA BCH_PH3\S1P5 | P11: - | Q11: 30 | R11: 100 | T11: kanishk | V11: 1.0 | W11: 2019/05/31,17:05:32 | X11: 2026/04/14,14:19:13 | Z11: =TRIM(CLEAN(I11)) -> SSA BCH-10.121.96.93-Grasim Chem Vilayat_2/5-10.121.96.94-Grasim Fibre Vilayat_1/5 | AA11: =SEARCH("_",N11) -> 14 | AB11: =SEARCH("_TN7",N11) -> 34 | AC11: =SEARCH("_",O11) -> 14 | AD11: =SEARCH("_TN7",O11) -> 35 | AE11: =TRIM(CLEAN(MID(N11,1,SEARCH("_",N11)-1))) -> 10.121.96.93 | AF11: =TRIM(CLEAN(MID(O11,1,SEARCH("_",O11)-1))) -> 10.121.96.94 | AG11: =MID(N11,AA11+1,AB11-AA11-1) -> Grasim Chem Vilayat | AH11: =MID(O11,AC11+1,AD11-AC11-1) -> Grasim Fibre Vilayat | AI11: =RIGHT(N11,LEN(N11)-SEARCH("\",N11)) -> S2P5 | AJ11: =RIGHT(O11,LEN(O11)-SEARCH("\",O11)) -> S1P5 | AK11: =IFERROR(VLOOKUP(Z11,'PASTE-DL-ALARMS'!$Q$10:$W$2200,7,FALSE),"") | AL11: =IFERROR(VLOOKUP(Z11,'PASTE-DL-ALARMS'!$Q$10:$W$2200,3,FALSE),"") | AM11: =CONCATENATE(AE11,"_",AG11,"_",AI11) -> 10.121.96.93_Grasim Chem Vilayat_S2P5 | AN11: =CONCATENATE(AF11,"_",AH11,"_",AJ11) -> 10.121.96.94_Grasim Fibre Vilayat_S1P5 | AO11: =$AL$3-AK11 -> #VALUE! | AP11: =IFERROR(VLOOKUP(Z11,'PASTE-DL-ALARMS'!$Q$10:$Z$2800,8,FALSE),"")
C12: =IF(D12="Critical",MAX($C$8:C11)+1,"") | D12: =TRIM(CLEAN(P12)) -> - | E12: =VLOOKUP('PASTE-DOWN-DL'!F12,'SSA-CODE'!$D$4:$E$56,2,FALSE) -> VAL | F12: =TRIM(CLEAN(SUBSTITUTE(G12,CHAR(160)," "))) -> SSA VAL | G12: =MID(I12,1,SEARCH("-",I12)-1) -> SSA VAL | H12: 3 | I12: SSA VAL-10.121.68.67-Silvassa_6/3-10.121.68.80-NIC-Silvassa_1/5 | J12: Fiber | K12: GE | L12: Eth | M12: BI-DIR | N12: 10.121.68.80_NIC Silvassa_TN703B_GJ_SSA VAL_PH2\S1P5 | O12: 10.121.68.67_Silvassa_TN725B_WTR_AM_PH3\S6P3 | P12: - | Q12: 68 | R12: 100 | S12: VALSAD SSA | T12: minaxikataria | U12: GCS ISSUE ID : 26139 | V12: 1.0 | W12: 2023/10/05,18:43:37 | X12: 2026/04/18,11:22:35 | Z12: =TRIM(CLEAN(I12)) -> SSA VAL-10.121.68.67-Silvassa_6/3-10.121.68.80-NIC-Silvassa_1/5 | AA12: =SEARCH("_",N12) -> 14 | AB12: =SEARCH("_TN7",N12) -> 27 | AC12: =SEARCH("_",O12) -> 14 | AD12: =SEARCH("_TN7",O12) -> 23 | AE12: =TRIM(CLEAN(MID(N12,1,SEARCH("_",N12)-1))) -> 10.121.68.80 | AF12: =TRIM(CLEAN(MID(O12,1,SEARCH("_",O12)-1))) -> 10.121.68.67 | AG12: =MID(N12,AA12+1,AB12-AA12-1) -> NIC Silvassa | AH12: =MID(O12,AC12+1,AD12-AC12-1) -> Silvassa | AI12: =RIGHT(N12,LEN(N12)-SEARCH("\",N12)) -> S1P5 | AJ12: =RIGHT(O12,LEN(O12)-SEARCH("\",O12)) -> S6P3 | AK12: =IFERROR(VLOOKUP(Z12,'PASTE-DL-ALARMS'!$Q$10:$W$2200,7,FALSE),"") | AL12: =IFERROR(VLOOKUP(Z12,'PASTE-DL-ALARMS'!$Q$10:$W$2200,3,FALSE),"") | AM12: =CONCATENATE(AE12,"_",AG12,"_",AI12) -> 10.121.68.80_NIC Silvassa_S1P5 | AN12: =CONCATENATE(AF12,"_",AH12,"_",AJ12) -> 10.121.68.67_Silvassa_S6P3 | AO12: =$AL$3-AK12 -> #VALUE! | AP12: =IFERROR(VLOOKUP(Z12,'PASTE-DL-ALARMS'!$Q$10:$Z$2800,8,FALSE),"")
C13: =IF(D13="Critical",MAX($C$8:C12)+1,"") | D13: =TRIM(CLEAN(P13)) -> - | E13: =VLOOKUP('PASTE-DOWN-DL'!F13,'SSA-CODE'!$D$4:$E$56,2,FALSE) -> AMR | F13: =TRIM(CLEAN(SUBSTITUTE(G13,CHAR(160)," "))) -> SSA AMR | G13: =MID(I13,1,SEARCH("-",I13)-1) -> SSA AMR | H13: 4 | I13: SSA AMR-10.121.96.26-SVU_GswanTC_2/6-10.121.96.11-KUP_Exch_4/2 | J13: Fiber | K13: GE | L13: Eth | M13: BI-DIR | N13: 10.121.96.26_SVU GSWAN TC_TN703B_GJ_SSA AMR_PH2\S2P6 | O13: 10.121.96.11_KUP EXCH_TN705B_GJ_SSA AMR_PH3\S4P2 | P13: - | Q13: 96 | R13: 100 | T13: 198505975 | U13: GujAmreli_SSA | V13: 1.0 | W13: 2019/11/05,11:09:21 | X13: 2026/04/18,11:23:10 | Z13: =TRIM(CLEAN(I13)) -> SSA AMR-10.121.96.26-SVU_GswanTC_2/6-10.121.96.11-KUP_Exch_4/2 | AA13: =SEARCH("_",N13) -> 14 | AB13: =SEARCH("_TN7",N13) -> 27 | AC13: =SEARCH("_",O13) -> 14 | AD13: =SEARCH("_TN7",O13) -> 23 | AE13: =TRIM(CLEAN(MID(N13,1,SEARCH("_",N13)-1))) -> 10.121.96.26 | AF13: =TRIM(CLEAN(MID(O13,1,SEARCH("_",O13)-1))) -> 10.121.96.11 | AG13: =MID(N13,AA13+1,AB13-AA13-1) -> SVU GSWAN TC | AH13: =MID(O13,AC13+1,AD13-AC13-1) -> KUP EXCH | AI13: =RIGHT(N13,LEN(N13)-SEARCH("\",N13)) -> S2P6 | AJ13: =RIGHT(O13,LEN(O13)-SEARCH("\",O13)) -> S4P2 | AK13: =IFERROR(VLOOKUP(Z13,'PASTE-DL-ALARMS'!$Q$10:$W$2200,7,FALSE),"") | AL13: =IFERROR(VLOOKUP(Z13,'PASTE-DL-ALARMS'!$Q$10:$W$2200,3,FALSE),"") | AM13: =CONCATENATE(AE13,"_",AG13,"_",AI13) -> 10.121.96.26_SVU GSWAN TC_S2P6 | AN13: =CONCATENATE(AF13,"_",AH13,"_",AJ13) -> 10.121.96.11_KUP EXCH_S4P2 | AO13: =$AL$3-AK13 -> #VALUE! | AP13: =IFERROR(VLOOKUP(Z13,'PASTE-DL-ALARMS'!$Q$10:$Z$2800,8,FALSE),"")
C14: =IF(D14="Critical",MAX($C$8:C13)+1,"") | D14: =TRIM(CLEAN(P14)) -> - | E14: =VLOOKUP('PASTE-DOWN-DL'!F14,'SSA-CODE'!$D$4:$E$56,2,FALSE) -> GDR | F14: =TRIM(CLEAN(SUBSTITUTE(G14,CHAR(160)," "))) -> SSA GDH | G14: =MID(I14,1,SEARCH("-",I14)-1) -> SSA GDH | H14: 5 | I14: SSA GDH-10.121.19.16-Nandarva_1/5-10.121.16.195-Sehra_3/2 | J14: Fiber | K14: GE | L14: Eth | M14: BI-DIR | N14: 10.121.19.16_Nandarva_TN703B_GJ_SSA GDH_PH3\S1P5 | O14: 10.121.16.195_Sehra_TN705B_WTR_AM_PH1\S3P2 | P14: - | Q14: 18 | R14: 100 | S14: Godhra_SSA_GCS_ID_15148 | T14: 199105665 | U14: Godhra_SSA | V14: 1.0 | W14: 2022/03/07,15:19:22 | X14: 2026/04/18,11:23:33 | Z14: =TRIM(CLEAN(I14)) -> SSA GDH-10.121.19.16-Nandarva_1/5-10.121.16.195-Sehra_3/2 | AA14: =SEARCH("_",N14) -> 14 | AB14: =SEARCH("_TN7",N14) -> 23 | AC14: =SEARCH("_",O14) -> 15 | AD14: =SEARCH("_TN7",O14) -> 21 | AE14: =TRIM(CLEAN(MID(N14,1,SEARCH("_",N14)-1))) -> 10.121.19.16 | AF14: =TRIM(CLEAN(MID(O14,1,SEARCH("_",O14)-1))) -> 10.121.16.195 | AG14: =MID(N14,AA14+1,AB14-AA14-1) -> Nandarva | AH14: =MID(O14,AC14+1,AD14-AC14-1) -> Sehra | AI14: =RIGHT(N14,LEN(N14)-SEARCH("\",N14)) -> S1P5 | AJ14: =RIGHT(O14,LEN(O14)-SEARCH("\",O14)) -> S3P2 | AK14: =IFERROR(VLOOKUP(Z14,'PASTE-DL-ALARMS'!$Q$10:$W$2200,7,FALSE),"") | AL14: =IFERROR(VLOOKUP(Z14,'PASTE-DL-ALARMS'!$Q$10:$W$2200,3,FALSE),"") | AM14: =CONCATENATE(AE14,"_",AG14,"_",AI14) -> 10.121.19.16_Nandarva_S1P5 | AN14: =CONCATENATE(AF14,"_",AH14,"_",AJ14) -> 10.121.16.195_Sehra_S3P2 | AO14: =$AL$3-AK14 -> #VALUE! | AP14: =IFERROR(VLOOKUP(Z14,'PASTE-DL-ALARMS'!$Q$10:$Z$2800,8,FALSE),"")
C15: =IF(D15="Critical",MAX($C$8:C14)+1,"") | D15: =TRIM(CLEAN(P15)) -> - | E15: =VLOOKUP('PASTE-DOWN-DL'!F15,'SSA-CODE'!$D$4:$E$56,2,FALSE) -> BHV | F15: =TRIM(CLEAN(SUBSTITUTE(G15,CHAR(160)," "))) -> SSA BV | G15: =MID(I15,1,SEARCH("-",I15)-1) -> SSA BV | H15: 6 | I15: SSA BV-10.121.17.165-Tana_2/5-10.121.17.164-Madhada_3/2 | J15: Fiber | K15: GE | L15: Eth | M15: BI-DIR | N15: 10.121.17.165_Tana_TN703B_GJ_SSA BV_PH3\S2P5 | O15: 10.121.17.164_MADHADA_TN705B_GJ_SSA BV_PH3\S3P2 | P15: - | Q15: 31 | R15: 100 | S15: Bhavnagar SSA GCS ID 40918 | T15: 200800716 | U15: Bhavnagar SSA GCS ID 40918 | V15: 1.0 | W15: 2025/04/19,18:19:56 | X15: 2026/04/02,13:10:43 | Z15: =TRIM(CLEAN(I15)) -> SSA BV-10.121.17.165-Tana_2/5-10.121.17.164-Madhada_3/2 | AA15: =SEARCH("_",N15) -> 15 | AB15: =SEARCH("_TN7",N15) -> 20 | AC15: =SEARCH("_",O15) -> 15 | AD15: =SEARCH("_TN7",O15) -> 23 | AE15: =TRIM(CLEAN(MID(N15,1,SEARCH("_",N15)-1))) -> 10.121.17.165 | AF15: =TRIM(CLEAN(MID(O15,1,SEARCH("_",O15)-1))) -> 10.121.17.164 | AG15: =MID(N15,AA15+1,AB15-AA15-1) -> Tana | AH15: =MID(O15,AC15+1,AD15-AC15-1) -> MADHADA | AI15: =RIGHT(N15,LEN(N15)-SEARCH("\",N15)) -> S2P5 | AJ15: =RIGHT(O15,LEN(O15)-SEARCH("\",O15)) -> S3P2 | AK15: =IFERROR(VLOOKUP(Z15,'PASTE-DL-ALARMS'!$Q$10:$W$2200,7,FALSE),"") | AL15: =IFERROR(VLOOKUP(Z15,'PASTE-DL-ALARMS'!$Q$10:$W$2200,3,FALSE),"") | AM15: =CONCATENATE(AE15,"_",AG15,"_",AI15) -> 10.121.17.165_Tana_S2P5 | AN15: =CONCATENATE(AF15,"_",AH15,"_",AJ15) -> 10.121.17.164_MADHADA_S3P2 | AO15: =$AL$3-AK15 -> #VALUE! | AP15: =IFERROR(VLOOKUP(Z15,'PASTE-DL-ALARMS'!$Q$10:$Z$2800,8,FALSE),"")
C16: =IF(D16="Critical",MAX($C$8:C15)+1,"") | D16: =TRIM(CLEAN(P16)) -> - | E16: =VLOOKUP('PASTE-DOWN-DL'!F16,'SSA-CODE'!$D$4:$E$56,2,FALSE) -> JND | F16: =TRIM(CLEAN(SUBSTITUTE(G16,CHAR(160)," "))) -> SSA JND | G16: =MID(I16,1,SEARCH("-",I16)-1) -> SSA JND | H16: 7 | I16: SSA JND-10.121.24.10-Somnath_1/5-10.121.24.25-GIDC VRL_1/5 | J16: Fiber | K16: GE | L16: Eth | M16: BI-DIR | N16: 10.121.24.10_SOMNATH_TN703B_GJ_SSA JND_PH2\S1P5 | O16: 10.121.24.25_GIDC VRL_TN703B_GJ_SSA JND_PH2\S1P5 | P16: - | Q16: 58 | R16: 100 | S16: Guj GCS ID: 035941 | T16: 200700547 | U16: Guj GCS ID: 035941 | V16: 1.0 | W16: 2024/11/20,16:23:53 | X16: 2026/04/02,13:11:21 | Z16: =TRIM(CLEAN(I16)) -> SSA JND-10.121.24.10-Somnath_1/5-10.121.24.25-GIDC VRL_1/5 | AA16: =SEARCH("_",N16) -> 14 | AB16: =SEARCH("_TN7",N16) -> 22 | AC16: =SEARCH("_",O16) -> 14 | AD16: =SEARCH("_TN7",O16) -> 23 | AE16: =TRIM(CLEAN(MID(N16,1,SEARCH("_",N16)-1))) -> 10.121.24.10 | AF16: =TRIM(CLEAN(MID(O16,1,SEARCH("_",O16)-1))) -> 10.121.24.25 | AG16: =MID(N16,AA16+1,AB16-AA16-1) -> SOMNATH | AH16: =MID(O16,AC16+1,AD16-AC16-1) -> GIDC VRL | AI16: =RIGHT(N16,LEN(N16)-SEARCH("\",N16)) -> S1P5 | AJ16: =RIGHT(O16,LEN(O16)-SEARCH("\",O16)) -> S1P5 | AK16: =IFERROR(VLOOKUP(Z16,'PASTE-DL-ALARMS'!$Q$10:$W$2200,7,FALSE),"") | AL16: =IFERROR(VLOOKUP(Z16,'PASTE-DL-ALARMS'!$Q$10:$W$2200,3,FALSE),"") | AM16: =CONCATENATE(AE16,"_",AG16,"_",AI16) -> 10.121.24.10_SOMNATH_S1P5 | AN16: =CONCATENATE(AF16,"_",AH16,"_",AJ16) -> 10.121.24.25_GIDC VRL_S1P5 | AO16: =$AL$3-AK16 -> #VALUE! | AP16: =IFERROR(VLOOKUP(Z16,'PASTE-DL-ALARMS'!$Q$10:$Z$2800,8,FALSE),"")
C17: =IF(D17="Critical",MAX($C$8:C16)+1,"") | D17: =TRIM(CLEAN(P17)) -> - | E17: =VLOOKUP('PASTE-DOWN-DL'!F17,'SSA-CODE'!$D$4:$E$56,2,FALSE) -> GDR | F17: =TRIM(CLEAN(SUBSTITUTE(G17,CHAR(160)," "))) -> SSA GDH | G17: =MID(I17,1,SEARCH("-",I17)-1) -> SSA GDH | H17: 8 | I17: SSA GDH-10.121.16.228-Godhra2_6/1-10.121.26.65-Godhra(GNE)_6/1 | J17: Fiber | K17: 10GE | L17: Eth | M17: BI-DIR | N17: 10.121.16.228_Godhra 2_TN725B_WTR_AM_PH1\S6P1 | O17: 10.121.26.65_Godhra (GNE)_TN725B_WTR_AM_PH2\S6P1 | P17: - | Q17: 75 | R17: 100 | S17: Godhra SSA | T17: minaxikataria | U17: GCS Issue id : 19925 | V17: 1.0 | W17: 2022/11/14,12:34:25 | X17: 2026/04/18,11:24:25 | Z17: =TRIM(CLEAN(I17)) -> SSA GDH-10.121.16.228-Godhra2_6/1-10.121.26.65-Godhra(GNE)_6/1 | AA17: =SEARCH("_",N17) -> 15 | AB17: =SEARCH("_TN7",N17) -> 24 | AC17: =SEARCH("_",O17) -> 14 | AD17: =SEARCH("_TN7",O17) -> 27 | AE17: =TRIM(CLEAN(MID(N17,1,SEARCH("_",N17)-1))) -> 10.121.16.228 | AF17: =TRIM(CLEAN(MID(O17,1,SEARCH("_",O17)-1))) -> 10.121.26.65 | AG17: =MID(N17,AA17+1,AB17-AA17-1) -> Godhra 2 | AH17: =MID(O17,AC17+1,AD17-AC17-1) -> Godhra (GNE) | AI17: =RIGHT(N17,LEN(N17)-SEARCH("\",N17)) -> S6P1 | AJ17: =RIGHT(O17,LEN(O17)-SEARCH("\",O17)) -> S6P1 | AK17: =IFERROR(VLOOKUP(Z17,'PASTE-DL-ALARMS'!$Q$10:$W$2200,7,FALSE),"") | AL17: =IFERROR(VLOOKUP(Z17,'PASTE-DL-ALARMS'!$Q$10:$W$2200,3,FALSE),"") | AM17: =CONCATENATE(AE17,"_",AG17,"_",AI17) -> 10.121.16.228_Godhra 2_S6P1 | AN17: =CONCATENATE(AF17,"_",AH17,"_",AJ17) -> 10.121.26.65_Godhra (GNE)_S6P1 | AO17: =$AL$3-AK17 -> #VALUE! | AP17: =IFERROR(VLOOKUP(Z17,'PASTE-DL-ALARMS'!$Q$10:$Z$2800,8,FALSE),"")
C18: =IF(D18="Critical",MAX($C$8:C17)+1,"") | D18: =TRIM(CLEAN(P18)) -> - | E18: =VLOOKUP('PASTE-DOWN-DL'!F18,'SSA-CODE'!$D$4:$E$56,2,FALSE) -> JMN | F18: =TRIM(CLEAN(SUBSTITUTE(G18,CHAR(160)," "))) -> SSA JMN | G18: =MID(I18,1,SEARCH("-",I18)-1) -> SSA JMN | H18: 9 | I18: SSA JMN-10.121.97.129-Mehulnagar ALB_6/4-10.121.20.1-Mehul Nagar(GNE)_6/4 | J18: Fiber | K18: GE | L18: Eth | M18: BI-DIR | N18: 10.121.97.129_Mehulnagar ALB_TN725B_GJ_SSA JMN_PH3\S6P4 | O18: 10.121.20.1_Mehul Nagar(GNE)_TN725B_GJ_SSA JMN_PH2\S6P4 | P18: - | Q18: 70 | R18: 100 | S18: Guj GCS ID No.- 044941 | T18: 200700547 | U18: SSA Jamnagar | V18: 1.0 | W18: 2025/09/11,12:38:46 | X18: 2026/04/02,13:12:32 | Z18: =TRIM(CLEAN(I18)) -> SSA JMN-10.121.97.129-Mehulnagar ALB_6/4-10.121.20.1-Mehul Nagar(GNE)_6/4 | AA18: =SEARCH("_",N18) -> 15 | AB18: =SEARCH("_TN7",N18) -> 30 | AC18: =SEARCH("_",O18) -> 13 | AD18: =SEARCH("_TN7",O18) -> 30 | AE18: =TRIM(CLEAN(MID(N18,1,SEARCH("_",N18)-1))) -> 10.121.97.129 | AF18: =TRIM(CLEAN(MID(O18,1,SEARCH("_",O18)-1))) -> 10.121.20.1 | AG18: =MID(N18,AA18+1,AB18-AA18-1) -> Mehulnagar ALB | AH18: =MID(O18,AC18+1,AD18-AC18-1) -> Mehul Nagar(GNE) | AI18: =RIGHT(N18,LEN(N18)-SEARCH("\",N18)) -> S6P4 | AJ18: =RIGHT(O18,LEN(O18)-SEARCH("\",O18)) -> S6P4 | AK18: =IFERROR(VLOOKUP(Z18,'PASTE-DL-ALARMS'!$Q$10:$W$2200,7,FALSE),"") | AL18: =IFERROR(VLOOKUP(Z18,'PASTE-DL-ALARMS'!$Q$10:$W$2200,3,FALSE),"") | AM18: =CONCATENATE(AE18,"_",AG18,"_",AI18) -> 10.121.97.129_Mehulnagar ALB_S6P4 | AN18: =CONCATENATE(AF18,"_",AH18,"_",AJ18) -> 10.121.20.1_Mehul Nagar(GNE)_S6P4 | AO18: =$AL$3-AK18 -> #VALUE! | AP18: =IFERROR(VLOOKUP(Z18,'PASTE-DL-ALARMS'!$Q$10:$Z$2800,8,FALSE),"")
C19: =IF(D19="Critical",MAX($C$8:C18)+1,"") | D19: =TRIM(CLEAN(P19)) -> - | E19: =VLOOKUP('PASTE-DOWN-DL'!F19,'SSA-CODE'!$D$4:$E$56,2,FALSE) -> BUJ | F19: =TRIM(CLEAN(SUBSTITUTE(G19,CHAR(160)," "))) -> SSA BUJ | G19: =MID(I19,1,SEARCH("-",I19)-1) -> SSA BUJ | H19: 10 | I19: SSA BUJ-10.121.96.156-Mata_na_Madh_1/5-10.121.96.137-Dayapar_4/3 | J19: Fiber | K19: GE | L19: Eth | M19: BI-DIR | N19: 10.121.96.137_Dayapar_TN705B_GJ_SSA BUJ_PH3\S4P3 | O19: 10.121.96.156_MATA NA MADH_TN703B_GJ_SSA BUJ_PH2\S1P5 | P19: - | Q19: 36 | R19: 100 | S19: Bhuj SSA - GCS ID-0002860 | T19: ritesh | U19: Bhuj SSA | V19: 1.0 | W19: 2019/07/09,18:40:33 | X19: 2026/04/18,11:25:02 | Z19: =TRIM(CLEAN(I19)) -> SSA BUJ-10.121.96.156-Mata_na_Madh_1/5-10.121.96.137-Dayapar_4/3 | AA19: =SEARCH("_",N19) -> 15 | AB19: =SEARCH("_TN7",N19) -> 23 | AC19: =SEARCH("_",O19) -> 15 | AD19: =SEARCH("_TN7",O19) -> 28 | AE19: =TRIM(CLEAN(MID(N19,1,SEARCH("_",N19)-1))) -> 10.121.96.137 | AF19: =TRIM(CLEAN(MID(O19,1,SEARCH("_",O19)-1))) -> 10.121.96.156 | AG19: =MID(N19,AA19+1,AB19-AA19-1) -> Dayapar | AH19: =MID(O19,AC19+1,AD19-AC19-1) -> MATA NA MADH | AI19: =RIGHT(N19,LEN(N19)-SEARCH("\",N19)) -> S4P3 | AJ19: =RIGHT(O19,LEN(O19)-SEARCH("\",O19)) -> S1P5 | AK19: =IFERROR(VLOOKUP(Z19,'PASTE-DL-ALARMS'!$Q$10:$W$2200,7,FALSE),"") | AL19: =IFERROR(VLOOKUP(Z19,'PASTE-DL-ALARMS'!$Q$10:$W$2200,3,FALSE),"") | AM19: =CONCATENATE(AE19,"_",AG19,"_",AI19) -> 10.121.96.137_Dayapar_S4P3 | AN19: =CONCATENATE(AF19,"_",AH19,"_",AJ19) -> 10.121.96.156_MATA NA MADH_S1P5 | AO19: =$AL$3-AK19 -> #VALUE! | AP19: =IFERROR(VLOOKUP(Z19,'PASTE-DL-ALARMS'!$Q$10:$Z$2800,8,FALSE),"")
C20: =IF(D20="Critical",MAX($C$8:C19)+1,"") | D20: =TRIM(CLEAN(P20)) -> - | E20: =VLOOKUP('PASTE-DOWN-DL'!F20,'SSA-CODE'!$D$4:$E$56,2,FALSE) -> BUJ | F20: =TRIM(CLEAN(SUBSTITUTE(G20,CHAR(160)," "))) -> SSA BUJ | G20: =MID(I20,1,SEARCH("-",I20)-1) -> SSA BUJ | H20: 11 | I20: SSA BUJ-10.121.24.67-Gandhidham_4/4-10.121.17.69-Gandhidham_4/5 | J20: Fiber | K20: GE | L20: Eth | M20: BI-DIR | N20: 10.121.24.67_Gandhidham_TN725B_GJ_SSA BUJ_PH2\S4P4 | O20: 10.121.17.69_GANDHIDHAM_TN725B_WTR_RJ_PH1\S4P5 | P20: - | Q20: 53 | R20: 100 | S20: Bhuj SSA | T20: vishleshpatel | U20: Bhuj SSA | V20: 1.0 | W20: 2019/03/11,16:45:48 | X20: 2025/02/22,12:38:23 | Z20: =TRIM(CLEAN(I20)) -> SSA BUJ-10.121.24.67-Gandhidham_4/4-10.121.17.69-Gandhidham_4/5 | AA20: =SEARCH("_",N20) -> 14 | AB20: =SEARCH("_TN7",N20) -> 25 | AC20: =SEARCH("_",O20) -> 14 | AD20: =SEARCH("_TN7",O20) -> 25 | AE20: =TRIM(CLEAN(MID(N20,1,SEARCH("_",N20)-1))) -> 10.121.24.67 | AF20: =TRIM(CLEAN(MID(O20,1,SEARCH("_",O20)-1))) -> 10.121.17.69 | AG20: =MID(N20,AA20+1,AB20-AA20-1) -> Gandhidham | AH20: =MID(O20,AC20+1,AD20-AC20-1) -> GANDHIDHAM | AI20: =RIGHT(N20,LEN(N20)-SEARCH("\",N20)) -> S4P4 | AJ20: =RIGHT(O20,LEN(O20)-SEARCH("\",O20)) -> S4P5 | AK20: =IFERROR(VLOOKUP(Z20,'PASTE-DL-ALARMS'!$Q$10:$W$2200,7,FALSE),"") | AL20: =IFERROR(VLOOKUP(Z20,'PASTE-DL-ALARMS'!$Q$10:$W$2200,3,FALSE),"") | AM20: =CONCATENATE(AE20,"_",AG20,"_",AI20) -> 10.121.24.67_Gandhidham_S4P4 | AN20: =CONCATENATE(AF20,"_",AH20,"_",AJ20) -> 10.121.17.69_GANDHIDHAM_S4P5 | AO20: =$AL$3-AK20 -> #VALUE! | AP20: =IFERROR(VLOOKUP(Z20,'PASTE-DL-ALARMS'!$Q$10:$Z$2800,8,FALSE),"")
C21: =IF(D21="Critical",MAX($C$8:C20)+1,"") | D21: =TRIM(CLEAN(P21)) -> - | E21: =VLOOKUP('PASTE-DOWN-DL'!F21,'SSA-CODE'!$D$4:$E$56,2,FALSE) -> SEN | F21: =TRIM(CLEAN(SUBSTITUTE(G21,CHAR(160)," "))) -> SSA SEN | G21: =MID(I21,1,SEARCH("-",I21)-1) -> SSA SEN | H21: 12 | I21: SSA SEN-10.121.99.31-Vana_3/1-10.121.99.38-Patdi_3/1-10GE | J21: Fiber | K21: 10GE | L21: Eth | M21: BI-DIR | N21: 10.121.99.31_VANA_TN705B_GJ_SSA SEN_PH3\S3P1 | O21: 10.121.99.38_PATDI_TN705B_WTR_RJ_PH1\S3P1 | P21: - | Q21: 18 | R21: 27 | S21: Surendranagar_SSA_GCS_Id_0007086 | T21: 199105665 | U21: Surendranagar_SSA | V21: 1.0 | W21: 2024/08/26,14:46:00 | X21: 2026/04/18,11:26:42 | Z21: =TRIM(CLEAN(I21)) -> SSA SEN-10.121.99.31-Vana_3/1-10.121.99.38-Patdi_3/1-10GE | AA21: =SEARCH("_",N21) -> 14 | AB21: =SEARCH("_TN7",N21) -> 19 | AC21: =SEARCH("_",O21) -> 14 | AD21: =SEARCH("_TN7",O21) -> 20 | AE21: =TRIM(CLEAN(MID(N21,1,SEARCH("_",N21)-1))) -> 10.121.99.31 | AF21: =TRIM(CLEAN(MID(O21,1,SEARCH("_",O21)-1))) -> 10.121.99.38 | AG21: =MID(N21,AA21+1,AB21-AA21-1) -> VANA | AH21: =MID(O21,AC21+1,AD21-AC21-1) -> PATDI | AI21: =RIGHT(N21,LEN(N21)-SEARCH("\",N21)) -> S3P1 | AJ21: =RIGHT(O21,LEN(O21)-SEARCH("\",O21)) -> S3P1 | AK21: =IFERROR(VLOOKUP(Z21,'PASTE-DL-ALARMS'!$Q$10:$W$2200,7,FALSE),"") | AL21: =IFERROR(VLOOKUP(Z21,'PASTE-DL-ALARMS'!$Q$10:$W$2200,3,FALSE),"") | AM21: =CONCATENATE(AE21,"_",AG21,"_",AI21) -> 10.121.99.31_VANA_S3P1 | AN21: =CONCATENATE(AF21,"_",AH21,"_",AJ21) -> 10.121.99.38_PATDI_S3P1 | AO21: =$AL$3-AK21 -> #VALUE! | AP21: =IFERROR(VLOOKUP(Z21,'PASTE-DL-ALARMS'!$Q$10:$Z$2800,8,FALSE),"")
C22: =IF(D22="Critical",MAX($C$8:C21)+1,"") | D22: =TRIM(CLEAN(P22)) -> - | E22: =VLOOKUP('PASTE-DOWN-DL'!F22,'SSA-CODE'!$D$4:$E$56,2,FALSE) -> SRT | F22: =TRIM(CLEAN(SUBSTITUTE(G22,CHAR(160)," "))) -> SSA SR | G22: =MID(I22,1,SEARCH("-",I22)-1) -> SSA SR | H22: 13 | I22: SSA SR-10.121.19.213-GETCO_ICHP_3/1-10.121.19.199-Rundh_5/1 | J22: Fiber | K22: 10GE | L22: Eth | M22: BI-DIR | N22: 10.121.19.199_RUNDH_TN725B_GJ_SSA SR_PH2\S5P1 | O22: 10.121.19.213_GETCO ICHP_TN705B_GJ_SSA SR_PH3\S3P1 | P22: - | Q22: 39 | R22: 59 | S22: GCS ID 37455 | T22: 200800022 | U22: SURAT SSA | V22: 1.0 | W22: 2025/07/16,16:20:54 | X22: 2026/04/18,11:27:22 | Z22: =TRIM(CLEAN(I22)) -> SSA SR-10.121.19.213-GETCO_ICHP_3/1-10.121.19.199-Rundh_5/1 | AA22: =SEARCH("_",N22) -> 15 | AB22: =SEARCH("_TN7",N22) -> 21 | AC22: =SEARCH("_",O22) -> 15 | AD22: =SEARCH("_TN7",O22) -> 26 | AE22: =TRIM(CLEAN(MID(N22,1,SEARCH("_",N22)-1))) -> 10.121.19.199 | AF22: =TRIM(CLEAN(MID(O22,1,SEARCH("_",O22)-1))) -> 10.121.19.213 | AG22: =MID(N22,AA22+1,AB22-AA22-1) -> RUNDH | AH22: =MID(O22,AC22+1,AD22-AC22-1) -> GETCO ICHP | AI22: =RIGHT(N22,LEN(N22)-SEARCH("\",N22)) -> S5P1 | AJ22: =RIGHT(O22,LEN(O22)-SEARCH("\",O22)) -> S3P1 | AK22: =IFERROR(VLOOKUP(Z22,'PASTE-DL-ALARMS'!$Q$10:$W$2200,7,FALSE),"") | AL22: =IFERROR(VLOOKUP(Z22,'PASTE-DL-ALARMS'!$Q$10:$W$2200,3,FALSE),"") | AM22: =CONCATENATE(AE22,"_",AG22,"_",AI22) -> 10.121.19.199_RUNDH_S5P1 | AN22: =CONCATENATE(AF22,"_",AH22,"_",AJ22) -> 10.121.19.213_GETCO ICHP_S3P1 | AO22: =$AL$3-AK22 -> #VALUE! | AP22: =IFERROR(VLOOKUP(Z22,'PASTE-DL-ALARMS'!$Q$10:$Z$2800,8,FALSE),"")
C23: =IF(D23="Critical",MAX($C$8:C22)+1,"") | D23: =TRIM(CLEAN(P23)) -> - | E23: =VLOOKUP('PASTE-DOWN-DL'!F23,'SSA-CODE'!$D$4:$E$56,2,FALSE) -> NDD | F23: =TRIM(CLEAN(SUBSTITUTE(G23,CHAR(160)," "))) -> SSA NAD | G23: =MID(I23,1,SEARCH("-",I23)-1) -> SSA NAD | H23: 14 | I23: SSA NAD-10.121.16.151-Naika_1/5-10.121.16.130-Kheda_5/3 | J23: Fiber | K23: GE | L23: Eth | M23: BI-DIR | N23: 10.121.16.151_Naika_TN703B_GJ_SSA NAD_PH3\S1P5 | O23: 10.121.16.130_Kheda_TN725B_WTR_AM_PH1\S5P3 | P23: - | Q23: 11 | R23: 100 | S23: GUJ GCS ID- 039080 | T23: 200700547 | U23: Nadiad | V23: 1.0 | W23: 2025/02/19,13:53:53 | X23: 2026/04/18,11:28:02 | Z23: =TRIM(CLEAN(I23)) -> SSA NAD-10.121.16.151-Naika_1/5-10.121.16.130-Kheda_5/3 | AA23: =SEARCH("_",N23) -> 15 | AB23: =SEARCH("_TN7",N23) -> 21 | AC23: =SEARCH("_",O23) -> 15 | AD23: =SEARCH("_TN7",O23) -> 21 | AE23: =TRIM(CLEAN(MID(N23,1,SEARCH("_",N23)-1))) -> 10.121.16.151 | AF23: =TRIM(CLEAN(MID(O23,1,SEARCH("_",O23)-1))) -> 10.121.16.130 | AG23: =MID(N23,AA23+1,AB23-AA23-1) -> Naika | AH23: =MID(O23,AC23+1,AD23-AC23-1) -> Kheda | AI23: =RIGHT(N23,LEN(N23)-SEARCH("\",N23)) -> S1P5 | AJ23: =RIGHT(O23,LEN(O23)-SEARCH("\",O23)) -> S5P3 | AK23: =IFERROR(VLOOKUP(Z23,'PASTE-DL-ALARMS'!$Q$10:$W$2200,7,FALSE),"") | AL23: =IFERROR(VLOOKUP(Z23,'PASTE-DL-ALARMS'!$Q$10:$W$2200,3,FALSE),"") | AM23: =CONCATENATE(AE23,"_",AG23,"_",AI23) -> 10.121.16.151_Naika_S1P5 | AN23: =CONCATENATE(AF23,"_",AH23,"_",AJ23) -> 10.121.16.130_Kheda_S5P3 | AO23: =$AL$3-AK23 -> #VALUE! | AP23: =IFERROR(VLOOKUP(Z23,'PASTE-DL-ALARMS'!$Q$10:$Z$2800,8,FALSE),"")
C24: =IF(D24="Critical",MAX($C$8:C23)+1,"") | D24: =TRIM(CLEAN(P24)) -> - | E24: =VLOOKUP('PASTE-DOWN-DL'!F24,'SSA-CODE'!$D$4:$E$56,2,FALSE) -> VDA | F24: =TRIM(CLEAN(SUBSTITUTE(G24,CHAR(160)," "))) -> SSA VDR | G24: =MID(I24,1,SEARCH("-",I24)-1) -> SSA VDR | H24: 15 | I24: SSA VDR-10.121.99.142-ONGC_3/1-10.121.19.132-Makarpura_5/1 | J24: Fiber | K24: 10GE | L24: Eth | M24: BI-DIR | N24: 10.121.99.142_ONGC_TN705B_GJ_SSA VDR_PH3\S3P1 | O24: 10.121.19.132_MAKARPURA_TN725B_GJ_SSA VDR_PH2\S5P1 | P24: - | Q24: 26 | R24: 56 | T24: Vikas | V24: 1.0 | W24: 2019/03/22,10:47:45 | X24: 2026/04/18,11:29:22 | Z24: =TRIM(CLEAN(I24)) -> SSA VDR-10.121.99.142-ONGC_3/1-10.121.19.132-Makarpura_5/1 | AA24: =SEARCH("_",N24) -> 15 | AB24: =SEARCH("_TN7",N24) -> 20 | AC24: =SEARCH("_",O24) -> 15 | AD24: =SEARCH("_TN7",O24) -> 25 | AE24: =TRIM(CLEAN(MID(N24,1,SEARCH("_",N24)-1))) -> 10.121.99.142 | AF24: =TRIM(CLEAN(MID(O24,1,SEARCH("_",O24)-1))) -> 10.121.19.132 | AG24: =MID(N24,AA24+1,AB24-AA24-1) -> ONGC | AH24: =MID(O24,AC24+1,AD24-AC24-1) -> MAKARPURA | AI24: =RIGHT(N24,LEN(N24)-SEARCH("\",N24)) -> S3P1 | AJ24: =RIGHT(O24,LEN(O24)-SEARCH("\",O24)) -> S5P1 | AK24: =IFERROR(VLOOKUP(Z24,'PASTE-DL-ALARMS'!$Q$10:$W$2200,7,FALSE),"") | AL24: =IFERROR(VLOOKUP(Z24,'PASTE-DL-ALARMS'!$Q$10:$W$2200,3,FALSE),"") | AM24: =CONCATENATE(AE24,"_",AG24,"_",AI24) -> 10.121.99.142_ONGC_S3P1 | AN24: =CONCATENATE(AF24,"_",AH24,"_",AJ24) -> 10.121.19.132_MAKARPURA_S5P1 | AO24: =$AL$3-AK24 -> #VALUE! | AP24: =IFERROR(VLOOKUP(Z24,'PASTE-DL-ALARMS'!$Q$10:$Z$2800,8,FALSE),"")
C25: =IF(D25="Critical",MAX($C$8:C24)+1,"") | D25: =TRIM(CLEAN(P25)) -> - | E25: =VLOOKUP('PASTE-DOWN-DL'!F25,'SSA-CODE'!$D$4:$E$56,2,FALSE) -> WTR RJ | F25: =TRIM(CLEAN(SUBSTITUTE(G25,CHAR(160)," "))) -> WTR RJ | G25: =MID(I25,1,SEARCH("-",I25)-1) -> WTR RJ | H25: 16 | I25: WTR RJ-10.121.17.129-Bhavnagar(GNE)_6/1-10.121.17.161-Bhavnagar3_6/1 | J25: Fiber | K25: 10GE | L25: Eth | M25: BI-DIR | N25: 10.121.17.161_BHAVNAGAR3_TN725B_WTR_RJ_PH2\S6P1 | O25: 10.121.17.129_BHAVNAGAR(GNE)_TN725B_WTR_RJ_PH2\S6P1 | P25: - | Q25: 84 | R25: 100 | T25: Nikhil | V25: 1.0 | W25: 2019/05/15,12:15:49 | X25: 2026/04/18,11:31:04 | Z25: =TRIM(CLEAN(I25)) -> WTR RJ-10.121.17.129-Bhavnagar(GNE)_6/1-10.121.17.161-Bhavnagar3_6/1 | AA25: =SEARCH("_",N25) -> 15 | AB25: =SEARCH("_TN7",N25) -> 26 | AC25: =SEARCH("_",O25) -> 15 | AD25: =SEARCH("_TN7",O25) -> 30 | AE25: =TRIM(CLEAN(MID(N25,1,SEARCH("_",N25)-1))) -> 10.121.17.161 | AF25: =TRIM(CLEAN(MID(O25,1,SEARCH("_",O25)-1))) -> 10.121.17.129 | AG25: =MID(N25,AA25+1,AB25-AA25-1) -> BHAVNAGAR3 | AH25: =MID(O25,AC25+1,AD25-AC25-1) -> BHAVNAGAR(GNE) | AI25: =RIGHT(N25,LEN(N25)-SEARCH("\",N25)) -> S6P1 | AJ25: =RIGHT(O25,LEN(O25)-SEARCH("\",O25)) -> S6P1 | AK25: =IFERROR(VLOOKUP(Z25,'PASTE-DL-ALARMS'!$Q$10:$W$2200,7,FALSE),"") | AL25: =IFERROR(VLOOKUP(Z25,'PASTE-DL-ALARMS'!$Q$10:$W$2200,3,FALSE),"") | AM25: =CONCATENATE(AE25,"_",AG25,"_",AI25) -> 10.121.17.161_BHAVNAGAR3_S6P1 | AN25: =CONCATENATE(AF25,"_",AH25,"_",AJ25) -> 10.121.17.129_BHAVNAGAR(GNE)_S6P1 | AO25: =$AL$3-AK25 -> #VALUE! | AP25: =IFERROR(VLOOKUP(Z25,'PASTE-DL-ALARMS'!$Q$10:$Z$2800,8,FALSE),"")
C26: =IF(D26="Critical",MAX($C$8:C25)+1,"") | D26: =TRIM(CLEAN(P26)) -> - | E26: =VLOOKUP('PASTE-DOWN-DL'!F26,'SSA-CODE'!$D$4:$E$56,2,FALSE) -> AHD | F26: =TRIM(CLEAN(SUBSTITUTE(G26,CHAR(160)," "))) -> SSA AM | G26: =MID(I26,1,SEARCH("-",I26)-1) -> SSA AM | H26: 17 | I26: SSA AM-10.121.18.243-Bhat_4/5-10.121.18.239-IPR Bhat_2/5 | J26: Fiber | K26: GE | L26: Eth | M26: BI-DIR | N26: 10.121.18.243_Bhat_TN705B_GJ_SSA AM_PH2\S4P5 | O26: 10.121.18.239_IPR Bhat_TN703B_GJ_SSA AM_PH2\S2P5 | P26: - | Q26: 6 | R26: 98 | S26: Ahmedabad SSA-0007842 | T26: ritesh | V26: 1.0 | W26: 2020/09/16,20:02:14 | X26: 2026/04/18,11:31:31 | Z26: =TRIM(CLEAN(I26)) -> SSA AM-10.121.18.243-Bhat_4/5-10.121.18.239-IPR Bhat_2/5 | AA26: =SEARCH("_",N26) -> 15 | AB26: =SEARCH("_TN7",N26) -> 20 | AC26: =SEARCH("_",O26) -> 15 | AD26: =SEARCH("_TN7",O26) -> 24 | AE26: =TRIM(CLEAN(MID(N26,1,SEARCH("_",N26)-1))) -> 10.121.18.243 | AF26: =TRIM(CLEAN(MID(O26,1,SEARCH("_",O26)-1))) -> 10.121.18.239 | AG26: =MID(N26,AA26+1,AB26-AA26-1) -> Bhat | AH26: =MID(O26,AC26+1,AD26-AC26-1) -> IPR Bhat | AI26: =RIGHT(N26,LEN(N26)-SEARCH("\",N26)) -> S4P5 | AJ26: =RIGHT(O26,LEN(O26)-SEARCH("\",O26)) -> S2P5 | AK26: =IFERROR(VLOOKUP(Z26,'PASTE-DL-ALARMS'!$Q$10:$W$2200,7,FALSE),"") | AL26: =IFERROR(VLOOKUP(Z26,'PASTE-DL-ALARMS'!$Q$10:$W$2200,3,FALSE),"") | AM26: =CONCATENATE(AE26,"_",AG26,"_",AI26) -> 10.121.18.243_Bhat_S4P5 | AN26: =CONCATENATE(AF26,"_",AH26,"_",AJ26) -> 10.121.18.239_IPR Bhat_S2P5 | AO26: =$AL$3-AK26 -> #VALUE! | AP26: =IFERROR(VLOOKUP(Z26,'PASTE-DL-ALARMS'!$Q$10:$Z$2800,8,FALSE),"")
C27: =IF(D27="Critical",MAX($C$8:C26)+1,"") | D27: =TRIM(CLEAN(P27)) -> - | E27: =VLOOKUP('PASTE-DOWN-DL'!F27,'SSA-CODE'!$D$4:$E$56,2,FALSE) -> JND | F27: =TRIM(CLEAN(SUBSTITUTE(G27,CHAR(160)," "))) -> SSA JND | G27: =MID(I27,1,SEARCH("-",I27)-1) -> SSA JND | H27: 18 | I27: SSA JND-10.121.24.7-Veraval_TE_5/1-10.121.97.230-Ajotha_TE_4/1 | J27: Fiber | K27: 10GE | L27: Eth | M27: BI-DIR | N27: 10.121.24.7_VERAVALTE B1_TN725B_GJ_SSA JND_PH2\S5P1 | O27: 10.121.97.230_AJOTHA TE_TN705B_GJ_SSA JND_PH3\S4P1 | P27: - | Q27: 2 | R27: 11 | S27: Guj GCS ID No.- 048227 | T27: 200700547 | U27: SSA JND | V27: 1.0 | W27: 2026/01/20,13:04:30 | X27: 2026/04/18,11:32:13 | Z27: =TRIM(CLEAN(I27)) -> SSA JND-10.121.24.7-Veraval_TE_5/1-10.121.97.230-Ajotha_TE_4/1 | AA27: =SEARCH("_",N27) -> 13 | AB27: =SEARCH("_TN7",N27) -> 26 | AC27: =SEARCH("_",O27) -> 15 | AD27: =SEARCH("_TN7",O27) -> 25 | AE27: =TRIM(CLEAN(MID(N27,1,SEARCH("_",N27)-1))) -> 10.121.24.7 | AF27: =TRIM(CLEAN(MID(O27,1,SEARCH("_",O27)-1))) -> 10.121.97.230 | AG27: =MID(N27,AA27+1,AB27-AA27-1) -> VERAVALTE B1 | AH27: =MID(O27,AC27+1,AD27-AC27-1) -> AJOTHA TE | AI27: =RIGHT(N27,LEN(N27)-SEARCH("\",N27)) -> S5P1 | AJ27: =RIGHT(O27,LEN(O27)-SEARCH("\",O27)) -> S4P1 | AK27: =IFERROR(VLOOKUP(Z27,'PASTE-DL-ALARMS'!$Q$10:$W$2200,7,FALSE),"") | AL27: =IFERROR(VLOOKUP(Z27,'PASTE-DL-ALARMS'!$Q$10:$W$2200,3,FALSE),"") | AM27: =CONCATENATE(AE27,"_",AG27,"_",AI27) -> 10.121.24.7_VERAVALTE B1_S5P1 | AN27: =CONCATENATE(AF27,"_",AH27,"_",AJ27) -> 10.121.97.230_AJOTHA TE_S4P1 | AO27: =$AL$3-AK27 -> #VALUE! | AP27: =IFERROR(VLOOKUP(Z27,'PASTE-DL-ALARMS'!$Q$10:$Z$2800,8,FALSE),"")
C28: =IF(D28="Critical",MAX($C$8:C27)+1,"") | D28: =TRIM(CLEAN(P28)) -> - | E28: =VLOOKUP('PASTE-DOWN-DL'!F28,'SSA-CODE'!$D$4:$E$56,2,FALSE) -> VDA | F28: =TRIM(CLEAN(SUBSTITUTE(G28,CHAR(160)," "))) -> SSA VDR | G28: =MID(I28,1,SEARCH("-",I28)-1) -> SSA VDR | H28: 19 | I28: SSA VDR-10.121.19.142-Gotri_Medical_1/5-10.121.19.136-Gotri_3/2 | J28: Fiber | K28: GE | L28: Eth | M28: BI-DIR | N28: 10.121.19.142_GOTRI Medical_TN703B_GJ_SSA VDR_PH3\S1P5 | O28: 10.121.19.136_GOTRI_TN705B_GJ_SSA VDR_PH2\S3P2 | P28: - | Q28: 25 | R28: 100 | S28: Vadodara SSA | T28: minaxikataria | U28: Vadodara SSA | V28: 1.0 | W28: 2022/02/07,12:58:48 | X28: 2026/04/20,13:02:16 | Z28: =TRIM(CLEAN(I28)) -> SSA VDR-10.121.19.142-Gotri_Medical_1/5-10.121.19.136-Gotri_3/2 | AA28: =SEARCH("_",N28) -> 15 | AB28: =SEARCH("_TN7",N28) -> 29 | AC28: =SEARCH("_",O28) -> 15 | AD28: =SEARCH("_TN7",O28) -> 21 | AE28: =TRIM(CLEAN(MID(N28,1,SEARCH("_",N28)-1))) -> 10.121.19.142 | AF28: =TRIM(CLEAN(MID(O28,1,SEARCH("_",O28)-1))) -> 10.121.19.136 | AG28: =MID(N28,AA28+1,AB28-AA28-1) -> GOTRI Medical | AH28: =MID(O28,AC28+1,AD28-AC28-1) -> GOTRI | AI28: =RIGHT(N28,LEN(N28)-SEARCH("\",N28)) -> S1P5 | AJ28: =RIGHT(O28,LEN(O28)-SEARCH("\",O28)) -> S3P2 | AK28: =IFERROR(VLOOKUP(Z28,'PASTE-DL-ALARMS'!$Q$10:$W$2200,7,FALSE),"") | AL28: =IFERROR(VLOOKUP(Z28,'PASTE-DL-ALARMS'!$Q$10:$W$2200,3,FALSE),"") | AM28: =CONCATENATE(AE28,"_",AG28,"_",AI28) -> 10.121.19.142_GOTRI Medical_S1P5 | AN28: =CONCATENATE(AF28,"_",AH28,"_",AJ28) -> 10.121.19.136_GOTRI_S3P2 | AO28: =$AL$3-AK28 -> #VALUE! | AP28: =IFERROR(VLOOKUP(Z28,'PASTE-DL-ALARMS'!$Q$10:$Z$2800,8,FALSE),"")
C29: =IF(D29="Critical",MAX($C$8:C28)+1,"") | D29: =TRIM(CLEAN(P29)) -> - | E29: =VLOOKUP('PASTE-DOWN-DL'!F29,'SSA-CODE'!$D$4:$E$56,2,FALSE) -> MSN | F29: =TRIM(CLEAN(SUBSTITUTE(G29,CHAR(160)," "))) -> SSA MEH | G29: =MID(I29,1,SEARCH("-",I29)-1) -> SSA MEH | H29: 20 | I29: SSA MEH-10.121.25.102-Sipor_Exch_2/5-10.121.25.80-Shapar_Exch_1/5 | J29: Fiber | K29: GE | L29: Eth | M29: BI-DIR | N29: 10.121.25.102_SIPOR EXCH_TN703B_GJ_SSA MEH_PH2\S2P5 | O29: 10.121.25.80_SHAPUR EXCH_TN703B_GJ_SSA MEH_PH2\S1P5 | P29: - | Q29: 9 | R29: 100 | S29: GCS-46197 | T29: 200800474 | U29: GCS-46197 | V29: 1.0 | W29: 2025/11/04,22:04:31 | X29: 2026/04/18,11:33:17 | Z29: =TRIM(CLEAN(I29)) -> SSA MEH-10.121.25.102-Sipor_Exch_2/5-10.121.25.80-Shapar_Exch_1/5 | AA29: =SEARCH("_",N29) -> 15 | AB29: =SEARCH("_TN7",N29) -> 26 | AC29: =SEARCH("_",O29) -> 14 | AD29: =SEARCH("_TN7",O29) -> 26 | AE29: =TRIM(CLEAN(MID(N29,1,SEARCH("_",N29)-1))) -> 10.121.25.102 | AF29: =TRIM(CLEAN(MID(O29,1,SEARCH("_",O29)-1))) -> 10.121.25.80 | AG29: =MID(N29,AA29+1,AB29-AA29-1) -> SIPOR EXCH | AH29: =MID(O29,AC29+1,AD29-AC29-1) -> SHAPUR EXCH | AI29: =RIGHT(N29,LEN(N29)-SEARCH("\",N29)) -> S2P5 | AJ29: =RIGHT(O29,LEN(O29)-SEARCH("\",O29)) -> S1P5 | AK29: =IFERROR(VLOOKUP(Z29,'PASTE-DL-ALARMS'!$Q$10:$W$2200,7,FALSE),"") | AL29: =IFERROR(VLOOKUP(Z29,'PASTE-DL-ALARMS'!$Q$10:$W$2200,3,FALSE),"") | AM29: =CONCATENATE(AE29,"_",AG29,"_",AI29) -> 10.121.25.102_SIPOR EXCH_S2P5 | AN29: =CONCATENATE(AF29,"_",AH29,"_",AJ29) -> 10.121.25.80_SHAPUR EXCH_S1P5 | AO29: =$AL$3-AK29 -> #VALUE! | AP29: =IFERROR(VLOOKUP(Z29,'PASTE-DL-ALARMS'!$Q$10:$Z$2800,8,FALSE),"")
C30: =IF(D30="Critical",MAX($C$8:C29)+1,"") | D30: =TRIM(CLEAN(P30)) -> - | E30: =VLOOKUP('PASTE-DOWN-DL'!F30,'SSA-CODE'!$D$4:$E$56,2,FALSE) -> BUJ | F30: =TRIM(CLEAN(SUBSTITUTE(G30,CHAR(160)," "))) -> SSA BUJ | G30: =MID(I30,1,SEARCH("-",I30)-1) -> SSA BUJ | H30: 21 | I30: SSA BUJ-10.121.17.86-Kunvarbet_Army_1/5-10.121.96.187-Khavda_5/5 | J30: Fiber | K30: GE | L30: Eth | M30: BI-DIR | N30: 10.121.17.86_Kunvarbet Army_TN703B_GJ_SSA BUJ_PH3\S1P5 | O30: 10.121.96.187_KHAVDA_TN725B_GJ_SSA BUJ_PH3\S5P5 | P30: - | Q30: 5 | R30: 96 | S30: Bhuj SSA GCS ID 43615 | T30: 200800716 | U30: Bhuj SSA GCS ID 43615 | V30: 1.0 | W30: 2025/07/29,14:54:33 | X30: 2026/04/18,11:33:39 | Z30: =TRIM(CLEAN(I30)) -> SSA BUJ-10.121.17.86-Kunvarbet_Army_1/5-10.121.96.187-Khavda_5/5 | AA30: =SEARCH("_",N30) -> 14 | AB30: =SEARCH("_TN7",N30) -> 29 | AC30: =SEARCH("_",O30) -> 15 | AD30: =SEARCH("_TN7",O30) -> 22 | AE30: =TRIM(CLEAN(MID(N30,1,SEARCH("_",N30)-1))) -> 10.121.17.86 | AF30: =TRIM(CLEAN(MID(O30,1,SEARCH("_",O30)-1))) -> 10.121.96.187 | AG30: =MID(N30,AA30+1,AB30-AA30-1) -> Kunvarbet Army | AH30: =MID(O30,AC30+1,AD30-AC30-1) -> KHAVDA | AI30: =RIGHT(N30,LEN(N30)-SEARCH("\",N30)) -> S1P5 | AJ30: =RIGHT(O30,LEN(O30)-SEARCH("\",O30)) -> S5P5 | AK30: =IFERROR(VLOOKUP(Z30,'PASTE-DL-ALARMS'!$Q$10:$W$2200,7,FALSE),"") | AL30: =IFERROR(VLOOKUP(Z30,'PASTE-DL-ALARMS'!$Q$10:$W$2200,3,FALSE),"") | AM30: =CONCATENATE(AE30,"_",AG30,"_",AI30) -> 10.121.17.86_Kunvarbet Army_S1P5 | AN30: =CONCATENATE(AF30,"_",AH30,"_",AJ30) -> 10.121.96.187_KHAVDA_S5P5 | AO30: =$AL$3-AK30 -> #VALUE! | AP30: =IFERROR(VLOOKUP(Z30,'PASTE-DL-ALARMS'!$Q$10:$Z$2800,8,FALSE),"")
C31: =IF(D31="Critical",MAX($C$8:C30)+1,"") | D31: =TRIM(CLEAN(P31)) -> - | E31: =VLOOKUP('PASTE-DOWN-DL'!F31,'SSA-CODE'!$D$4:$E$56,2,FALSE) -> VAL | F31: =TRIM(CLEAN(SUBSTITUTE(G31,CHAR(160)," "))) -> SSA VAL | G31: =MID(I31,1,SEARCH("-",I31)-1) -> SSA VAL | H31: 22 | I31: SSA VAL-10.121.16.67-Navasari_4/2-10.121.16.121-Navsari Agricultural University_2/5 | J31: Fiber | K31: GE | L31: Eth | M31: BI-DIR | N31: 10.121.16.67_NAVASARI_TN725B_WTR_AM_PH2\S4P2 | O31: 10.121.16.121_Navsari Agricultural University_TN703B_GJ_SSA VAL_PH2\S2P5 | P31: - | Q31: 8 | R31: 99 | S31: Valsad SSA GCS ID 19649 | T31: 200800716 | U31: Valsad SSA GCS ID 19649 | V31: 1.0 | W31: 2022/10/30,00:07:57 | X31: 2026/04/18,11:38:21 | Z31: =TRIM(CLEAN(I31)) -> SSA VAL-10.121.16.67-Navasari_4/2-10.121.16.121-Navsari Agricultural University_2/5 | AA31: =SEARCH("_",N31) -> 14 | AB31: =SEARCH("_TN7",N31) -> 23 | AC31: =SEARCH("_",O31) -> 15 | AD31: =SEARCH("_TN7",O31) -> 47 | AE31: =TRIM(CLEAN(MID(N31,1,SEARCH("_",N31)-1))) -> 10.121.16.67 | AF31: =TRIM(CLEAN(MID(O31,1,SEARCH("_",O31)-1))) -> 10.121.16.121 | AG31: =MID(N31,AA31+1,AB31-AA31-1) -> NAVASARI | AH31: =MID(O31,AC31+1,AD31-AC31-1) -> Navsari Agricultural University | AI31: =RIGHT(N31,LEN(N31)-SEARCH("\",N31)) -> S4P2 | AJ31: =RIGHT(O31,LEN(O31)-SEARCH("\",O31)) -> S2P5 | AK31: =IFERROR(VLOOKUP(Z31,'PASTE-DL-ALARMS'!$Q$10:$W$2200,7,FALSE),"") | AL31: =IFERROR(VLOOKUP(Z31,'PASTE-DL-ALARMS'!$Q$10:$W$2200,3,FALSE),"") | AM31: =CONCATENATE(AE31,"_",AG31,"_",AI31) -> 10.121.16.67_NAVASARI_S4P2 | AN31: =CONCATENATE(AF31,"_",AH31,"_",AJ31) -> 10.121.16.121_Navsari Agricultural University_S2P5 | AO31: =$AL$3-AK31 -> #VALUE! | AP31: =IFERROR(VLOOKUP(Z31,'PASTE-DL-ALARMS'!$Q$10:$Z$2800,8,FALSE),"")
C32: =IF(D32="Critical",MAX($C$8:C31)+1,"") | D32: =TRIM(CLEAN(P32)) -> - | E32: =VLOOKUP('PASTE-DOWN-DL'!F32,'SSA-CODE'!$D$4:$E$56,2,FALSE) -> NDD | F32: =TRIM(CLEAN(SUBSTITUTE(G32,CHAR(160)," "))) -> SSA NAD | G32: =MID(I32,1,SEARCH("-",I32)-1) -> SSA NAD | H32: 23 | I32: SSA NAD-10.121.24.238-Sojitra_4/2-10.121.98.85-Vatav _1/5 | J32: Fiber | K32: GE | L32: Eth | M32: BI-DIR | N32: 10.121.24.238_Sojitra B1_TN705B_GJ_SSA NAD_PH2\S4P2 | O32: 10.121.98.85_Vatav _TN703B_GJ_SSA NAD_PH3\S1P5 | P32: - | Q32: 48 | R32: 100 | S32: Nadiad SSA GCS ID 45911 | T32: 200800716 | U32: Nadiad SSA GCS ID 45911 | V32: 1.0 | W32: 2025/10/16,00:13:18 | X32: 2026/04/18,11:38:49 | Z32: =TRIM(CLEAN(I32)) -> SSA NAD-10.121.24.238-Sojitra_4/2-10.121.98.85-Vatav _1/5 | AA32: =SEARCH("_",N32) -> 15 | AB32: =SEARCH("_TN7",N32) -> 26 | AC32: =SEARCH("_",O32) -> 14 | AD32: =SEARCH("_TN7",O32) -> 21 | AE32: =TRIM(CLEAN(MID(N32,1,SEARCH("_",N32)-1))) -> 10.121.24.238 | AF32: =TRIM(CLEAN(MID(O32,1,SEARCH("_",O32)-1))) -> 10.121.98.85 | AG32: =MID(N32,AA32+1,AB32-AA32-1) -> Sojitra B1 | AH32: =MID(O32,AC32+1,AD32-AC32-1) -> Vatav | AI32: =RIGHT(N32,LEN(N32)-SEARCH("\",N32)) -> S4P2 | AJ32: =RIGHT(O32,LEN(O32)-SEARCH("\",O32)) -> S1P5 | AK32: =IFERROR(VLOOKUP(Z32,'PASTE-DL-ALARMS'!$Q$10:$W$2200,7,FALSE),"") | AL32: =IFERROR(VLOOKUP(Z32,'PASTE-DL-ALARMS'!$Q$10:$W$2200,3,FALSE),"") | AM32: =CONCATENATE(AE32,"_",AG32,"_",AI32) -> 10.121.24.238_Sojitra B1_S4P2 | AN32: =CONCATENATE(AF32,"_",AH32,"_",AJ32) -> 10.121.98.85_Vatav _S1P5 | AO32: =$AL$3-AK32 -> #VALUE! | AP32: =IFERROR(VLOOKUP(Z32,'PASTE-DL-ALARMS'!$Q$10:$Z$2800,8,FALSE),"")
C33: =IF(D33="Critical",MAX($C$8:C32)+1,"") | D33: =TRIM(CLEAN(P33)) -> - | E33: =VLOOKUP('PASTE-DOWN-DL'!F33,'SSA-CODE'!$D$4:$E$56,2,FALSE) -> WTR AM | F33: =TRIM(CLEAN(SUBSTITUTE(G33,CHAR(160)," "))) -> WTR AM | G33: =MID(I33,1,SEARCH("-",I33)-1) -> WTR AM | H33: 24 | I33: WTR AM-10.121.15.132-Gandhinagar_6/1-10.121.15.193-Mehsana3(GNE)_6/1 | J33: Fiber | K33: 10GE | L33: Eth | M33: BI-DIR | N33: 10.121.15.132_GANDHINAGAR_TN725B_WTR_AM_PH1\S6P1 | O33: 10.121.15.193_Mehsana3(GNE)_TN725B_WTR_AM_PH1\S6P1 | P33: - | Q33: 16 | R33: 25 | T33: Jayesh | V33: 1.0 | W33: 2023/02/09,14:48:21 | X33: 2026/04/18,11:39:31 | Z33: =TRIM(CLEAN(I33)) -> WTR AM-10.121.15.132-Gandhinagar_6/1-10.121.15.193-Mehsana3(GNE)_6/1 | AA33: =SEARCH("_",N33) -> 15 | AB33: =SEARCH("_TN7",N33) -> 27 | AC33: =SEARCH("_",O33) -> 15 | AD33: =SEARCH("_TN7",O33) -> 29 | AE33: =TRIM(CLEAN(MID(N33,1,SEARCH("_",N33)-1))) -> 10.121.15.132 | AF33: =TRIM(CLEAN(MID(O33,1,SEARCH("_",O33)-1))) -> 10.121.15.193 | AG33: =MID(N33,AA33+1,AB33-AA33-1) -> GANDHINAGAR | AH33: =MID(O33,AC33+1,AD33-AC33-1) -> Mehsana3(GNE) | AI33: =RIGHT(N33,LEN(N33)-SEARCH("\",N33)) -> S6P1 | AJ33: =RIGHT(O33,LEN(O33)-SEARCH("\",O33)) -> S6P1 | AK33: =IFERROR(VLOOKUP(Z33,'PASTE-DL-ALARMS'!$Q$10:$W$2200,7,FALSE),"") | AL33: =IFERROR(VLOOKUP(Z33,'PASTE-DL-ALARMS'!$Q$10:$W$2200,3,FALSE),"") | AM33: =CONCATENATE(AE33,"_",AG33,"_",AI33) -> 10.121.15.132_GANDHINAGAR_S6P1 | AN33: =CONCATENATE(AF33,"_",AH33,"_",AJ33) -> 10.121.15.193_Mehsana3(GNE)_S6P1 | AO33: =$AL$3-AK33 -> #VALUE! | AP33: =IFERROR(VLOOKUP(Z33,'PASTE-DL-ALARMS'!$Q$10:$Z$2800,8,FALSE),"")
C34: =IF(D34="Critical",MAX($C$8:C33)+1,"") | D34: =TRIM(CLEAN(P34)) -> - | E34: =VLOOKUP('PASTE-DOWN-DL'!F34,'SSA-CODE'!$D$4:$E$56,2,FALSE) -> SEN | F34: =TRIM(CLEAN(SUBSTITUTE(G34,CHAR(160)," "))) -> SSA SEN | G34: =MID(I34,1,SEARCH("-",I34)-1) -> SSA SEN | H34: 25 | I34: SSA SEN-10.121.99.5-Dhangdhra_4/1-10.121.69.74-Khambhada_3/1 | J34: Fiber | K34: 10GE | L34: Eth | M34: BI-DIR | N34: 10.121.99.5_DHANGDHRA_TN725B_GJ_SSA SEN_PH3\S4P1 | O34: 10.121.69.74_Khambhada_TN705B_WTR_RJ_PH1\S3P1 | P34: - | Q34: 23 | R34: 32 | T34: Rahul | V34: 1.0 | W34: 2020/11/20,16:57:32 | X34: 2026/04/18,11:40:15 | Z34: =TRIM(CLEAN(I34)) -> SSA SEN-10.121.99.5-Dhangdhra_4/1-10.121.69.74-Khambhada_3/1 | AA34: =SEARCH("_",N34) -> 13 | AB34: =SEARCH("_TN7",N34) -> 23 | AC34: =SEARCH("_",O34) -> 14 | AD34: =SEARCH("_TN7",O34) -> 24 | AE34: =TRIM(CLEAN(MID(N34,1,SEARCH("_",N34)-1))) -> 10.121.99.5 | AF34: =TRIM(CLEAN(MID(O34,1,SEARCH("_",O34)-1))) -> 10.121.69.74 | AG34: =MID(N34,AA34+1,AB34-AA34-1) -> DHANGDHRA | AH34: =MID(O34,AC34+1,AD34-AC34-1) -> Khambhada | AI34: =RIGHT(N34,LEN(N34)-SEARCH("\",N34)) -> S4P1 | AJ34: =RIGHT(O34,LEN(O34)-SEARCH("\",O34)) -> S3P1 | AK34: =IFERROR(VLOOKUP(Z34,'PASTE-DL-ALARMS'!$Q$10:$W$2200,7,FALSE),"") | AL34: =IFERROR(VLOOKUP(Z34,'PASTE-DL-ALARMS'!$Q$10:$W$2200,3,FALSE),"") | AM34: =CONCATENATE(AE34,"_",AG34,"_",AI34) -> 10.121.99.5_DHANGDHRA_S4P1 | AN34: =CONCATENATE(AF34,"_",AH34,"_",AJ34) -> 10.121.69.74_Khambhada_S3P1 | AO34: =$AL$3-AK34 -> #VALUE! | AP34: =IFERROR(VLOOKUP(Z34,'PASTE-DL-ALARMS'!$Q$10:$Z$2800,8,FALSE),"")
C35: =IF(D35="Critical",MAX($C$8:C34)+1,"") | D35: =TRIM(CLEAN(P35)) -> - | E35: =VLOOKUP('PASTE-DOWN-DL'!F35,'SSA-CODE'!$D$4:$E$56,2,FALSE) -> VDA | F35: =TRIM(CLEAN(SUBSTITUTE(G35,CHAR(160)," "))) -> SSA VDR | G35: =MID(I35,1,SEARCH("-",I35)-1) -> SSA VDR | H35: 26 | I35: SSA VDR-10.121.19.138-City2_5/8-10.121.99.150-City3_5/8 | J35: Twisted-Pair | K35: GE | L35: Eth | M35: BI-DIR | N35: 10.121.19.138_CITY2_TN725B_GJ_SSA VDR_PH2\S5P8 | O35: 10.121.99.150_CITY 3_TN725B_GJ_SSA VDR_PH3\S5P8 | P35: - | Q35: 97 | R35: 100 | S35: GUJ_GCS_ID_0018854 | T35: 200800788 | U35: VADODARA_SSA | V35: 1.0 | W35: 2022/09/21,15:43:13 | X35: 2026/04/18,11:40:42 | Z35: =TRIM(CLEAN(I35)) -> SSA VDR-10.121.19.138-City2_5/8-10.121.99.150-City3_5/8 | AA35: =SEARCH("_",N35) -> 15 | AB35: =SEARCH("_TN7",N35) -> 21 | AC35: =SEARCH("_",O35) -> 15 | AD35: =SEARCH("_TN7",O35) -> 22 | AE35: =TRIM(CLEAN(MID(N35,1,SEARCH("_",N35)-1))) -> 10.121.19.138 | AF35: =TRIM(CLEAN(MID(O35,1,SEARCH("_",O35)-1))) -> 10.121.99.150 | AG35: =MID(N35,AA35+1,AB35-AA35-1) -> CITY2 | AH35: =MID(O35,AC35+1,AD35-AC35-1) -> CITY 3 | AI35: =RIGHT(N35,LEN(N35)-SEARCH("\",N35)) -> S5P8 | AJ35: =RIGHT(O35,LEN(O35)-SEARCH("\",O35)) -> S5P8 | AK35: =IFERROR(VLOOKUP(Z35,'PASTE-DL-ALARMS'!$Q$10:$W$2200,7,FALSE),"") | AL35: =IFERROR(VLOOKUP(Z35,'PASTE-DL-ALARMS'!$Q$10:$W$2200,3,FALSE),"") | AM35: =CONCATENATE(AE35,"_",AG35,"_",AI35) -> 10.121.19.138_CITY2_S5P8 | AN35: =CONCATENATE(AF35,"_",AH35,"_",AJ35) -> 10.121.99.150_CITY 3_S5P8 | AO35: =$AL$3-AK35 -> #VALUE! | AP35: =IFERROR(VLOOKUP(Z35,'PASTE-DL-ALARMS'!$Q$10:$Z$2800,8,FALSE),"")
C36: =IF(D36="Critical",MAX($C$8:C35)+1,"") | D36: =TRIM(CLEAN(P36)) -> - | E36: =VLOOKUP('PASTE-DOWN-DL'!F36,'SSA-CODE'!$D$4:$E$56,2,FALSE) -> HMR | F36: =TRIM(CLEAN(SUBSTITUTE(G36,CHAR(160)," "))) -> SSA HMR | G36: =MID(I36,1,SEARCH("-",I36)-1) -> SSA HMR | H36: 27 | I36: SSA HMR-10.121.97.80-Raigad_1/5-10.121.25.165-Gambhoi_4/4 | J36: Fiber | K36: GE | L36: Eth | M36: BI-DIR | N36: 10.121.97.80_RAIGAD_TN703B_GJ_SSA HMR_PH3\S1P5 | O36: 10.121.25.165_GAMBHOI_TN705B_GJ_SSA HMR_PH2\S4P4 | P36: - | Q36: 25 | R36: 100 | S36: HMR SSA GCS ID 7684 | T36: 200800716 | U36: HMR SSA | V36: 1.0 | W36: 2020/09/08,12:16:33 | X36: 2026/04/18,11:41:12 | Z36: =TRIM(CLEAN(I36)) -> SSA HMR-10.121.97.80-Raigad_1/5-10.121.25.165-Gambhoi_4/4 | AA36: =SEARCH("_",N36) -> 14 | AB36: =SEARCH("_TN7",N36) -> 21 | AC36: =SEARCH("_",O36) -> 15 | AD36: =SEARCH("_TN7",O36) -> 23 | AE36: =TRIM(CLEAN(MID(N36,1,SEARCH("_",N36)-1))) -> 10.121.97.80 | AF36: =TRIM(CLEAN(MID(O36,1,SEARCH("_",O36)-1))) -> 10.121.25.165 | AG36: =MID(N36,AA36+1,AB36-AA36-1) -> RAIGAD | AH36: =MID(O36,AC36+1,AD36-AC36-1) -> GAMBHOI | AI36: =RIGHT(N36,LEN(N36)-SEARCH("\",N36)) -> S1P5 | AJ36: =RIGHT(O36,LEN(O36)-SEARCH("\",O36)) -> S4P4 | AK36: =IFERROR(VLOOKUP(Z36,'PASTE-DL-ALARMS'!$Q$10:$W$2200,7,FALSE),"") | AL36: =IFERROR(VLOOKUP(Z36,'PASTE-DL-ALARMS'!$Q$10:$W$2200,3,FALSE),"") | AM36: =CONCATENATE(AE36,"_",AG36,"_",AI36) -> 10.121.97.80_RAIGAD_S1P5 | AN36: =CONCATENATE(AF36,"_",AH36,"_",AJ36) -> 10.121.25.165_GAMBHOI_S4P4 | AO36: =$AL$3-AK36 -> #VALUE! | AP36: =IFERROR(VLOOKUP(Z36,'PASTE-DL-ALARMS'!$Q$10:$Z$2800,8,FALSE),"")
C37: =IF(D37="Critical",MAX($C$8:C36)+1,"") -> 1 | D37: =TRIM(CLEAN(P37)) -> Critical | E37: =VLOOKUP('PASTE-DOWN-DL'!F37,'SSA-CODE'!$D$4:$E$56,2,FALSE) -> VAL | F37: =TRIM(CLEAN(SUBSTITUTE(G37,CHAR(160)," "))) -> SSA VAL | G37: =MID(I37,1,SEARCH("-",I37)-1) -> SSA VAL | H37: 28 | I37: SSA VAL-10.121.16.107-KAPRADA_4/3-10.121.24.167-DAPADA_4/2 | J37: Fiber | K37: GE | L37: Eth | M37: BI-DIR | N37: 10.121.16.107_KAPRADA-TE_TN725B_GJ_SSA VAL_PH3\S4P3 | O37: 10.121.24.167_DAPADA_TN705B_GJ_SSA VAL_PH3\S4P2 | P37: Critical | Q37: 18 | R37: 100 | S37: GUJ_VAL_GCSID_61002 | T37: 200300828 | U37: VALSAD SSA | V37: 1.0 | W37: 2026/05/05,18:11:37 | X37: 2026/05/12,17:50:13 | Z37: =TRIM(CLEAN(I37)) -> SSA VAL-10.121.16.107-KAPRADA_4/3-10.121.24.167-DAPADA_4/2 | AA37: =SEARCH("_",N37) -> 15 | AB37: =SEARCH("_TN7",N37) -> 26 | AC37: =SEARCH("_",O37) -> 15 | AD37: =SEARCH("_TN7",O37) -> 22 | AE37: =TRIM(CLEAN(MID(N37,1,SEARCH("_",N37)-1))) -> 10.121.16.107 | AF37: =TRIM(CLEAN(MID(O37,1,SEARCH("_",O37)-1))) -> 10.121.24.167 | AG37: =MID(N37,AA37+1,AB37-AA37-1) -> KAPRADA-TE | AH37: =MID(O37,AC37+1,AD37-AC37-1) -> DAPADA | AI37: =RIGHT(N37,LEN(N37)-SEARCH("\",N37)) -> S4P3 | AJ37: =RIGHT(O37,LEN(O37)-SEARCH("\",O37)) -> S4P2 | AK37: =IFERROR(VLOOKUP(Z37,'PASTE-DL-ALARMS'!$Q$10:$W$2200,7,FALSE),"") -> 15-05-2026 | AL37: =IFERROR(VLOOKUP(Z37,'PASTE-DL-ALARMS'!$Q$10:$W$2200,3,FALSE),"") -> 16:22:47 | AM37: =CONCATENATE(AE37,"_",AG37,"_",AI37) -> 10.121.16.107_KAPRADA-TE_S4P3 | AN37: =CONCATENATE(AF37,"_",AH37,"_",AJ37) -> 10.121.24.167_DAPADA_S4P2 | AO37: =$AL$3-AK37 -> 0 | AP37: =IFERROR(VLOOKUP(Z37,'PASTE-DL-ALARMS'!$Q$10:$Z$2800,8,FALSE),"") -> 2026/05/15,16:22:47
C38: =IF(D38="Critical",MAX($C$8:C37)+1,"") | D38: =TRIM(CLEAN(P38)) -> - | E38: =VLOOKUP('PASTE-DOWN-DL'!F38,'SSA-CODE'!$D$4:$E$56,2,FALSE) -> VDA | F38: =TRIM(CLEAN(SUBSTITUTE(G38,CHAR(160)," "))) -> SSA VDR | G38: =MID(I38,1,SEARCH("-",I38)-1) -> SSA VDR | H38: 29 | I38: SSA VDR-10.121.19.132-Makarpura_4/6-10.121.99.158-MGVCL_Tarsli_1/6 | J38: Fiber | K38: GE | L38: Eth | M38: BI-DIR | N38: 10.121.19.132_MAKARPURA_TN725B_GJ_SSA VDR_PH2\S4P6 | O38: 10.121.99.158_MGVCL TARSLI_TN703B_GJ_SSA VDR_PH3\S1P6 | P38: - | Q38: 6 | R38: 97 | S38: Vadodara SSA GCS ID14252 | T38: 200800716 | U38: Vadodara SSA GCS ID14252 | V38: 1.0 | W38: 2022/01/13,19:35:14 | X38: 2026/04/18,11:46:22 | Z38: =TRIM(CLEAN(I38)) -> SSA VDR-10.121.19.132-Makarpura_4/6-10.121.99.158-MGVCL_Tarsli_1/6 | AA38: =SEARCH("_",N38) -> 15 | AB38: =SEARCH("_TN7",N38) -> 25 | AC38: =SEARCH("_",O38) -> 15 | AD38: =SEARCH("_TN7",O38) -> 28 | AE38: =TRIM(CLEAN(MID(N38,1,SEARCH("_",N38)-1))) -> 10.121.19.132 | AF38: =TRIM(CLEAN(MID(O38,1,SEARCH("_",O38)-1))) -> 10.121.99.158 | AG38: =MID(N38,AA38+1,AB38-AA38-1) -> MAKARPURA | AH38: =MID(O38,AC38+1,AD38-AC38-1) -> MGVCL TARSLI | AI38: =RIGHT(N38,LEN(N38)-SEARCH("\",N38)) -> S4P6 | AJ38: =RIGHT(O38,LEN(O38)-SEARCH("\",O38)) -> S1P6 | AK38: =IFERROR(VLOOKUP(Z38,'PASTE-DL-ALARMS'!$Q$10:$W$2200,7,FALSE),"") | AL38: =IFERROR(VLOOKUP(Z38,'PASTE-DL-ALARMS'!$Q$10:$W$2200,3,FALSE),"") | AM38: =CONCATENATE(AE38,"_",AG38,"_",AI38) -> 10.121.19.132_MAKARPURA_S4P6 | AN38: =CONCATENATE(AF38,"_",AH38,"_",AJ38) -> 10.121.99.158_MGVCL TARSLI_S1P6 | AO38: =$AL$3-AK38 -> #VALUE! | AP38: =IFERROR(VLOOKUP(Z38,'PASTE-DL-ALARMS'!$Q$10:$Z$2800,8,FALSE),"")
C39: =IF(D39="Critical",MAX($C$8:C38)+1,"") | D39: =TRIM(CLEAN(P39)) -> - | E39: =VLOOKUP('PASTE-DOWN-DL'!F39,'SSA-CODE'!$D$4:$E$56,2,FALSE) -> BUJ | F39: =TRIM(CLEAN(SUBSTITUTE(G39,CHAR(160)," "))) -> SSA BUJ | G39: =MID(I39,1,SEARCH("-",I39)-1) -> SSA BUJ | H39: 30 | I39: SSA BUJ-10.121.24.66-Mundra Rd TE_6/3-10.121.17.66-Bhuj2(GNE)_3/4 | J39: Fiber | K39: GE | L39: Eth | M39: BI-DIR | N39: 10.121.24.66_MBM Bhuj B2_TN725B_GJ_SSA BUJ_PH2\S6P3 | O39: 10.121.17.66_BHUJ2(GNE)_TN725B_WTR_RJ_PH1\S3P4 | P39: - | Q39: 91 | R39: 100 | S39: GCS_ID-0014961 | T39: 60070238 | U39: Bhuj_SSA | V39: 1.0 | W39: 2022/02/25,13:59:34 | X39: 2026/04/18,11:46:55 | Z39: =TRIM(CLEAN(I39)) -> SSA BUJ-10.121.24.66-Mundra Rd TE_6/3-10.121.17.66-Bhuj2(GNE)_3/4 | AA39: =SEARCH("_",N39) -> 14 | AB39: =SEARCH("_TN7",N39) -> 26 | AC39: =SEARCH("_",O39) -> 14 | AD39: =SEARCH("_TN7",O39) -> 25 | AE39: =TRIM(CLEAN(MID(N39,1,SEARCH("_",N39)-1))) -> 10.121.24.66 | AF39: =TRIM(CLEAN(MID(O39,1,SEARCH("_",O39)-1))) -> 10.121.17.66 | AG39: =MID(N39,AA39+1,AB39-AA39-1) -> MBM Bhuj B2 | AH39: =MID(O39,AC39+1,AD39-AC39-1) -> BHUJ2(GNE) | AI39: =RIGHT(N39,LEN(N39)-SEARCH("\",N39)) -> S6P3 | AJ39: =RIGHT(O39,LEN(O39)-SEARCH("\",O39)) -> S3P4 | AK39: =IFERROR(VLOOKUP(Z39,'PASTE-DL-ALARMS'!$Q$10:$W$2200,7,FALSE),"") | AL39: =IFERROR(VLOOKUP(Z39,'PASTE-DL-ALARMS'!$Q$10:$W$2200,3,FALSE),"") | AM39: =CONCATENATE(AE39,"_",AG39,"_",AI39) -> 10.121.24.66_MBM Bhuj B2_S6P3 | AN39: =CONCATENATE(AF39,"_",AH39,"_",AJ39) -> 10.121.17.66_BHUJ2(GNE)_S3P4 | AO39: =$AL$3-AK39 -> #VALUE! | AP39: =IFERROR(VLOOKUP(Z39,'PASTE-DL-ALARMS'!$Q$10:$Z$2800,8,FALSE),"")
C40: =IF(D40="Critical",MAX($C$8:C39)+1,"") | D40: =TRIM(CLEAN(P40)) -> - | E40: =VLOOKUP('PASTE-DOWN-DL'!F40,'SSA-CODE'!$D$4:$E$56,2,FALSE) -> BUJ | F40: =TRIM(CLEAN(SUBSTITUTE(G40,CHAR(160)," "))) -> SSA BUJ | G40: =MID(I40,1,SEARCH("-",I40)-1) -> SSA BUJ | H40: 31 | I40: SSA BUJ-10.121.96.165-AIR_Kukma_1/5-10.121.24.69-Kukma_4/2 | J40: Fiber | K40: GE | L40: Eth | M40: BI-DIR | N40: 10.121.96.165_AIR KUKMA_TN703B_GJ_SSA BUJ_PH3\S1P5 | O40: 10.121.24.69_KUKMA_TN705B_GJ_SSA BUJ_PH2\S4P2 | P40: - | Q40: 7 | R40: 88 | S40: GUJ_GCS_ID_0043120 | T40: 200800788 | U40: BHUJ_SSA | V40: 1.0 | W40: 2025/07/12,23:58:05 | X40: 2026/04/18,11:47:30 | Z40: =TRIM(CLEAN(I40)) -> SSA BUJ-10.121.96.165-AIR_Kukma_1/5-10.121.24.69-Kukma_4/2 | AA40: =SEARCH("_",N40) -> 15 | AB40: =SEARCH("_TN7",N40) -> 25 | AC40: =SEARCH("_",O40) -> 14 | AD40: =SEARCH("_TN7",O40) -> 20 | AE40: =TRIM(CLEAN(MID(N40,1,SEARCH("_",N40)-1))) -> 10.121.96.165 | AF40: =TRIM(CLEAN(MID(O40,1,SEARCH("_",O40)-1))) -> 10.121.24.69 | AG40: =MID(N40,AA40+1,AB40-AA40-1) -> AIR KUKMA | AH40: =MID(O40,AC40+1,AD40-AC40-1) -> KUKMA | AI40: =RIGHT(N40,LEN(N40)-SEARCH("\",N40)) -> S1P5 | AJ40: =RIGHT(O40,LEN(O40)-SEARCH("\",O40)) -> S4P2 | AK40: =IFERROR(VLOOKUP(Z40,'PASTE-DL-ALARMS'!$Q$10:$W$2200,7,FALSE),"") | AL40: =IFERROR(VLOOKUP(Z40,'PASTE-DL-ALARMS'!$Q$10:$W$2200,3,FALSE),"") | AM40: =CONCATENATE(AE40,"_",AG40,"_",AI40) -> 10.121.96.165_AIR KUKMA_S1P5 | AN40: =CONCATENATE(AF40,"_",AH40,"_",AJ40) -> 10.121.24.69_KUKMA_S4P2 | AO40: =$AL$3-AK40 -> #VALUE! | AP40: =IFERROR(VLOOKUP(Z40,'PASTE-DL-ALARMS'!$Q$10:$Z$2800,8,FALSE),"")
C41: =IF(D41="Critical",MAX($C$8:C40)+1,"") | D41: =TRIM(CLEAN(P41)) -> - | E41: =VLOOKUP('PASTE-DOWN-DL'!F41,'SSA-CODE'!$D$4:$E$56,2,FALSE) -> AHD | F41: =TRIM(CLEAN(SUBSTITUTE(G41,CHAR(160)," "))) -> SSA AM | G41: =MID(I41,1,SEARCH("-",I41)-1) -> SSA AM | H41: 32 | I41: SSA AM-10.121.18.233-Mahatma_2/5-10.121.18.204-5ESS GNR_3/4 | J41: Fiber | K41: GE | L41: Eth | M41: BI-DIR | N41: 10.121.18.204_5ESS-GNR_TN725B_GJ_SSA AM_PH1\S3P4 | O41: 10.121.18.233_MAHATMA_TN703B_GJ_SSA AM_PH3\S2P5 | P41: - | Q41: 42 | R41: 100 | S41: Ahmedabad SSA GCS ID 25348 | T41: 200800716 | U41: Ahmedabad SSA GCS ID 25348 | V41: 1.0 | W41: 2023/08/26,20:26:05 | X41: 2026/04/18,11:47:59 | Z41: =TRIM(CLEAN(I41)) -> SSA AM-10.121.18.233-Mahatma_2/5-10.121.18.204-5ESS GNR_3/4 | AA41: =SEARCH("_",N41) -> 15 | AB41: =SEARCH("_TN7",N41) -> 24 | AC41: =SEARCH("_",O41) -> 15 | AD41: =SEARCH("_TN7",O41) -> 23 | AE41: =TRIM(CLEAN(MID(N41,1,SEARCH("_",N41)-1))) -> 10.121.18.204 | AF41: =TRIM(CLEAN(MID(O41,1,SEARCH("_",O41)-1))) -> 10.121.18.233 | AG41: =MID(N41,AA41+1,AB41-AA41-1) -> 5ESS-GNR | AH41: =MID(O41,AC41+1,AD41-AC41-1) -> MAHATMA | AI41: =RIGHT(N41,LEN(N41)-SEARCH("\",N41)) -> S3P4 | AJ41: =RIGHT(O41,LEN(O41)-SEARCH("\",O41)) -> S2P5 | AK41: =IFERROR(VLOOKUP(Z41,'PASTE-DL-ALARMS'!$Q$10:$W$2200,7,FALSE),"") | AL41: =IFERROR(VLOOKUP(Z41,'PASTE-DL-ALARMS'!$Q$10:$W$2200,3,FALSE),"") | AM41: =CONCATENATE(AE41,"_",AG41,"_",AI41) -> 10.121.18.204_5ESS-GNR_S3P4 | AN41: =CONCATENATE(AF41,"_",AH41,"_",AJ41) -> 10.121.18.233_MAHATMA_S2P5 | AO41: =$AL$3-AK41 -> #VALUE! | AP41: =IFERROR(VLOOKUP(Z41,'PASTE-DL-ALARMS'!$Q$10:$Z$2800,8,FALSE),"")
C42: =IF(D42="Critical",MAX($C$8:C41)+1,"") | D42: =TRIM(CLEAN(P42)) -> - | E42: =VLOOKUP('PASTE-DOWN-DL'!F42,'SSA-CODE'!$D$4:$E$56,2,FALSE) -> WTR RJ | F42: =TRIM(CLEAN(SUBSTITUTE(G42,CHAR(160)," "))) -> WTR RJ | G42: =MID(I42,1,SEARCH("-",I42)-1) -> WTR RJ | H42: 33 | I42: WTR RJ-10.121.17.66-Bhuj2(GNE)_4/7-10.121.17.65-Bhuj1(GNE)_4/7 | J42: Twisted-Pair | K42: GE | L42: Eth | M42: BI-DIR | N42: 10.121.17.66_BHUJ2(GNE)_TN725B_WTR_RJ_PH1\S4P7 | O42: 10.121.17.65_BHUJ1(GNE)_TN725B_WTR_RJ_PH1\S4P7 | P42: - | Q42: 68 | R42: 100 | T42: 200303555 | V42: 1.0 | W42: 2018/08/21,15:25:10 | X42: 2026/04/18,11:48:32 | Z42: =TRIM(CLEAN(I42)) -> WTR RJ-10.121.17.66-Bhuj2(GNE)_4/7-10.121.17.65-Bhuj1(GNE)_4/7 | AA42: =SEARCH("_",N42) -> 14 | AB42: =SEARCH("_TN7",N42) -> 25 | AC42: =SEARCH("_",O42) -> 14 | AD42: =SEARCH("_TN7",O42) -> 25 | AE42: =TRIM(CLEAN(MID(N42,1,SEARCH("_",N42)-1))) -> 10.121.17.66 | AF42: =TRIM(CLEAN(MID(O42,1,SEARCH("_",O42)-1))) -> 10.121.17.65 | AG42: =MID(N42,AA42+1,AB42-AA42-1) -> BHUJ2(GNE) | AH42: =MID(O42,AC42+1,AD42-AC42-1) -> BHUJ1(GNE) | AI42: =RIGHT(N42,LEN(N42)-SEARCH("\",N42)) -> S4P7 | AJ42: =RIGHT(O42,LEN(O42)-SEARCH("\",O42)) -> S4P7 | AK42: =IFERROR(VLOOKUP(Z42,'PASTE-DL-ALARMS'!$Q$10:$W$2200,7,FALSE),"") | AL42: =IFERROR(VLOOKUP(Z42,'PASTE-DL-ALARMS'!$Q$10:$W$2200,3,FALSE),"") | AM42: =CONCATENATE(AE42,"_",AG42,"_",AI42) -> 10.121.17.66_BHUJ2(GNE)_S4P7 | AN42: =CONCATENATE(AF42,"_",AH42,"_",AJ42) -> 10.121.17.65_BHUJ1(GNE)_S4P7 | AO42: =$AL$3-AK42 -> #VALUE! | AP42: =IFERROR(VLOOKUP(Z42,'PASTE-DL-ALARMS'!$Q$10:$Z$2800,8,FALSE),"")
C43: =IF(D43="Critical",MAX($C$8:C42)+1,"") | D43: =TRIM(CLEAN(P43)) -> - | E43: =VLOOKUP('PASTE-DOWN-DL'!F43,'SSA-CODE'!$D$4:$E$56,2,FALSE) -> GDR | F43: =TRIM(CLEAN(SUBSTITUTE(G43,CHAR(160)," "))) -> SSA GDH | G43: =MID(I43,1,SEARCH("-",I43)-1) -> SSA GDH | H43: 34 | I43: SSA GDH-10.121.19.1-Dahod TE(GNE)_4/5-10.121.19.25-Bhurani_1/5 | J43: Fiber | K43: GE | L43: Eth | M43: BI-DIR | N43: 10.121.19.25_BHURANI_TN703B_GJ_SSA GDH_PH3\S1P5 | O43: 10.121.19.1_Dahod TE(GNE)_TN725B_GJ_SSA GDH_PH2\S4P5 | P43: - | Q43: 46 | R43: 100 | T43: Vikas | V43: 1.0 | W43: 2019/07/03,13:25:11 | X43: 2026/04/18,11:49:16 | Z43: =TRIM(CLEAN(I43)) -> SSA GDH-10.121.19.1-Dahod TE(GNE)_4/5-10.121.19.25-Bhurani_1/5 | AA43: =SEARCH("_",N43) -> 14 | AB43: =SEARCH("_TN7",N43) -> 22 | AC43: =SEARCH("_",O43) -> 13 | AD43: =SEARCH("_TN7",O43) -> 27 | AE43: =TRIM(CLEAN(MID(N43,1,SEARCH("_",N43)-1))) -> 10.121.19.25 | AF43: =TRIM(CLEAN(MID(O43,1,SEARCH("_",O43)-1))) -> 10.121.19.1 | AG43: =MID(N43,AA43+1,AB43-AA43-1) -> BHURANI | AH43: =MID(O43,AC43+1,AD43-AC43-1) -> Dahod TE(GNE) | AI43: =RIGHT(N43,LEN(N43)-SEARCH("\",N43)) -> S1P5 | AJ43: =RIGHT(O43,LEN(O43)-SEARCH("\",O43)) -> S4P5 | AK43: =IFERROR(VLOOKUP(Z43,'PASTE-DL-ALARMS'!$Q$10:$W$2200,7,FALSE),"") | AL43: =IFERROR(VLOOKUP(Z43,'PASTE-DL-ALARMS'!$Q$10:$W$2200,3,FALSE),"") | AM43: =CONCATENATE(AE43,"_",AG43,"_",AI43) -> 10.121.19.25_BHURANI_S1P5 | AN43: =CONCATENATE(AF43,"_",AH43,"_",AJ43) -> 10.121.19.1_Dahod TE(GNE)_S4P5 | AO43: =$AL$3-AK43 -> #VALUE! | AP43: =IFERROR(VLOOKUP(Z43,'PASTE-DL-ALARMS'!$Q$10:$Z$2800,8,FALSE),"")
C44: =IF(D44="Critical",MAX($C$8:C43)+1,"") | D44: =TRIM(CLEAN(P44)) -> - | E44: =VLOOKUP('PASTE-DOWN-DL'!F44,'SSA-CODE'!$D$4:$E$56,2,FALSE) -> AHD | F44: =TRIM(CLEAN(SUBSTITUTE(G44,CHAR(160)," "))) -> SSA AM | G44: =MID(I44,1,SEARCH("-",I44)-1) -> SSA AM | H44: 35 | I44: SSA AM-10.121.18.4-ScienceCity_5/1-10.121.17.198-Naranpura_6/1_10G_Link | J44: Fiber | K44: 10GE | L44: Eth | M44: BI-DIR | N44: 10.121.17.198_NARANPURA_TN725B_GJ_SSA AM_PH1\S6P1 | O44: 10.121.18.4_SCIENCE CITY_TN725B_GJ_SSA AM_PH1\S5P1 | P44: - | Q44: 8 | R44: 17 | T44: minaxikataria | V44: 1.0 | W44: 2019/12/11,17:06:50 | X44: 2026/01/20,13:04:22 | Z44: =TRIM(CLEAN(I44)) -> SSA AM-10.121.18.4-ScienceCity_5/1-10.121.17.198-Naranpura_6/1_10G_Link | AA44: =SEARCH("_",N44) -> 15 | AB44: =SEARCH("_TN7",N44) -> 25 | AC44: =SEARCH("_",O44) -> 13 | AD44: =SEARCH("_TN7",O44) -> 26 | AE44: =TRIM(CLEAN(MID(N44,1,SEARCH("_",N44)-1))) -> 10.121.17.198 | AF44: =TRIM(CLEAN(MID(O44,1,SEARCH("_",O44)-1))) -> 10.121.18.4 | AG44: =MID(N44,AA44+1,AB44-AA44-1) -> NARANPURA | AH44: =MID(O44,AC44+1,AD44-AC44-1) -> SCIENCE CITY | AI44: =RIGHT(N44,LEN(N44)-SEARCH("\",N44)) -> S6P1 | AJ44: =RIGHT(O44,LEN(O44)-SEARCH("\",O44)) -> S5P1 | AK44: =IFERROR(VLOOKUP(Z44,'PASTE-DL-ALARMS'!$Q$10:$W$2200,7,FALSE),"") | AL44: =IFERROR(VLOOKUP(Z44,'PASTE-DL-ALARMS'!$Q$10:$W$2200,3,FALSE),"") | AM44: =CONCATENATE(AE44,"_",AG44,"_",AI44) -> 10.121.17.198_NARANPURA_S6P1 | AN44: =CONCATENATE(AF44,"_",AH44,"_",AJ44) -> 10.121.18.4_SCIENCE CITY_S5P1 | AO44: =$AL$3-AK44 -> #VALUE! | AP44: =IFERROR(VLOOKUP(Z44,'PASTE-DL-ALARMS'!$Q$10:$Z$2800,8,FALSE),"")
C45: =IF(D45="Critical",MAX($C$8:C44)+1,"") | D45: =TRIM(CLEAN(P45)) -> - | E45: =VLOOKUP('PASTE-DOWN-DL'!F45,'SSA-CODE'!$D$4:$E$56,2,FALSE) -> JMN | F45: =TRIM(CLEAN(SUBSTITUTE(G45,CHAR(160)," "))) -> SSA JMN | G45: =MID(I45,1,SEARCH("-",I45)-1) -> SSA JMN | H45: 36 | I45: SSA JMN-10.121.20.36-Sikka 1/5-10.121.97.130-Sikka_3/3 | J45: Fiber | K45: GE | L45: Eth | M45: BI-DIR | N45: 10.121.20.36_SIKKA 2_TN703B_GJ_SSA JMN_PH2\S1P5 | O45: 10.121.97.130_Sikka_TN705B_GJ_SSA JMN_PH3\S3P3 | P45: - | Q45: 5 | R45: 96 | T45: Pawan | V45: 1.0 | W45: 2019/07/25,17:07:44 | X45: 2026/04/18,11:50:31 | Z45: =TRIM(CLEAN(I45)) -> SSA JMN-10.121.20.36-Sikka 1/5-10.121.97.130-Sikka_3/3 | AA45: =SEARCH("_",N45) -> 14 | AB45: =SEARCH("_TN7",N45) -> 22 | AC45: =SEARCH("_",O45) -> 15 | AD45: =SEARCH("_TN7",O45) -> 21 | AE45: =TRIM(CLEAN(MID(N45,1,SEARCH("_",N45)-1))) -> 10.121.20.36 | AF45: =TRIM(CLEAN(MID(O45,1,SEARCH("_",O45)-1))) -> 10.121.97.130 | AG45: =MID(N45,AA45+1,AB45-AA45-1) -> SIKKA 2 | AH45: =MID(O45,AC45+1,AD45-AC45-1) -> Sikka | AI45: =RIGHT(N45,LEN(N45)-SEARCH("\",N45)) -> S1P5 | AJ45: =RIGHT(O45,LEN(O45)-SEARCH("\",O45)) -> S3P3 | AK45: =IFERROR(VLOOKUP(Z45,'PASTE-DL-ALARMS'!$Q$10:$W$2200,7,FALSE),"") | AL45: =IFERROR(VLOOKUP(Z45,'PASTE-DL-ALARMS'!$Q$10:$W$2200,3,FALSE),"") | AM45: =CONCATENATE(AE45,"_",AG45,"_",AI45) -> 10.121.20.36_SIKKA 2_S1P5 | AN45: =CONCATENATE(AF45,"_",AH45,"_",AJ45) -> 10.121.97.130_Sikka_S3P3 | AO45: =$AL$3-AK45 -> #VALUE! | AP45: =IFERROR(VLOOKUP(Z45,'PASTE-DL-ALARMS'!$Q$10:$Z$2800,8,FALSE),"")
C46: =IF(D46="Critical",MAX($C$8:C45)+1,"") | D46: =TRIM(CLEAN(P46)) -> - | E46: =VLOOKUP('PASTE-DOWN-DL'!F46,'SSA-CODE'!$D$4:$E$56,2,FALSE) -> BHV | F46: =TRIM(CLEAN(SUBSTITUTE(G46,CHAR(160)," "))) -> SSA BV | G46: =MID(I46,1,SEARCH("-",I46)-1) -> SSA BV | H46: 37 | I46: SSA BV-10.121.17.184-Tansa_1/5-10.121.17.183-Bhandariya_1/6 | J46: Fiber | K46: GE | L46: Eth | M46: BI-DIR | N46: 10.121.17.184_TANSA_TN703B_GJ_SSA BV_PH3\S1P5 | O46: 10.121.17.183_BHANDARIYA_TN703B_GJ_SSA BV_PH3\S1P6 | P46: - | Q46: 22 | R46: 100 | T46: Pawan | V46: 1.0 | W46: 2019/08/31,12:06:49 | X46: 2026/04/18,11:51:42 | Z46: =TRIM(CLEAN(I46)) -> SSA BV-10.121.17.184-Tansa_1/5-10.121.17.183-Bhandariya_1/6 | AA46: =SEARCH("_",N46) -> 15 | AB46: =SEARCH("_TN7",N46) -> 21 | AC46: =SEARCH("_",O46) -> 15 | AD46: =SEARCH("_TN7",O46) -> 26 | AE46: =TRIM(CLEAN(MID(N46,1,SEARCH("_",N46)-1))) -> 10.121.17.184 | AF46: =TRIM(CLEAN(MID(O46,1,SEARCH("_",O46)-1))) -> 10.121.17.183 | AG46: =MID(N46,AA46+1,AB46-AA46-1) -> TANSA | AH46: =MID(O46,AC46+1,AD46-AC46-1) -> BHANDARIYA | AI46: =RIGHT(N46,LEN(N46)-SEARCH("\",N46)) -> S1P5 | AJ46: =RIGHT(O46,LEN(O46)-SEARCH("\",O46)) -> S1P6 | AK46: =IFERROR(VLOOKUP(Z46,'PASTE-DL-ALARMS'!$Q$10:$W$2200,7,FALSE),"") | AL46: =IFERROR(VLOOKUP(Z46,'PASTE-DL-ALARMS'!$Q$10:$W$2200,3,FALSE),"") | AM46: =CONCATENATE(AE46,"_",AG46,"_",AI46) -> 10.121.17.184_TANSA_S1P5 | AN46: =CONCATENATE(AF46,"_",AH46,"_",AJ46) -> 10.121.17.183_BHANDARIYA_S1P6 | AO46: =$AL$3-AK46 -> #VALUE! | AP46: =IFERROR(VLOOKUP(Z46,'PASTE-DL-ALARMS'!$Q$10:$Z$2800,8,FALSE),"")
C47: =IF(D47="Critical",MAX($C$8:C46)+1,"") | D47: =TRIM(CLEAN(P47)) -> - | E47: =VLOOKUP('PASTE-DOWN-DL'!F47,'SSA-CODE'!$D$4:$E$56,2,FALSE) -> MSN | F47: =TRIM(CLEAN(SUBSTITUTE(G47,CHAR(160)," "))) -> SSA MEH | G47: =MID(I47,1,SEARCH("-",I47)-1) -> SSA MEH | H47: 38 | I47: SSA MEH-10.121.18.161-Madhupura_1/5-10.121.17.209-Railwaypura_6/2 | J47: Fiber | K47: GE | L47: Eth | M47: BI-DIR | N47: 10.121.18.161_Madhupura_TN703B_GJ_SSA AM_PH3\S1P5 | O47: 10.121.17.209_RAILWAYPURA_TN725B_GJ_SSA AM_PH1\S6P2 | P47: - | Q47: 5 | R47: 96 | S47: Guj_Mehsana-SSA_GCS_ID-0022325 | T47: 200700547 | U47: Guj_Mehsana-SSA_GCS_ID-0022325 | V47: 1.0 | W47: 2023/03/18,15:07:37 | X47: 2026/04/18,11:52:04 | Z47: =TRIM(CLEAN(I47)) -> SSA MEH-10.121.18.161-Madhupura_1/5-10.121.17.209-Railwaypura_6/2 | AA47: =SEARCH("_",N47) -> 15 | AB47: =SEARCH("_TN7",N47) -> 25 | AC47: =SEARCH("_",O47) -> 15 | AD47: =SEARCH("_TN7",O47) -> 27 | AE47: =TRIM(CLEAN(MID(N47,1,SEARCH("_",N47)-1))) -> 10.121.18.161 | AF47: =TRIM(CLEAN(MID(O47,1,SEARCH("_",O47)-1))) -> 10.121.17.209 | AG47: =MID(N47,AA47+1,AB47-AA47-1) -> Madhupura | AH47: =MID(O47,AC47+1,AD47-AC47-1) -> RAILWAYPURA | AI47: =RIGHT(N47,LEN(N47)-SEARCH("\",N47)) -> S1P5 | AJ47: =RIGHT(O47,LEN(O47)-SEARCH("\",O47)) -> S6P2 | AK47: =IFERROR(VLOOKUP(Z47,'PASTE-DL-ALARMS'!$Q$10:$W$2200,7,FALSE),"") | AL47: =IFERROR(VLOOKUP(Z47,'PASTE-DL-ALARMS'!$Q$10:$W$2200,3,FALSE),"") | AM47: =CONCATENATE(AE47,"_",AG47,"_",AI47) -> 10.121.18.161_Madhupura_S1P5 | AN47: =CONCATENATE(AF47,"_",AH47,"_",AJ47) -> 10.121.17.209_RAILWAYPURA_S6P2 | AO47: =$AL$3-AK47 -> #VALUE! | AP47: =IFERROR(VLOOKUP(Z47,'PASTE-DL-ALARMS'!$Q$10:$Z$2800,8,FALSE),"")
C48: =IF(D48="Critical",MAX($C$8:C47)+1,"") | D48: =TRIM(CLEAN(P48)) -> - | E48: =VLOOKUP('PASTE-DOWN-DL'!F48,'SSA-CODE'!$D$4:$E$56,2,FALSE) -> WTR AM | F48: =TRIM(CLEAN(SUBSTITUTE(G48,CHAR(160)," "))) -> WTR AM | G48: =MID(I48,1,SEARCH("-",I48)-1) -> WTR AM | H48: 39 | I48: WTR AM-10.121.15.134-Bhadra(GNE)-10.121.15.144-Bhadra_3/7 | J48: Twisted-Pair | K48: GE | L48: Eth | M48: BI-DIR | N48: 10.121.15.144_AM BHADRA(GNE)_TN725B_WTR_AM_PH3\S3P7 | O48: 10.121.15.134_AM-BHADRA_TN725B_WTR_AM_PH1\S3P9 | P48: - | Q48: 80 | R48: 100 | T48: Punit | V48: 1.0 | W48: 2019/04/11,08:27:05 | X48: 2026/04/18,11:54:07 | Z48: =TRIM(CLEAN(I48)) -> WTR AM-10.121.15.134-Bhadra(GNE)-10.121.15.144-Bhadra_3/7 | AA48: =SEARCH("_",N48) -> 15 | AB48: =SEARCH("_TN7",N48) -> 30 | AC48: =SEARCH("_",O48) -> 15 | AD48: =SEARCH("_TN7",O48) -> 25 | AE48: =TRIM(CLEAN(MID(N48,1,SEARCH("_",N48)-1))) -> 10.121.15.144 | AF48: =TRIM(CLEAN(MID(O48,1,SEARCH("_",O48)-1))) -> 10.121.15.134 | AG48: =MID(N48,AA48+1,AB48-AA48-1) -> AM BHADRA(GNE) | AH48: =MID(O48,AC48+1,AD48-AC48-1) -> AM-BHADRA | AI48: =RIGHT(N48,LEN(N48)-SEARCH("\",N48)) -> S3P7 | AJ48: =RIGHT(O48,LEN(O48)-SEARCH("\",O48)) -> S3P9 | AK48: =IFERROR(VLOOKUP(Z48,'PASTE-DL-ALARMS'!$Q$10:$W$2200,7,FALSE),"") | AL48: =IFERROR(VLOOKUP(Z48,'PASTE-DL-ALARMS'!$Q$10:$W$2200,3,FALSE),"") | AM48: =CONCATENATE(AE48,"_",AG48,"_",AI48) -> 10.121.15.144_AM BHADRA(GNE)_S3P7 | AN48: =CONCATENATE(AF48,"_",AH48,"_",AJ48) -> 10.121.15.134_AM-BHADRA_S3P9 | AO48: =$AL$3-AK48 -> #VALUE! | AP48: =IFERROR(VLOOKUP(Z48,'PASTE-DL-ALARMS'!$Q$10:$Z$2800,8,FALSE),"")
C49: =IF(D49="Critical",MAX($C$8:C48)+1,"") | D49: =TRIM(CLEAN(P49)) -> - | E49: =VLOOKUP('PASTE-DOWN-DL'!F49,'SSA-CODE'!$D$4:$E$56,2,FALSE) -> PLR | F49: =TRIM(CLEAN(SUBSTITUTE(G49,CHAR(160)," "))) -> SSA PNP | G49: =MID(I49,1,SEARCH("-",I49)-1) -> SSA PNP | H49: 40 | I49: SSA PNP-10.121.98.137-Malan_3/1-10.121.98.138-Dhandha_4/1 | J49: Fiber | K49: 10GE | L49: Eth | M49: BI-DIR | N49: 10.121.98.137_Malan_TN705B_GJ_SSA PNP_PH2\S3P1 | O49: 10.121.98.138_DHANDHA_TN705B_GJ_SSA PNP_PH2\S4P1 | P49: - | Q49: 3 | R49: 12 | S49: Palanpur_SSA_GCSID_2965 | T49: sporwal | U49: Palanpur_SSA | V49: 1.0 | W49: 2019/07/19,14:58:58 | X49: 2026/04/18,11:55:02 | Z49: =TRIM(CLEAN(I49)) -> SSA PNP-10.121.98.137-Malan_3/1-10.121.98.138-Dhandha_4/1 | AA49: =SEARCH("_",N49) -> 15 | AB49: =SEARCH("_TN7",N49) -> 21 | AC49: =SEARCH("_",O49) -> 15 | AD49: =SEARCH("_TN7",O49) -> 23 | AE49: =TRIM(CLEAN(MID(N49,1,SEARCH("_",N49)-1))) -> 10.121.98.137 | AF49: =TRIM(CLEAN(MID(O49,1,SEARCH("_",O49)-1))) -> 10.121.98.138 | AG49: =MID(N49,AA49+1,AB49-AA49-1) -> Malan | AH49: =MID(O49,AC49+1,AD49-AC49-1) -> DHANDHA | AI49: =RIGHT(N49,LEN(N49)-SEARCH("\",N49)) -> S3P1 | AJ49: =RIGHT(O49,LEN(O49)-SEARCH("\",O49)) -> S4P1 | AK49: =IFERROR(VLOOKUP(Z49,'PASTE-DL-ALARMS'!$Q$10:$W$2200,7,FALSE),"") | AL49: =IFERROR(VLOOKUP(Z49,'PASTE-DL-ALARMS'!$Q$10:$W$2200,3,FALSE),"") | AM49: =CONCATENATE(AE49,"_",AG49,"_",AI49) -> 10.121.98.137_Malan_S3P1 | AN49: =CONCATENATE(AF49,"_",AH49,"_",AJ49) -> 10.121.98.138_DHANDHA_S4P1 | AO49: =$AL$3-AK49 -> #VALUE! | AP49: =IFERROR(VLOOKUP(Z49,'PASTE-DL-ALARMS'!$Q$10:$Z$2800,8,FALSE),"")
C50: =IF(D50="Critical",MAX($C$8:C49)+1,"") | D50: =TRIM(CLEAN(P50)) -> - | E50: =VLOOKUP('PASTE-DOWN-DL'!F50,'SSA-CODE'!$D$4:$E$56,2,FALSE) -> VDA | F50: =TRIM(CLEAN(SUBSTITUTE(G50,CHAR(160)," "))) -> SSA VDR | G50: =MID(I50,1,SEARCH("-",I50)-1) -> SSA VDR | H50: 41 | I50: SSA VDR-10.121.16.16-Karelibaug_3/1-10.121.16.17-Fatehgunj N2_4/1 | J50: Fiber | K50: 10GE | L50: Eth | M50: BI-DIR | N50: 10.121.16.16_KARELIBAUG N2_TN705B_GJ_SSA VDR_PH3\S3P1 | O50: 10.121.16.17_ FATEHGUNJ N2_TN705B_WTR_AM_PH2\S4P1 | P50: - | Q50: 11 | R50: 31 | S50: VADODARA_SSA_GCS_ID_0048212 | T50: 200800788 | U50: VADODARA_SSA_GCS_ID_0048212 | V50: 1.0 | W50: 2026/03/03,14:21:22 | X50: 2026/04/18,12:35:13 | Z50: =TRIM(CLEAN(I50)) -> SSA VDR-10.121.16.16-Karelibaug_3/1-10.121.16.17-Fatehgunj N2_4/1 | AA50: =SEARCH("_",N50) -> 14 | AB50: =SEARCH("_TN7",N50) -> 28 | AC50: =SEARCH("_",O50) -> 14 | AD50: =SEARCH("_TN7",O50) -> 28 | AE50: =TRIM(CLEAN(MID(N50,1,SEARCH("_",N50)-1))) -> 10.121.16.16 | AF50: =TRIM(CLEAN(MID(O50,1,SEARCH("_",O50)-1))) -> 10.121.16.17 | AG50: =MID(N50,AA50+1,AB50-AA50-1) -> KARELIBAUG N2 | AH50: =MID(O50,AC50+1,AD50-AC50-1) -> FATEHGUNJ N2 | AI50: =RIGHT(N50,LEN(N50)-SEARCH("\",N50)) -> S3P1 | AJ50: =RIGHT(O50,LEN(O50)-SEARCH("\",O50)) -> S4P1 | AK50: =IFERROR(VLOOKUP(Z50,'PASTE-DL-ALARMS'!$Q$10:$W$2200,7,FALSE),"") | AL50: =IFERROR(VLOOKUP(Z50,'PASTE-DL-ALARMS'!$Q$10:$W$2200,3,FALSE),"") | AM50: =CONCATENATE(AE50,"_",AG50,"_",AI50) -> 10.121.16.16_KARELIBAUG N2_S3P1 | AN50: =CONCATENATE(AF50,"_",AH50,"_",AJ50) -> 10.121.16.17_ FATEHGUNJ N2_S4P1 | AO50: =$AL$3-AK50 -> #VALUE! | AP50: =IFERROR(VLOOKUP(Z50,'PASTE-DL-ALARMS'!$Q$10:$Z$2800,8,FALSE),"")
C51: =IF(D51="Critical",MAX($C$8:C50)+1,"") | D51: =TRIM(CLEAN(P51)) -> - | E51: =VLOOKUP('PASTE-DOWN-DL'!F51,'SSA-CODE'!$D$4:$E$56,2,FALSE) -> WTR AM | F51: =TRIM(CLEAN(SUBSTITUTE(G51,CHAR(160)," "))) -> WTR AM | G51: =MID(I51,1,SEARCH("-",I51)-1) -> WTR AM | H51: 42 | I51: WTR AM-10.121.15.155-Bagodara_6/1-10.121.15.147-Bavla_4/1 | J51: Fiber | K51: 10GE | L51: Eth | M51: BI-DIR | N51: 10.121.15.155_BAGODARA_TN725B_WTR_AM_PH3\S6P1 | O51: 10.121.15.147_BAVLA_TN725B_WTR_AM_PH2\S4P1 | P51: - | Q51: 16 | R51: 25 | T51: kanishk | V51: 1.0 | W51: 2023/03/31,18:09:43 | X51: 2026/04/18,12:35:35 | Y51: Bavla-Dhandhuka UTL Lemda/2 | Z51: =TRIM(CLEAN(I51)) -> WTR AM-10.121.15.155-Bagodara_6/1-10.121.15.147-Bavla_4/1 | AA51: =SEARCH("_",N51) -> 15 | AB51: =SEARCH("_TN7",N51) -> 24 | AC51: =SEARCH("_",O51) -> 15 | AD51: =SEARCH("_TN7",O51) -> 21 | AE51: =TRIM(CLEAN(MID(N51,1,SEARCH("_",N51)-1))) -> 10.121.15.155 | AF51: =TRIM(CLEAN(MID(O51,1,SEARCH("_",O51)-1))) -> 10.121.15.147 | AG51: =MID(N51,AA51+1,AB51-AA51-1) -> BAGODARA | AH51: =MID(O51,AC51+1,AD51-AC51-1) -> BAVLA | AI51: =RIGHT(N51,LEN(N51)-SEARCH("\",N51)) -> S6P1 | AJ51: =RIGHT(O51,LEN(O51)-SEARCH("\",O51)) -> S4P1 | AK51: =IFERROR(VLOOKUP(Z51,'PASTE-DL-ALARMS'!$Q$10:$W$2200,7,FALSE),"") | AL51: =IFERROR(VLOOKUP(Z51,'PASTE-DL-ALARMS'!$Q$10:$W$2200,3,FALSE),"") | AM51: =CONCATENATE(AE51,"_",AG51,"_",AI51) -> 10.121.15.155_BAGODARA_S6P1 | AN51: =CONCATENATE(AF51,"_",AH51,"_",AJ51) -> 10.121.15.147_BAVLA_S4P1 | AO51: =$AL$3-AK51 -> #VALUE! | AP51: =IFERROR(VLOOKUP(Z51,'PASTE-DL-ALARMS'!$Q$10:$Z$2800,8,FALSE),"")
C52: =IF(D52="Critical",MAX($C$8:C51)+1,"") | D52: =TRIM(CLEAN(P52)) -> - | E52: =VLOOKUP('PASTE-DOWN-DL'!F52,'SSA-CODE'!$D$4:$E$56,2,FALSE) -> AHD | F52: =TRIM(CLEAN(SUBSTITUTE(G52,CHAR(160)," "))) -> SSA AM | G52: =MID(I52,1,SEARCH("-",I52)-1) -> SSA AM | H52: 43 | I52: SSA AM-10.121.18.248-Sector28_4/3-10.121.18.242-FCI_City_1/5 | J52: Fiber | K52: GE | L52: Eth | M52: BI-DIR | N52: 10.121.18.242_FCI CITY_TN703B_GJ_SSA AM_PH2\S1P5 | O52: 10.121.18.248_SECTOR -28_TN725B_GJ_SSA AM_PH3\S4P3 | P52: - | Q52: 1 | R52: 92 | S52: Ahmedabad SSA | T52: minaxikataria | U52: Ahmedabad SSA | V52: 1.0 | W52: 2019/11/19,15:03:42 | X52: 2026/04/18,13:22:22 | Z52: =TRIM(CLEAN(I52)) -> SSA AM-10.121.18.248-Sector28_4/3-10.121.18.242-FCI_City_1/5 | AA52: =SEARCH("_",N52) -> 15 | AB52: =SEARCH("_TN7",N52) -> 24 | AC52: =SEARCH("_",O52) -> 15 | AD52: =SEARCH("_TN7",O52) -> 26 | AE52: =TRIM(CLEAN(MID(N52,1,SEARCH("_",N52)-1))) -> 10.121.18.242 | AF52: =TRIM(CLEAN(MID(O52,1,SEARCH("_",O52)-1))) -> 10.121.18.248 | AG52: =MID(N52,AA52+1,AB52-AA52-1) -> FCI CITY | AH52: =MID(O52,AC52+1,AD52-AC52-1) -> SECTOR -28 | AI52: =RIGHT(N52,LEN(N52)-SEARCH("\",N52)) -> S1P5 | AJ52: =RIGHT(O52,LEN(O52)-SEARCH("\",O52)) -> S4P3 | AK52: =IFERROR(VLOOKUP(Z52,'PASTE-DL-ALARMS'!$Q$10:$W$2200,7,FALSE),"") | AL52: =IFERROR(VLOOKUP(Z52,'PASTE-DL-ALARMS'!$Q$10:$W$2200,3,FALSE),"") | AM52: =CONCATENATE(AE52,"_",AG52,"_",AI52) -> 10.121.18.242_FCI CITY_S1P5 | AN52: =CONCATENATE(AF52,"_",AH52,"_",AJ52) -> 10.121.18.248_SECTOR -28_S4P3 | AO52: =$AL$3-AK52 -> #VALUE! | AP52: =IFERROR(VLOOKUP(Z52,'PASTE-DL-ALARMS'!$Q$10:$Z$2800,8,FALSE),"")
C53: =IF(D53="Critical",MAX($C$8:C52)+1,"") | D53: =TRIM(CLEAN(P53)) -> - | E53: =VLOOKUP('PASTE-DOWN-DL'!F53,'SSA-CODE'!$D$4:$E$56,2,FALSE) -> RJT | F53: =TRIM(CLEAN(SUBSTITUTE(G53,CHAR(160)," "))) -> SSA RJ | G53: =MID(I53,1,SEARCH("-",I53)-1) -> SSA RJ | H53: 44 | I53: SSA RJ-10.121.19.106-PrincePalaceBTS_1/5-10.121.19.74-RaiyaRoad_3/6 | J53: Fiber | K53: GE | L53: Eth | M53: BI-DIR | N53: 10.121.19.106_PrincePalaceBTS_TN703B_GJ_SSA RJ_PH3\S1P5 | O53: 10.121.19.74_RAIYA ROAD_TN725B_GJ_SSA RJ_PH2\S3P6 | P53: - | Q53: 8 | R53: 99 | S53: Rajkot SSA- GCS ID-0011332 | T53: ritesh | U53: Rajkot SSA- | V53: 1.0 | W53: 2021/06/20,08:47:09 | X53: 2026/04/18,13:25:18 | Z53: =TRIM(CLEAN(I53)) -> SSA RJ-10.121.19.106-PrincePalaceBTS_1/5-10.121.19.74-RaiyaRoad_3/6 | AA53: =SEARCH("_",N53) -> 15 | AB53: =SEARCH("_TN7",N53) -> 31 | AC53: =SEARCH("_",O53) -> 14 | AD53: =SEARCH("_TN7",O53) -> 25 | AE53: =TRIM(CLEAN(MID(N53,1,SEARCH("_",N53)-1))) -> 10.121.19.106 | AF53: =TRIM(CLEAN(MID(O53,1,SEARCH("_",O53)-1))) -> 10.121.19.74 | AG53: =MID(N53,AA53+1,AB53-AA53-1) -> PrincePalaceBTS | AH53: =MID(O53,AC53+1,AD53-AC53-1) -> RAIYA ROAD | AI53: =RIGHT(N53,LEN(N53)-SEARCH("\",N53)) -> S1P5 | AJ53: =RIGHT(O53,LEN(O53)-SEARCH("\",O53)) -> S3P6 | AK53: =IFERROR(VLOOKUP(Z53,'PASTE-DL-ALARMS'!$Q$10:$W$2200,7,FALSE),"") | AL53: =IFERROR(VLOOKUP(Z53,'PASTE-DL-ALARMS'!$Q$10:$W$2200,3,FALSE),"") | AM53: =CONCATENATE(AE53,"_",AG53,"_",AI53) -> 10.121.19.106_PrincePalaceBTS_S1P5 | AN53: =CONCATENATE(AF53,"_",AH53,"_",AJ53) -> 10.121.19.74_RAIYA ROAD_S3P6 | AO53: =$AL$3-AK53 -> #VALUE! | AP53: =IFERROR(VLOOKUP(Z53,'PASTE-DL-ALARMS'!$Q$10:$Z$2800,8,FALSE),"")
C54: =IF(D54="Critical",MAX($C$8:C53)+1,"") | D54: =TRIM(CLEAN(P54)) -> - | E54: =VLOOKUP('PASTE-DOWN-DL'!F54,'SSA-CODE'!$D$4:$E$56,2,FALSE) -> AHD | F54: =TRIM(CLEAN(SUBSTITUTE(G54,CHAR(160)," "))) -> SSA AM | G54: =MID(I54,1,SEARCH("-",I54)-1) -> SSA AM | H54: 45 | I54: SSA AM-10.121.18.79-Vejalpur_3/1-10.121.18.77-Brahmshatriya_4/1 | J54: Fiber | K54: 10GE | L54: Eth | M54: BI-DIR | N54: 10.121.18.79_VEJALPUR_TN705B_GJ_SSA AM_PH1\S3P1 | O54: 10.121.18.77_BRAHMSHATRIYA_TN705B_GJ_SSA AM_PH1\S4P1 | P54: - | Q54: 9 | R54: 18 | T54: root | V54: 1.0 | W54: 2018/06/08,12:07:08 | X54: 2026/01/20,17:14:02 | Z54: =TRIM(CLEAN(I54)) -> SSA AM-10.121.18.79-Vejalpur_3/1-10.121.18.77-Brahmshatriya_4/1 | AA54: =SEARCH("_",N54) -> 14 | AB54: =SEARCH("_TN7",N54) -> 23 | AC54: =SEARCH("_",O54) -> 14 | AD54: =SEARCH("_TN7",O54) -> 28 | AE54: =TRIM(CLEAN(MID(N54,1,SEARCH("_",N54)-1))) -> 10.121.18.79 | AF54: =TRIM(CLEAN(MID(O54,1,SEARCH("_",O54)-1))) -> 10.121.18.77 | AG54: =MID(N54,AA54+1,AB54-AA54-1) -> VEJALPUR | AH54: =MID(O54,AC54+1,AD54-AC54-1) -> BRAHMSHATRIYA | AI54: =RIGHT(N54,LEN(N54)-SEARCH("\",N54)) -> S3P1 | AJ54: =RIGHT(O54,LEN(O54)-SEARCH("\",O54)) -> S4P1 | AK54: =IFERROR(VLOOKUP(Z54,'PASTE-DL-ALARMS'!$Q$10:$W$2200,7,FALSE),"") | AL54: =IFERROR(VLOOKUP(Z54,'PASTE-DL-ALARMS'!$Q$10:$W$2200,3,FALSE),"") | AM54: =CONCATENATE(AE54,"_",AG54,"_",AI54) -> 10.121.18.79_VEJALPUR_S3P1 | AN54: =CONCATENATE(AF54,"_",AH54,"_",AJ54) -> 10.121.18.77_BRAHMSHATRIYA_S4P1 | AO54: =$AL$3-AK54 -> #VALUE! | AP54: =IFERROR(VLOOKUP(Z54,'PASTE-DL-ALARMS'!$Q$10:$Z$2800,8,FALSE),"")
C55: =IF(D55="Critical",MAX($C$8:C54)+1,"") | D55: =TRIM(CLEAN(P55)) -> - | E55: =VLOOKUP('PASTE-DOWN-DL'!F55,'SSA-CODE'!$D$4:$E$56,2,FALSE) -> RJT | F55: =TRIM(CLEAN(SUBSTITUTE(G55,CHAR(160)," "))) -> SSA RJ | G55: =MID(I55,1,SEARCH("-",I55)-1) -> SSA RJ | H55: 46 | I55: SSA RJ-10.121.19.66-KR2GNE_3/2-10.121.19.112-Sadguru Vatika BTS1_1/5 | J55: Fiber | K55: GE | L55: Eth | M55: BI-DIR | N55: 10.121.19.66_KR2 GNE_TN725B_GJ_SSA RJ_PH2\S3P2 | O55: 10.121.19.112_Sadguru Vatika BTS1_TN703B_GJ_SSA RJ_PH2\S1P5 | P55: - | Q55: 15 | R55: 100 | S55: Rajkot_SSA_GCS_Id_0008705 | T55: 199105665 | U55: Rajkot_SSA | V55: 1.0 | W55: 2020/11/26,17:02:23 | X55: 2026/04/18,13:26:09 | Z55: =TRIM(CLEAN(I55)) -> SSA RJ-10.121.19.66-KR2GNE_3/2-10.121.19.112-Sadguru Vatika BTS1_1/5 | AA55: =SEARCH("_",N55) -> 14 | AB55: =SEARCH("_TN7",N55) -> 22 | AC55: =SEARCH("_",O55) -> 15 | AD55: =SEARCH("_TN7",O55) -> 35 | AE55: =TRIM(CLEAN(MID(N55,1,SEARCH("_",N55)-1))) -> 10.121.19.66 | AF55: =TRIM(CLEAN(MID(O55,1,SEARCH("_",O55)-1))) -> 10.121.19.112 | AG55: =MID(N55,AA55+1,AB55-AA55-1) -> KR2 GNE | AH55: =MID(O55,AC55+1,AD55-AC55-1) -> Sadguru Vatika BTS1 | AI55: =RIGHT(N55,LEN(N55)-SEARCH("\",N55)) -> S3P2 | AJ55: =RIGHT(O55,LEN(O55)-SEARCH("\",O55)) -> S1P5 | AK55: =IFERROR(VLOOKUP(Z55,'PASTE-DL-ALARMS'!$Q$10:$W$2200,7,FALSE),"") | AL55: =IFERROR(VLOOKUP(Z55,'PASTE-DL-ALARMS'!$Q$10:$W$2200,3,FALSE),"") | AM55: =CONCATENATE(AE55,"_",AG55,"_",AI55) -> 10.121.19.66_KR2 GNE_S3P2 | AN55: =CONCATENATE(AF55,"_",AH55,"_",AJ55) -> 10.121.19.112_Sadguru Vatika BTS1_S1P5 | AO55: =$AL$3-AK55 -> #VALUE! | AP55: =IFERROR(VLOOKUP(Z55,'PASTE-DL-ALARMS'!$Q$10:$Z$2800,8,FALSE),"")
C56: =IF(D56="Critical",MAX($C$8:C55)+1,"") | D56: =TRIM(CLEAN(P56)) -> - | E56: =VLOOKUP('PASTE-DOWN-DL'!F56,'SSA-CODE'!$D$4:$E$56,2,FALSE) -> WTR RJ | F56: =TRIM(CLEAN(SUBSTITUTE(G56,CHAR(160)," "))) -> WTR RJ | G56: =MID(I56,1,SEARCH("-",I56)-1) -> WTR RJ | H56: 47 | I56: WTR RJ-10.121.17.130-Bhavnagar_4/1-10.121.17.131-Sihor_6/1 | J56: Fiber | K56: 10GE | L56: Eth | M56: BI-DIR | N56: 10.121.17.131_SIHOR_TN725B_WTR_RJ_PH1\S6P1 | O56: 10.121.17.130_BHAVNAGAR_TN725B_WTR_RJ_PH1\S4P1 | P56: - | Q56: 12 | R56: 21 | T56: root | V56: 1.0 | W56: 2018/04/28,16:33:32 | X56: 2026/04/18,13:26:44 | Y56: FIBER | Z56: =TRIM(CLEAN(I56)) -> WTR RJ-10.121.17.130-Bhavnagar_4/1-10.121.17.131-Sihor_6/1 | AA56: =SEARCH("_",N56) -> 15 | AB56: =SEARCH("_TN7",N56) -> 21 | AC56: =SEARCH("_",O56) -> 15 | AD56: =SEARCH("_TN7",O56) -> 25 | AE56: =TRIM(CLEAN(MID(N56,1,SEARCH("_",N56)-1))) -> 10.121.17.131 | AF56: =TRIM(CLEAN(MID(O56,1,SEARCH("_",O56)-1))) -> 10.121.17.130 | AG56: =MID(N56,AA56+1,AB56-AA56-1) -> SIHOR | AH56: =MID(O56,AC56+1,AD56-AC56-1) -> BHAVNAGAR | AI56: =RIGHT(N56,LEN(N56)-SEARCH("\",N56)) -> S6P1 | AJ56: =RIGHT(O56,LEN(O56)-SEARCH("\",O56)) -> S4P1 | AK56: =IFERROR(VLOOKUP(Z56,'PASTE-DL-ALARMS'!$Q$10:$W$2200,7,FALSE),"") | AL56: =IFERROR(VLOOKUP(Z56,'PASTE-DL-ALARMS'!$Q$10:$W$2200,3,FALSE),"") | AM56: =CONCATENATE(AE56,"_",AG56,"_",AI56) -> 10.121.17.131_SIHOR_S6P1 | AN56: =CONCATENATE(AF56,"_",AH56,"_",AJ56) -> 10.121.17.130_BHAVNAGAR_S4P1 | AO56: =$AL$3-AK56 -> #VALUE! | AP56: =IFERROR(VLOOKUP(Z56,'PASTE-DL-ALARMS'!$Q$10:$Z$2800,8,FALSE),"")
C57: =IF(D57="Critical",MAX($C$8:C56)+1,"") | D57: =TRIM(CLEAN(P57)) -> - | E57: =VLOOKUP('PASTE-DOWN-DL'!F57,'SSA-CODE'!$D$4:$E$56,2,FALSE) -> WTR RJ | F57: =TRIM(CLEAN(SUBSTITUTE(G57,CHAR(160)," "))) -> WTR RJ | G57: =MID(I57,1,SEARCH("-",I57)-1) -> WTR RJ | H57: 48 | I57: WTR RJ-10.121.17.1-RajkotKR(GNE)_3/3-10.121.17.5-Morbi_3/3 | J57: Fiber | K57: GE | L57: Eth | M57: BI-DIR | N57: 10.121.17.5_MORBI_TN725B_WTR_RJ_PH1\S3P3 | O57: 10.121.17.1_RAJKOT KR(GNE)_TN725B_WTR_RJ_PH1\S3P3 | P57: - | Q57: 54 | R57: 100 | T57: Rahul | V57: 1.0 | W57: 2019/07/31,16:41:44 | X57: 2026/04/18,13:27:17 | Y57: ON RJ-BCU UTL LAMBDA 7/2 | Z57: =TRIM(CLEAN(I57)) -> WTR RJ-10.121.17.1-RajkotKR(GNE)_3/3-10.121.17.5-Morbi_3/3 | AA57: =SEARCH("_",N57) -> 13 | AB57: =SEARCH("_TN7",N57) -> 19 | AC57: =SEARCH("_",O57) -> 13 | AD57: =SEARCH("_TN7",O57) -> 28 | AE57: =TRIM(CLEAN(MID(N57,1,SEARCH("_",N57)-1))) -> 10.121.17.5 | AF57: =TRIM(CLEAN(MID(O57,1,SEARCH("_",O57)-1))) -> 10.121.17.1 | AG57: =MID(N57,AA57+1,AB57-AA57-1) -> MORBI | AH57: =MID(O57,AC57+1,AD57-AC57-1) -> RAJKOT KR(GNE) | AI57: =RIGHT(N57,LEN(N57)-SEARCH("\",N57)) -> S3P3 | AJ57: =RIGHT(O57,LEN(O57)-SEARCH("\",O57)) -> S3P3 | AK57: =IFERROR(VLOOKUP(Z57,'PASTE-DL-ALARMS'!$Q$10:$W$2200,7,FALSE),"") | AL57: =IFERROR(VLOOKUP(Z57,'PASTE-DL-ALARMS'!$Q$10:$W$2200,3,FALSE),"") | AM57: =CONCATENATE(AE57,"_",AG57,"_",AI57) -> 10.121.17.5_MORBI_S3P3 | AN57: =CONCATENATE(AF57,"_",AH57,"_",AJ57) -> 10.121.17.1_RAJKOT KR(GNE)_S3P3 | AO57: =$AL$3-AK57 -> #VALUE! | AP57: =IFERROR(VLOOKUP(Z57,'PASTE-DL-ALARMS'!$Q$10:$Z$2800,8,FALSE),"")
C58: =IF(D58="Critical",MAX($C$8:C57)+1,"") | D58: =TRIM(CLEAN(P58)) -> - | E58: =VLOOKUP('PASTE-DOWN-DL'!F58,'SSA-CODE'!$D$4:$E$56,2,FALSE) -> BUJ | F58: =TRIM(CLEAN(SUBSTITUTE(G58,CHAR(160)," "))) -> SSA BUJ | G58: =MID(I58,1,SEARCH("-",I58)-1) -> SSA BUJ | H58: 49 | I58: SSA BUJ-10.121.96.180-Tera_2/5-10.121.96.181-BITTA_2/5 | J58: Fiber | K58: GE | L58: Eth | M58: BI-DIR | N58: 10.121.96.180_TERA_TN703B_GJ_SSA BUJ_PH3\S2P5 | O58: 10.121.96.181_BITTA_TN703B_GJ_SSA BUJ_PH3\S2P5 | P58: - | Q58: 4 | R58: 95 | S58: Bhuj_SSA_GCS_ID_13765 | T58: 199105665 | U58: Bhuj_SSA | V58: 1.0 | W58: 2021/12/10,17:52:38 | X58: 2026/04/18,13:27:55 | Z58: =TRIM(CLEAN(I58)) -> SSA BUJ-10.121.96.180-Tera_2/5-10.121.96.181-BITTA_2/5 | AA58: =SEARCH("_",N58) -> 15 | AB58: =SEARCH("_TN7",N58) -> 20 | AC58: =SEARCH("_",O58) -> 15 | AD58: =SEARCH("_TN7",O58) -> 21 | AE58: =TRIM(CLEAN(MID(N58,1,SEARCH("_",N58)-1))) -> 10.121.96.180 | AF58: =TRIM(CLEAN(MID(O58,1,SEARCH("_",O58)-1))) -> 10.121.96.181 | AG58: =MID(N58,AA58+1,AB58-AA58-1) -> TERA | AH58: =MID(O58,AC58+1,AD58-AC58-1) -> BITTA | AI58: =RIGHT(N58,LEN(N58)-SEARCH("\",N58)) -> S2P5 | AJ58: =RIGHT(O58,LEN(O58)-SEARCH("\",O58)) -> S2P5 | AK58: =IFERROR(VLOOKUP(Z58,'PASTE-DL-ALARMS'!$Q$10:$W$2200,7,FALSE),"") | AL58: =IFERROR(VLOOKUP(Z58,'PASTE-DL-ALARMS'!$Q$10:$W$2200,3,FALSE),"") | AM58: =CONCATENATE(AE58,"_",AG58,"_",AI58) -> 10.121.96.180_TERA_S2P5 | AN58: =CONCATENATE(AF58,"_",AH58,"_",AJ58) -> 10.121.96.181_BITTA_S2P5 | AO58: =$AL$3-AK58 -> #VALUE! | AP58: =IFERROR(VLOOKUP(Z58,'PASTE-DL-ALARMS'!$Q$10:$Z$2800,8,FALSE),"")
C59: =IF(D59="Critical",MAX($C$8:C58)+1,"") | D59: =TRIM(CLEAN(P59)) -> - | E59: =VLOOKUP('PASTE-DOWN-DL'!F59,'SSA-CODE'!$D$4:$E$56,2,FALSE) -> SRT | F59: =TRIM(CLEAN(SUBSTITUTE(G59,CHAR(160)," "))) -> SSA SR | G59: =MID(I59,1,SEARCH("-",I59)-1) -> SSA SR | H59: 50 | I59: SSA SR-10.121.100.22-Nizer_4/1-to-10.121.100.21-Uchhal_4/1 | J59: Fiber | K59: 10GE | L59: Eth | M59: BI-DIR | N59: 10.121.100.22_NIZER_TN705B_GJ_SSA SR_PH3\S4P1 | O59: 10.121.100.21_UCHHAL_TN705B_GJ_SSA SR_PH3\S4P1 | P59: - | Q59: 7 | R59: 16 | S59: GCS-47802 | T59: 200800474 | U59: GCS-47802 | V59: 1.0 | W59: 2026/01/03,20:37:50 | X59: 2026/04/18,13:30:28 | Z59: =TRIM(CLEAN(I59)) -> SSA SR-10.121.100.22-Nizer_4/1-to-10.121.100.21-Uchhal_4/1 | AA59: =SEARCH("_",N59) -> 15 | AB59: =SEARCH("_TN7",N59) -> 21 | AC59: =SEARCH("_",O59) -> 15 | AD59: =SEARCH("_TN7",O59) -> 22 | AE59: =TRIM(CLEAN(MID(N59,1,SEARCH("_",N59)-1))) -> 10.121.100.22 | AF59: =TRIM(CLEAN(MID(O59,1,SEARCH("_",O59)-1))) -> 10.121.100.21 | AG59: =MID(N59,AA59+1,AB59-AA59-1) -> NIZER | AH59: =MID(O59,AC59+1,AD59-AC59-1) -> UCHHAL | AI59: =RIGHT(N59,LEN(N59)-SEARCH("\",N59)) -> S4P1 | AJ59: =RIGHT(O59,LEN(O59)-SEARCH("\",O59)) -> S4P1 | AK59: =IFERROR(VLOOKUP(Z59,'PASTE-DL-ALARMS'!$Q$10:$W$2200,7,FALSE),"") | AL59: =IFERROR(VLOOKUP(Z59,'PASTE-DL-ALARMS'!$Q$10:$W$2200,3,FALSE),"") | AM59: =CONCATENATE(AE59,"_",AG59,"_",AI59) -> 10.121.100.22_NIZER_S4P1 | AN59: =CONCATENATE(AF59,"_",AH59,"_",AJ59) -> 10.121.100.21_UCHHAL_S4P1 | AO59: =$AL$3-AK59 -> #VALUE! | AP59: =IFERROR(VLOOKUP(Z59,'PASTE-DL-ALARMS'!$Q$10:$Z$2800,8,FALSE),"")
C60: =IF(D60="Critical",MAX($C$8:C59)+1,"") | D60: =TRIM(CLEAN(P60)) -> - | E60: =VLOOKUP('PASTE-DOWN-DL'!F60,'SSA-CODE'!$D$4:$E$56,2,FALSE) -> WTR RJ | F60: =TRIM(CLEAN(SUBSTITUTE(G60,CHAR(160)," "))) -> WTR RJ | G60: =MID(I60,1,SEARCH("-",I60)-1) -> WTR RJ | H60: 51 | I60: WTR RJ-10.121.17.5-Morbi_5/2-10.121.17.26-Rajkot_6/3 | J60: Fiber | K60: GE | L60: Eth | M60: BI-DIR | N60: 10.121.17.26_RAJKOT_TN725B_WTR_RJ_PH1\S6P3 | O60: 10.121.17.5_MORBI_TN725B_WTR_RJ_PH1\S5P2 | P60: - | Q60: 68 | R60: 100 | S60: GCS ID no. 030949 | T60: 200700547 | U60: Rajkot | V60: 1.0 | W60: 2024/05/17,18:48:11 | X60: 2026/04/18,13:32:30 | Z60: =TRIM(CLEAN(I60)) -> WTR RJ-10.121.17.5-Morbi_5/2-10.121.17.26-Rajkot_6/3 | AA60: =SEARCH("_",N60) -> 14 | AB60: =SEARCH("_TN7",N60) -> 21 | AC60: =SEARCH("_",O60) -> 13 | AD60: =SEARCH("_TN7",O60) -> 19 | AE60: =TRIM(CLEAN(MID(N60,1,SEARCH("_",N60)-1))) -> 10.121.17.26 | AF60: =TRIM(CLEAN(MID(O60,1,SEARCH("_",O60)-1))) -> 10.121.17.5 | AG60: =MID(N60,AA60+1,AB60-AA60-1) -> RAJKOT | AH60: =MID(O60,AC60+1,AD60-AC60-1) -> MORBI | AI60: =RIGHT(N60,LEN(N60)-SEARCH("\",N60)) -> S6P3 | AJ60: =RIGHT(O60,LEN(O60)-SEARCH("\",O60)) -> S5P2 | AK60: =IFERROR(VLOOKUP(Z60,'PASTE-DL-ALARMS'!$Q$10:$W$2200,7,FALSE),"") | AL60: =IFERROR(VLOOKUP(Z60,'PASTE-DL-ALARMS'!$Q$10:$W$2200,3,FALSE),"") | AM60: =CONCATENATE(AE60,"_",AG60,"_",AI60) -> 10.121.17.26_RAJKOT_S6P3 | AN60: =CONCATENATE(AF60,"_",AH60,"_",AJ60) -> 10.121.17.5_MORBI_S5P2 | AO60: =$AL$3-AK60 -> #VALUE! | AP60: =IFERROR(VLOOKUP(Z60,'PASTE-DL-ALARMS'!$Q$10:$Z$2800,8,FALSE),"")
C61: =IF(D61="Critical",MAX($C$8:C60)+1,"") | D61: =TRIM(CLEAN(P61)) -> - | E61: =VLOOKUP('PASTE-DOWN-DL'!F61,'SSA-CODE'!$D$4:$E$56,2,FALSE) -> NDD | F61: =TRIM(CLEAN(SUBSTITUTE(G61,CHAR(160)," "))) -> SSA NAD | G61: =MID(I61,1,SEARCH("-",I61)-1) -> SSA NAD | H61: 52 | I61: SSA NAD-10.121.16.132-Nadiad_4/9-10.121.16.243-Nadiad Micro_4/9 | J61: Twisted-Pair | K61: GE | L61: Eth | M61: BI-DIR | N61: 10.121.16.132_Nadiad_TN725B_WTR_AM_PH1\S4P9 | O61: 10.121.16.243_Nadiad Micro_TN705B_WTR_AM_PH3\S4P9 | P61: - | Q61: 40 | R61: 100 | S61: GCS_ID-0038223 | T61: 60070238 | U61: Nadiad_SSA | V61: 1.0 | W61: 2025/01/23,19:57:16 | X61: 2026/04/18,13:33:36 | Z61: =TRIM(CLEAN(I61)) -> SSA NAD-10.121.16.132-Nadiad_4/9-10.121.16.243-Nadiad Micro_4/9 | AA61: =SEARCH("_",N61) -> 15 | AB61: =SEARCH("_TN7",N61) -> 22 | AC61: =SEARCH("_",O61) -> 15 | AD61: =SEARCH("_TN7",O61) -> 28 | AE61: =TRIM(CLEAN(MID(N61,1,SEARCH("_",N61)-1))) -> 10.121.16.132 | AF61: =TRIM(CLEAN(MID(O61,1,SEARCH("_",O61)-1))) -> 10.121.16.243 | AG61: =MID(N61,AA61+1,AB61-AA61-1) -> Nadiad | AH61: =MID(O61,AC61+1,AD61-AC61-1) -> Nadiad Micro | AI61: =RIGHT(N61,LEN(N61)-SEARCH("\",N61)) -> S4P9 | AJ61: =RIGHT(O61,LEN(O61)-SEARCH("\",O61)) -> S4P9 | AK61: =IFERROR(VLOOKUP(Z61,'PASTE-DL-ALARMS'!$Q$10:$W$2200,7,FALSE),"") | AL61: =IFERROR(VLOOKUP(Z61,'PASTE-DL-ALARMS'!$Q$10:$W$2200,3,FALSE),"") | AM61: =CONCATENATE(AE61,"_",AG61,"_",AI61) -> 10.121.16.132_Nadiad_S4P9 | AN61: =CONCATENATE(AF61,"_",AH61,"_",AJ61) -> 10.121.16.243_Nadiad Micro_S4P9 | AO61: =$AL$3-AK61 -> #VALUE! | AP61: =IFERROR(VLOOKUP(Z61,'PASTE-DL-ALARMS'!$Q$10:$Z$2800,8,FALSE),"")
C62: =IF(D62="Critical",MAX($C$8:C61)+1,"") | D62: =TRIM(CLEAN(P62)) -> - | E62: =VLOOKUP('PASTE-DOWN-DL'!F62,'SSA-CODE'!$D$4:$E$56,2,FALSE) -> BUJ | F62: =TRIM(CLEAN(SUBSTITUTE(G62,CHAR(160)," "))) -> SSA BUJ | G62: =MID(I62,1,SEARCH("-",I62)-1) -> SSA BUJ | H62: 53 | I62: SSA BUJ-10.121.24.74-Adipur_4/3-10.121.24.122-Polytechnic BTS_1/5 | J62: Fiber | K62: GE | L62: Eth | M62: BI-DIR | N62: 10.121.24.74_Adipur_TN725B_GJ_SSA BUJ_PH3\S4P3 | O62: 10.121.24.122_Polytechnic BTS_TN703B_GJ_SSA BUJ_PH2\S1P5 | P62: - | Q62: 4 | R62: 95 | T62: bhalchandra | V62: 1.0 | W62: 2018/12/06,11:15:39 | X62: 2026/04/18,13:34:17 | Z62: =TRIM(CLEAN(I62)) -> SSA BUJ-10.121.24.74-Adipur_4/3-10.121.24.122-Polytechnic BTS_1/5 | AA62: =SEARCH("_",N62) -> 14 | AB62: =SEARCH("_TN7",N62) -> 21 | AC62: =SEARCH("_",O62) -> 15 | AD62: =SEARCH("_TN7",O62) -> 31 | AE62: =TRIM(CLEAN(MID(N62,1,SEARCH("_",N62)-1))) -> 10.121.24.74 | AF62: =TRIM(CLEAN(MID(O62,1,SEARCH("_",O62)-1))) -> 10.121.24.122 | AG62: =MID(N62,AA62+1,AB62-AA62-1) -> Adipur | AH62: =MID(O62,AC62+1,AD62-AC62-1) -> Polytechnic BTS | AI62: =RIGHT(N62,LEN(N62)-SEARCH("\",N62)) -> S4P3 | AJ62: =RIGHT(O62,LEN(O62)-SEARCH("\",O62)) -> S1P5 | AK62: =IFERROR(VLOOKUP(Z62,'PASTE-DL-ALARMS'!$Q$10:$W$2200,7,FALSE),"") | AL62: =IFERROR(VLOOKUP(Z62,'PASTE-DL-ALARMS'!$Q$10:$W$2200,3,FALSE),"") | AM62: =CONCATENATE(AE62,"_",AG62,"_",AI62) -> 10.121.24.74_Adipur_S4P3 | AN62: =CONCATENATE(AF62,"_",AH62,"_",AJ62) -> 10.121.24.122_Polytechnic BTS_S1P5 | AO62: =$AL$3-AK62 -> #VALUE! | AP62: =IFERROR(VLOOKUP(Z62,'PASTE-DL-ALARMS'!$Q$10:$Z$2800,8,FALSE),"")
C63: =IF(D63="Critical",MAX($C$8:C62)+1,"") | D63: =TRIM(CLEAN(P63)) -> - | E63: =VLOOKUP('PASTE-DOWN-DL'!F63,'SSA-CODE'!$D$4:$E$56,2,FALSE) -> MSN | F63: =TRIM(CLEAN(SUBSTITUTE(G63,CHAR(160)," "))) -> SSA MEH | G63: =MID(I63,1,SEARCH("-",I63)-1) -> SSA MEH | H63: 54 | I63: SSA MEH-10.121.25.71-Nandasan Exch_3/1-10.121.98.1-Kadi Ex_4/1 | J63: Fiber | K63: 10GE | L63: Eth | M63: BI-DIR | N63: 10.121.98.1_KADI EX_TN705B_GJ_SSA MEH_PH3\S4P1 | O63: 10.121.25.71_NANDASAN EXCH_TN705B_GJ_SSA MEH_PH2\S3P1 | P63: - | Q63: 23 | R63: 32 | T63: bhalchandra | V63: 1.0 | W63: 2019/09/18,16:56:05 | X63: 2026/04/18,13:34:45 | Z63: =TRIM(CLEAN(I63)) -> SSA MEH-10.121.25.71-Nandasan Exch_3/1-10.121.98.1-Kadi Ex_4/1 | AA63: =SEARCH("_",N63) -> 13 | AB63: =SEARCH("_TN7",N63) -> 21 | AC63: =SEARCH("_",O63) -> 14 | AD63: =SEARCH("_TN7",O63) -> 28 | AE63: =TRIM(CLEAN(MID(N63,1,SEARCH("_",N63)-1))) -> 10.121.98.1 | AF63: =TRIM(CLEAN(MID(O63,1,SEARCH("_",O63)-1))) -> 10.121.25.71 | AG63: =MID(N63,AA63+1,AB63-AA63-1) -> KADI EX | AH63: =MID(O63,AC63+1,AD63-AC63-1) -> NANDASAN EXCH | AI63: =RIGHT(N63,LEN(N63)-SEARCH("\",N63)) -> S4P1 | AJ63: =RIGHT(O63,LEN(O63)-SEARCH("\",O63)) -> S3P1 | AK63: =IFERROR(VLOOKUP(Z63,'PASTE-DL-ALARMS'!$Q$10:$W$2200,7,FALSE),"") | AL63: =IFERROR(VLOOKUP(Z63,'PASTE-DL-ALARMS'!$Q$10:$W$2200,3,FALSE),"") | AM63: =CONCATENATE(AE63,"_",AG63,"_",AI63) -> 10.121.98.1_KADI EX_S4P1 | AN63: =CONCATENATE(AF63,"_",AH63,"_",AJ63) -> 10.121.25.71_NANDASAN EXCH_S3P1 | AO63: =$AL$3-AK63 -> #VALUE! | AP63: =IFERROR(VLOOKUP(Z63,'PASTE-DL-ALARMS'!$Q$10:$Z$2800,8,FALSE),"")
C64: =IF(D64="Critical",MAX($C$8:C63)+1,"") | D64: =TRIM(CLEAN(P64)) -> - | E64: =VLOOKUP('PASTE-DOWN-DL'!F64,'SSA-CODE'!$D$4:$E$56,2,FALSE) -> AMR | F64: =TRIM(CLEAN(SUBSTITUTE(G64,CHAR(160)," "))) -> SSA AMR | G64: =MID(I64,1,SEARCH("-",I64)-1) -> SSA AMR | H64: 55 | I64: SSA AMR-10.121.96.56-Amreli(GNE)_3/3-10.121.96.46-Royal Complex BTS_2/6 | J64: Fiber | K64: GE | L64: Eth | M64: BI-DIR | N64: 10.121.96.56_Amreli GNE_TN725B_GJ_SSA AMR_PH2\S3P3 | O64: 10.121.96.46_Royal Complex BTS_TN703B_GJ_SSA AMR_PH2\S2P6 | P64: - | Q64: 19 | R64: 100 | S64: Amreli_SSA_GCS_ID_0006872 | T64: 199105665 | U64: Amreli-SSA | V64: 1.0 | W64: 2020/07/20,12:07:26 | X64: 2026/04/21,12:01:16 | Z64: =TRIM(CLEAN(I64)) -> SSA AMR-10.121.96.56-Amreli(GNE)_3/3-10.121.96.46-Royal Complex BTS_2/6 | AA64: =SEARCH("_",N64) -> 14 | AB64: =SEARCH("_TN7",N64) -> 25 | AC64: =SEARCH("_",O64) -> 14 | AD64: =SEARCH("_TN7",O64) -> 32 | AE64: =TRIM(CLEAN(MID(N64,1,SEARCH("_",N64)-1))) -> 10.121.96.56 | AF64: =TRIM(CLEAN(MID(O64,1,SEARCH("_",O64)-1))) -> 10.121.96.46 | AG64: =MID(N64,AA64+1,AB64-AA64-1) -> Amreli GNE | AH64: =MID(O64,AC64+1,AD64-AC64-1) -> Royal Complex BTS | AI64: =RIGHT(N64,LEN(N64)-SEARCH("\",N64)) -> S3P3 | AJ64: =RIGHT(O64,LEN(O64)-SEARCH("\",O64)) -> S2P6 | AK64: =IFERROR(VLOOKUP(Z64,'PASTE-DL-ALARMS'!$Q$10:$W$2200,7,FALSE),"") | AL64: =IFERROR(VLOOKUP(Z64,'PASTE-DL-ALARMS'!$Q$10:$W$2200,3,FALSE),"") | AM64: =CONCATENATE(AE64,"_",AG64,"_",AI64) -> 10.121.96.56_Amreli GNE_S3P3 | AN64: =CONCATENATE(AF64,"_",AH64,"_",AJ64) -> 10.121.96.46_Royal Complex BTS_S2P6 | AO64: =$AL$3-AK64 -> #VALUE! | AP64: =IFERROR(VLOOKUP(Z64,'PASTE-DL-ALARMS'!$Q$10:$Z$2800,8,FALSE),"")
C65: =IF(D65="Critical",MAX($C$8:C64)+1,"") | D65: =TRIM(CLEAN(P65)) -> - | E65: =VLOOKUP('PASTE-DOWN-DL'!F65,'SSA-CODE'!$D$4:$E$56,2,FALSE) -> JMN | F65: =TRIM(CLEAN(SUBSTITUTE(G65,CHAR(160)," "))) -> SSA JMN | G65: =MID(I65,1,SEARCH("-",I65)-1) -> SSA JMN | H65: 56 | I65: SSA JMN-10.121.20.58-Sbi Ranjit Road_2/5-10.121.97.150-DeepakShoppingBTS_2/6 | J65: Fiber | K65: GE | L65: Eth | M65: BI-DIR | N65: 10.121.20.58_SBI RANJIT ROAD_TN703B_GJ_SSA JMN_PH2\S2P5 | O65: 10.121.97.150_DEEPAK SHOPPING BTS_TN703B_GJ_SSA JMN_PH3\S2P6 | P65: - | Q65: 8 | R65: 99 | S65: Jamnagar SSA | T65: minaxikataria | U65: Jmanagar SSA | V65: 1.0 | W65: 2021/07/10,11:29:29 | X65: 2026/04/21,11:58:11 | Z65: =TRIM(CLEAN(I65)) -> SSA JMN-10.121.20.58-Sbi Ranjit Road_2/5-10.121.97.150-DeepakShoppingBTS_2/6 | AA65: =SEARCH("_",N65) -> 14 | AB65: =SEARCH("_TN7",N65) -> 30 | AC65: =SEARCH("_",O65) -> 15 | AD65: =SEARCH("_TN7",O65) -> 35 | AE65: =TRIM(CLEAN(MID(N65,1,SEARCH("_",N65)-1))) -> 10.121.20.58 | AF65: =TRIM(CLEAN(MID(O65,1,SEARCH("_",O65)-1))) -> 10.121.97.150 | AG65: =MID(N65,AA65+1,AB65-AA65-1) -> SBI RANJIT ROAD | AH65: =MID(O65,AC65+1,AD65-AC65-1) -> DEEPAK SHOPPING BTS | AI65: =RIGHT(N65,LEN(N65)-SEARCH("\",N65)) -> S2P5 | AJ65: =RIGHT(O65,LEN(O65)-SEARCH("\",O65)) -> S2P6 | AK65: =IFERROR(VLOOKUP(Z65,'PASTE-DL-ALARMS'!$Q$10:$W$2200,7,FALSE),"") | AL65: =IFERROR(VLOOKUP(Z65,'PASTE-DL-ALARMS'!$Q$10:$W$2200,3,FALSE),"") | AM65: =CONCATENATE(AE65,"_",AG65,"_",AI65) -> 10.121.20.58_SBI RANJIT ROAD_S2P5 | AN65: =CONCATENATE(AF65,"_",AH65,"_",AJ65) -> 10.121.97.150_DEEPAK SHOPPING BTS_S2P6 | AO65: =$AL$3-AK65 -> #VALUE! | AP65: =IFERROR(VLOOKUP(Z65,'PASTE-DL-ALARMS'!$Q$10:$Z$2800,8,FALSE),"")
C66: =IF(D66="Critical",MAX($C$8:C65)+1,"") | D66: =TRIM(CLEAN(P66)) -> - | E66: =VLOOKUP('PASTE-DOWN-DL'!F66,'SSA-CODE'!$D$4:$E$56,2,FALSE) -> AHD | F66: =TRIM(CLEAN(SUBSTITUTE(G66,CHAR(160)," "))) -> SSA AM | G66: =MID(I66,1,SEARCH("-",I66)-1) -> SSA AM | H66: 57 | I66: SSA AM-10.121.18.21-HighCourt_4/2-10.121.18.4-ScienceCity_4/2 | J66: Fiber | K66: GE | L66: Eth | M66: BI-DIR | N66: 10.121.18.4_SCIENCE CITY_TN725B_GJ_SSA AM_PH1\S4P2 | O66: 10.121.18.21_HighCourt_TN705B_GJ_SSA AM_PH3\S4P2 | P66: - | Q66: 35 | R66: 100 | S66: Ahmedabad SSA | T66: minaxikataria | U66: Ahmedabad SSA | V66: 1.0 | W66: 2020/07/28,15:15:00 | X66: 2026/01/20,14:40:19 | Z66: =TRIM(CLEAN(I66)) -> SSA AM-10.121.18.21-HighCourt_4/2-10.121.18.4-ScienceCity_4/2 | AA66: =SEARCH("_",N66) -> 13 | AB66: =SEARCH("_TN7",N66) -> 26 | AC66: =SEARCH("_",O66) -> 14 | AD66: =SEARCH("_TN7",O66) -> 24 | AE66: =TRIM(CLEAN(MID(N66,1,SEARCH("_",N66)-1))) -> 10.121.18.4 | AF66: =TRIM(CLEAN(MID(O66,1,SEARCH("_",O66)-1))) -> 10.121.18.21 | AG66: =MID(N66,AA66+1,AB66-AA66-1) -> SCIENCE CITY | AH66: =MID(O66,AC66+1,AD66-AC66-1) -> HighCourt | AI66: =RIGHT(N66,LEN(N66)-SEARCH("\",N66)) -> S4P2 | AJ66: =RIGHT(O66,LEN(O66)-SEARCH("\",O66)) -> S4P2 | AK66: =IFERROR(VLOOKUP(Z66,'PASTE-DL-ALARMS'!$Q$10:$W$2200,7,FALSE),"") | AL66: =IFERROR(VLOOKUP(Z66,'PASTE-DL-ALARMS'!$Q$10:$W$2200,3,FALSE),"") | AM66: =CONCATENATE(AE66,"_",AG66,"_",AI66) -> 10.121.18.4_SCIENCE CITY_S4P2 | AN66: =CONCATENATE(AF66,"_",AH66,"_",AJ66) -> 10.121.18.21_HighCourt_S4P2 | AO66: =$AL$3-AK66 -> #VALUE! | AP66: =IFERROR(VLOOKUP(Z66,'PASTE-DL-ALARMS'!$Q$10:$Z$2800,8,FALSE),"")
C67: =IF(D67="Critical",MAX($C$8:C66)+1,"") | D67: =TRIM(CLEAN(P67)) -> - | E67: =VLOOKUP('PASTE-DOWN-DL'!F67,'SSA-CODE'!$D$4:$E$56,2,FALSE) -> WTR RJ | F67: =TRIM(CLEAN(SUBSTITUTE(G67,CHAR(160)," "))) -> WTR RJ | G67: =MID(I67,1,SEARCH("-",I67)-1) -> WTR RJ | H67: 58 | I67: WTR RJ-10.121.17.27-Rajkot KR_3/2-10.121.17.26-Rajkot_3/2 | J67: Fiber | K67: GE | L67: Eth | M67: BI-DIR | N67: 10.121.17.26_RAJKOT_TN725B_WTR_RJ_PH1\S3P2 | O67: 10.121.17.27_RAJKOT KR_TN725B_WTR_RJ_PH3\S3P2 | P67: - | Q67: 43 | R67: 100 | T67: 201300343 | V67: 1.0 | W67: 2023/11/02,16:53:46 | X67: 2026/04/21,11:58:51 | Y67: DARK FIBER | Z67: =TRIM(CLEAN(I67)) -> WTR RJ-10.121.17.27-Rajkot KR_3/2-10.121.17.26-Rajkot_3/2 | AA67: =SEARCH("_",N67) -> 14 | AB67: =SEARCH("_TN7",N67) -> 21 | AC67: =SEARCH("_",O67) -> 14 | AD67: =SEARCH("_TN7",O67) -> 24 | AE67: =TRIM(CLEAN(MID(N67,1,SEARCH("_",N67)-1))) -> 10.121.17.26 | AF67: =TRIM(CLEAN(MID(O67,1,SEARCH("_",O67)-1))) -> 10.121.17.27 | AG67: =MID(N67,AA67+1,AB67-AA67-1) -> RAJKOT | AH67: =MID(O67,AC67+1,AD67-AC67-1) -> RAJKOT KR | AI67: =RIGHT(N67,LEN(N67)-SEARCH("\",N67)) -> S3P2 | AJ67: =RIGHT(O67,LEN(O67)-SEARCH("\",O67)) -> S3P2 | AK67: =IFERROR(VLOOKUP(Z67,'PASTE-DL-ALARMS'!$Q$10:$W$2200,7,FALSE),"") | AL67: =IFERROR(VLOOKUP(Z67,'PASTE-DL-ALARMS'!$Q$10:$W$2200,3,FALSE),"") | AM67: =CONCATENATE(AE67,"_",AG67,"_",AI67) -> 10.121.17.26_RAJKOT_S3P2 | AN67: =CONCATENATE(AF67,"_",AH67,"_",AJ67) -> 10.121.17.27_RAJKOT KR_S3P2 | AO67: =$AL$3-AK67 -> #VALUE! | AP67: =IFERROR(VLOOKUP(Z67,'PASTE-DL-ALARMS'!$Q$10:$Z$2800,8,FALSE),"")
C68: =IF(D68="Critical",MAX($C$8:C67)+1,"") | D68: =TRIM(CLEAN(P68)) -> - | E68: =VLOOKUP('PASTE-DOWN-DL'!F68,'SSA-CODE'!$D$4:$E$56,2,FALSE) -> WTR RJ | F68: =TRIM(CLEAN(SUBSTITUTE(G68,CHAR(160)," "))) -> WTR RJ | G68: =MID(I68,1,SEARCH("-",I68)-1) -> WTR RJ | H68: 59 | I68: WTR RJ-10.121.17.76-Aadesar_6/1-10.121.17.71-Samkhiyali_6/1 | J68: Fiber | K68: 10GE | L68: Eth | M68: BI-DIR | N68: 10.121.17.76_AADESAR_TN725B_GJ_SSA BUJ_PH3\S6P1 | O68: 10.121.17.71_SAMKHIYALI_TN725B_WTR_RJ_PH1\S6P1 | P68: - | Q68: 23 | R68: 33 | T68: 200800788 | U68: bhuj_ssa | V68: 1.0 | W68: 2020/08/28,19:05:52 | X68: 2026/04/21,11:59:29 | Z68: =TRIM(CLEAN(I68)) -> WTR RJ-10.121.17.76-Aadesar_6/1-10.121.17.71-Samkhiyali_6/1 | AA68: =SEARCH("_",N68) -> 14 | AB68: =SEARCH("_TN7",N68) -> 22 | AC68: =SEARCH("_",O68) -> 14 | AD68: =SEARCH("_TN7",O68) -> 25 | AE68: =TRIM(CLEAN(MID(N68,1,SEARCH("_",N68)-1))) -> 10.121.17.76 | AF68: =TRIM(CLEAN(MID(O68,1,SEARCH("_",O68)-1))) -> 10.121.17.71 | AG68: =MID(N68,AA68+1,AB68-AA68-1) -> AADESAR | AH68: =MID(O68,AC68+1,AD68-AC68-1) -> SAMKHIYALI | AI68: =RIGHT(N68,LEN(N68)-SEARCH("\",N68)) -> S6P1 | AJ68: =RIGHT(O68,LEN(O68)-SEARCH("\",O68)) -> S6P1 | AK68: =IFERROR(VLOOKUP(Z68,'PASTE-DL-ALARMS'!$Q$10:$W$2200,7,FALSE),"") | AL68: =IFERROR(VLOOKUP(Z68,'PASTE-DL-ALARMS'!$Q$10:$W$2200,3,FALSE),"") | AM68: =CONCATENATE(AE68,"_",AG68,"_",AI68) -> 10.121.17.76_AADESAR_S6P1 | AN68: =CONCATENATE(AF68,"_",AH68,"_",AJ68) -> 10.121.17.71_SAMKHIYALI_S6P1 | AO68: =$AL$3-AK68 -> #VALUE! | AP68: =IFERROR(VLOOKUP(Z68,'PASTE-DL-ALARMS'!$Q$10:$Z$2800,8,FALSE),"")
C69: =IF(D69="Critical",MAX($C$8:C68)+1,"") | D69: =TRIM(CLEAN(P69)) -> - | E69: =VLOOKUP('PASTE-DOWN-DL'!F69,'SSA-CODE'!$D$4:$E$56,2,FALSE) -> VDA | F69: =TRIM(CLEAN(SUBSTITUTE(G69,CHAR(160)," "))) -> SSA VDR | G69: =MID(I69,1,SEARCH("-",I69)-1) -> SSA VDR | H69: 60 | I69: SSA VDR-10.121.99.129-Alkapuri(GNE)_4/1-10.121.19.130-Alkapuri(GNE)_6/1 | J69: Fiber | K69: 10GE | L69: Eth | M69: BI-DIR | N69: 10.121.99.129_ALKAPURI(GNE)_TN725B_GJ_SSA VDR_PH3\S4P1 | O69: 10.121.19.130_ALKAPURI(GNE)_TN725B_GJ_SSA VDR_PH2\S6P1 | P69: - | Q69: 35 | R69: 44 | S69: GCS_ID-0038690 | T69: 60070238 | U69: Vadodara_SSA | V69: 1.0 | W69: 2025/02/07,10:40:17 | X69: 2026/04/21,12:00:35 | Z69: =TRIM(CLEAN(I69)) -> SSA VDR-10.121.99.129-Alkapuri(GNE)_4/1-10.121.19.130-Alkapuri(GNE)_6/1 | AA69: =SEARCH("_",N69) -> 15 | AB69: =SEARCH("_TN7",N69) -> 29 | AC69: =SEARCH("_",O69) -> 15 | AD69: =SEARCH("_TN7",O69) -> 29 | AE69: =TRIM(CLEAN(MID(N69,1,SEARCH("_",N69)-1))) -> 10.121.99.129 | AF69: =TRIM(CLEAN(MID(O69,1,SEARCH("_",O69)-1))) -> 10.121.19.130 | AG69: =MID(N69,AA69+1,AB69-AA69-1) -> ALKAPURI(GNE) | AH69: =MID(O69,AC69+1,AD69-AC69-1) -> ALKAPURI(GNE) | AI69: =RIGHT(N69,LEN(N69)-SEARCH("\",N69)) -> S4P1 | AJ69: =RIGHT(O69,LEN(O69)-SEARCH("\",O69)) -> S6P1 | AK69: =IFERROR(VLOOKUP(Z69,'PASTE-DL-ALARMS'!$Q$10:$W$2200,7,FALSE),"") | AL69: =IFERROR(VLOOKUP(Z69,'PASTE-DL-ALARMS'!$Q$10:$W$2200,3,FALSE),"") | AM69: =CONCATENATE(AE69,"_",AG69,"_",AI69) -> 10.121.99.129_ALKAPURI(GNE)_S4P1 | AN69: =CONCATENATE(AF69,"_",AH69,"_",AJ69) -> 10.121.19.130_ALKAPURI(GNE)_S6P1 | AO69: =$AL$3-AK69 -> #VALUE! | AP69: =IFERROR(VLOOKUP(Z69,'PASTE-DL-ALARMS'!$Q$10:$Z$2800,8,FALSE),"")
C70: =IF(D70="Critical",MAX($C$8:C69)+1,"") | D70: =TRIM(CLEAN(P70)) -> - | E70: =VLOOKUP('PASTE-DOWN-DL'!F70,'SSA-CODE'!$D$4:$E$56,2,FALSE) -> BUJ | F70: =TRIM(CLEAN(SUBSTITUTE(G70,CHAR(160)," "))) -> SSA BUJ | G70: =MID(I70,1,SEARCH("-",I70)-1) -> SSA BUJ | H70: 61 | I70: SSA BUJ-10.121.96.139-Nakhatrana B2_5/2-10.121.96.142-NANA-ANGIYA A1_1/5 | J70: Fiber | K70: GE | L70: Eth | M70: BI-DIR | N70: 10.121.96.139_Nakhatrana_TN725B_GJ_SSA BUJ_PH2\S5P2 | O70: 10.121.96.142_NANA ANGIYA_TN703B_GJ_SSA BUJ_PH2\S1P5 | P70: - | Q70: 31 | R70: 100 | S70: GCS_ID-0043031 | T70: Atul | U70: Bhuj_SSAA | V70: 1.0 | W70: 2025/07/10,16:21:41 | X70: 2025/07/10,20:09:58 | Z70: =TRIM(CLEAN(I70)) -> SSA BUJ-10.121.96.139-Nakhatrana B2_5/2-10.121.96.142-NANA-ANGIYA A1_1/5 | AA70: =SEARCH("_",N70) -> 15 | AB70: =SEARCH("_TN7",N70) -> 26 | AC70: =SEARCH("_",O70) -> 15 | AD70: =SEARCH("_TN7",O70) -> 27 | AE70: =TRIM(CLEAN(MID(N70,1,SEARCH("_",N70)-1))) -> 10.121.96.139 | AF70: =TRIM(CLEAN(MID(O70,1,SEARCH("_",O70)-1))) -> 10.121.96.142 | AG70: =MID(N70,AA70+1,AB70-AA70-1) -> Nakhatrana | AH70: =MID(O70,AC70+1,AD70-AC70-1) -> NANA ANGIYA | AI70: =RIGHT(N70,LEN(N70)-SEARCH("\",N70)) -> S5P2 | AJ70: =RIGHT(O70,LEN(O70)-SEARCH("\",O70)) -> S1P5 | AK70: =IFERROR(VLOOKUP(Z70,'PASTE-DL-ALARMS'!$Q$10:$W$2200,7,FALSE),"") | AL70: =IFERROR(VLOOKUP(Z70,'PASTE-DL-ALARMS'!$Q$10:$W$2200,3,FALSE),"") | AM70: =CONCATENATE(AE70,"_",AG70,"_",AI70) -> 10.121.96.139_Nakhatrana_S5P2 | AN70: =CONCATENATE(AF70,"_",AH70,"_",AJ70) -> 10.121.96.142_NANA ANGIYA_S1P5 | AO70: =$AL$3-AK70 -> #VALUE! | AP70: =IFERROR(VLOOKUP(Z70,'PASTE-DL-ALARMS'!$Q$10:$Z$2800,8,FALSE),"")
C71: =IF(D71="Critical",MAX($C$8:C70)+1,"") | D71: =TRIM(CLEAN(P71)) -> - | E71: =VLOOKUP('PASTE-DOWN-DL'!F71,'SSA-CODE'!$D$4:$E$56,2,FALSE) -> AHD | F71: =TRIM(CLEAN(SUBSTITUTE(G71,CHAR(160)," "))) -> SSA AM | G71: =MID(I71,1,SEARCH("-",I71)-1) -> SSA AM | H71: 62 | I71: SSA AM-10.121.17.206-Thaltej_3/3-10.121.17.211-Torrent Pharma CO_1/5 | J71: Fiber | K71: GE | L71: Eth | M71: BI-DIR | N71: 10.121.17.206_THALTEJ_TN725B_GJ_SSA AM_PH1\S3P3 | O71: 10.121.17.211_Torrent Pharma CO_TN703B_GJ_SSA AM_PH3\S1P5 | P71: - | Q71: 1 | R71: 1 | S71: GUJ_AHD_GCSID_47128 | T71: 200300828 | U71: AHMEDABAD SSA | V71: 1.0 | W71: 2025/12/10,16:24:17 | X71: 2026/01/20,12:46:47 | Y71: Thaltej - Shilaj 288F 1/21/5&6 at Thaltej end and F1&2 at Customer end | Z71: =TRIM(CLEAN(I71)) -> SSA AM-10.121.17.206-Thaltej_3/3-10.121.17.211-Torrent Pharma CO_1/5 | AA71: =SEARCH("_",N71) -> 15 | AB71: =SEARCH("_TN7",N71) -> 23 | AC71: =SEARCH("_",O71) -> 15 | AD71: =SEARCH("_TN7",O71) -> 33 | AE71: =TRIM(CLEAN(MID(N71,1,SEARCH("_",N71)-1))) -> 10.121.17.206 | AF71: =TRIM(CLEAN(MID(O71,1,SEARCH("_",O71)-1))) -> 10.121.17.211 | AG71: =MID(N71,AA71+1,AB71-AA71-1) -> THALTEJ | AH71: =MID(O71,AC71+1,AD71-AC71-1) -> Torrent Pharma CO | AI71: =RIGHT(N71,LEN(N71)-SEARCH("\",N71)) -> S3P3 | AJ71: =RIGHT(O71,LEN(O71)-SEARCH("\",O71)) -> S1P5 | AK71: =IFERROR(VLOOKUP(Z71,'PASTE-DL-ALARMS'!$Q$10:$W$2200,7,FALSE),"") | AL71: =IFERROR(VLOOKUP(Z71,'PASTE-DL-ALARMS'!$Q$10:$W$2200,3,FALSE),"") | AM71: =CONCATENATE(AE71,"_",AG71,"_",AI71) -> 10.121.17.206_THALTEJ_S3P3 | AN71: =CONCATENATE(AF71,"_",AH71,"_",AJ71) -> 10.121.17.211_Torrent Pharma CO_S1P5 | AO71: =$AL$3-AK71 -> #VALUE! | AP71: =IFERROR(VLOOKUP(Z71,'PASTE-DL-ALARMS'!$Q$10:$Z$2800,8,FALSE),"")
C72: =IF(D72="Critical",MAX($C$8:C71)+1,"") | D72: =TRIM(CLEAN(P72)) -> - | E72: =VLOOKUP('PASTE-DOWN-DL'!F72,'SSA-CODE'!$D$4:$E$56,2,FALSE) -> #N/A | F72: =TRIM(CLEAN(SUBSTITUTE(G72,CHAR(160)," "))) -> WTR BPL | G72: =MID(I72,1,SEARCH("-",I72)-1) -> WTR BPL | H72: 63 | I72: WTR BPL-10.121.71.148-TN725B_SHIVPURI_PH3\S6P1-10.121.71.149-TN725B_KARELA_PH3\S4P1 | J72: Fiber | K72: 10GE | L72: Eth | M72: BI-DIR | N72: e=18814S6P1 | O72: e=20839S4P1 | P72: - | Q72: 91 | R72: 98 | T72: Nikhil | V72: 1.0 | W72: 2019/07/18,12:42:15 | X72: 2025/05/06,09:38:40 | Z72: =TRIM(CLEAN(I72)) -> WTR BPL-10.121.71.148-TN725B_SHIVPURI_PH3\S6P1-10.121.71.149-TN725B_KARELA_PH3\S4P1 | AA72: =SEARCH("_",N72) -> #VALUE! | AB72: =SEARCH("_TN7",N72) -> #VALUE! | AC72: =SEARCH("_",O72) -> #VALUE! | AD72: =SEARCH("_TN7",O72) -> #VALUE! | AE72: =TRIM(CLEAN(MID(N72,1,SEARCH("_",N72)-1))) -> #VALUE! | AF72: =TRIM(CLEAN(MID(O72,1,SEARCH("_",O72)-1))) -> #VALUE! | AG72: =MID(N72,AA72+1,AB72-AA72-1) -> #VALUE! | AH72: =MID(O72,AC72+1,AD72-AC72-1) -> #VALUE! | AI72: =RIGHT(N72,LEN(N72)-SEARCH("\",N72)) -> #VALUE! | AJ72: =RIGHT(O72,LEN(O72)-SEARCH("\",O72)) -> #VALUE! | AK72: =IFERROR(VLOOKUP(Z72,'PASTE-DL-ALARMS'!$Q$10:$W$2200,7,FALSE),"") | AL72: =IFERROR(VLOOKUP(Z72,'PASTE-DL-ALARMS'!$Q$10:$W$2200,3,FALSE),"") | AM72: =CONCATENATE(AE72,"_",AG72,"_",AI72) -> #VALUE! | AN72: =CONCATENATE(AF72,"_",AH72,"_",AJ72) -> #VALUE! | AO72: =$AL$3-AK72 -> #VALUE! | AP72: =IFERROR(VLOOKUP(Z72,'PASTE-DL-ALARMS'!$Q$10:$Z$2800,8,FALSE),"")
C73: =IF(D73="Critical",MAX($C$8:C72)+1,"") | D73: =TRIM(CLEAN(P73)) -> - | E73: =VLOOKUP('PASTE-DOWN-DL'!F73,'SSA-CODE'!$D$4:$E$56,2,FALSE) -> SRT | F73: =TRIM(CLEAN(SUBSTITUTE(G73,CHAR(160)," "))) -> SSA SR | G73: =MID(I73,1,SEARCH("-",I73)-1) -> SSA SR | H73: 64 | I73: SSA SR-10.121.100.1-SURAT(GNE) B2_6/1-10.121.68.1-Surat 3 B2_6/1 | J73: Fiber | K73: 10GE | L73: Eth | M73: BI-DIR | N73: 10.121.100.1_SURAT(GNE)_TN725B_GJ_SSA SR_PH3\S6P1 | O73: 10.121.68.1_Surat 3(GNE)_TN725B_WTR_AM_PH3\S6P1 | P73: - | Q73: 66 | R73: 78 | S73: Surat SSA - GCS Issue id : 0002405 | T73: minaxikataria | U73: Surat SSA - GCS Issue id : 0002405 | V73: 1.0 | W73: 2019/05/22,11:42:35 | X73: 2023/01/09,15:11:17 | Z73: =TRIM(CLEAN(I73)) -> SSA SR-10.121.100.1-SURAT(GNE) B2_6/1-10.121.68.1-Surat 3 B2_6/1 | AA73: =SEARCH("_",N73) -> 14 | AB73: =SEARCH("_TN7",N73) -> 25 | AC73: =SEARCH("_",O73) -> 13 | AD73: =SEARCH("_TN7",O73) -> 26 | AE73: =TRIM(CLEAN(MID(N73,1,SEARCH("_",N73)-1))) -> 10.121.100.1 | AF73: =TRIM(CLEAN(MID(O73,1,SEARCH("_",O73)-1))) -> 10.121.68.1 | AG73: =MID(N73,AA73+1,AB73-AA73-1) -> SURAT(GNE) | AH73: =MID(O73,AC73+1,AD73-AC73-1) -> Surat 3(GNE) | AI73: =RIGHT(N73,LEN(N73)-SEARCH("\",N73)) -> S6P1 | AJ73: =RIGHT(O73,LEN(O73)-SEARCH("\",O73)) -> S6P1 | AK73: =IFERROR(VLOOKUP(Z73,'PASTE-DL-ALARMS'!$Q$10:$W$2200,7,FALSE),"") | AL73: =IFERROR(VLOOKUP(Z73,'PASTE-DL-ALARMS'!$Q$10:$W$2200,3,FALSE),"") | AM73: =CONCATENATE(AE73,"_",AG73,"_",AI73) -> 10.121.100.1_SURAT(GNE)_S6P1 | AN73: =CONCATENATE(AF73,"_",AH73,"_",AJ73) -> 10.121.68.1_Surat 3(GNE)_S6P1 | AO73: =$AL$3-AK73 -> #VALUE! | AP73: =IFERROR(VLOOKUP(Z73,'PASTE-DL-ALARMS'!$Q$10:$Z$2800,8,FALSE),"")
C74: =IF(D74="Critical",MAX($C$8:C73)+1,"") | D74: =TRIM(CLEAN(P74)) -> - | E74: =VLOOKUP('PASTE-DOWN-DL'!F74,'SSA-CODE'!$D$4:$E$56,2,FALSE) -> #N/A | F74: =TRIM(CLEAN(SUBSTITUTE(G74,CHAR(160)," "))) -> WTR BHOPAL | G74: =MID(I74,1,SEARCH("-",I74)-1) -> WTR BHOPAL | H74: 65 | I74: WTR BHOPAL-10.121.71.148-TN725B_SHIVPURI_PH3 6/6-10.121.71.129-TN725B_ACHELESHER_B2_PH3 6/6 | J74: Fiber | K74: GE | L74: Eth | M74: BI-DIR | N74: e=13910S6P6 | O74: e=18814S6P6 | P74: - | Q74: 85 | R74: 100 | T74: 200901136 | U74: 200901136 | V74: 1.0 | W74: 2021/11/10,15:36:38 | X74: 2023/04/15,14:36:10 | Y74: media-gwalior-otn-17/5+spr-otn-45/5 | Z74: =TRIM(CLEAN(I74)) -> WTR BHOPAL-10.121.71.148-TN725B_SHIVPURI_PH3 6/6-10.121.71.129-TN725B_ACHELESHER_B2_PH3 6/6 | AA74: =SEARCH("_",N74) -> #VALUE! | AB74: =SEARCH("_TN7",N74) -> #VALUE! | AC74: =SEARCH("_",O74) -> #VALUE! | AD74: =SEARCH("_TN7",O74) -> #VALUE! | AE74: =TRIM(CLEAN(MID(N74,1,SEARCH("_",N74)-1))) -> #VALUE! | AF74: =TRIM(CLEAN(MID(O74,1,SEARCH("_",O74)-1))) -> #VALUE! | AG74: =MID(N74,AA74+1,AB74-AA74-1) -> #VALUE! | AH74: =MID(O74,AC74+1,AD74-AC74-1) -> #VALUE! | AI74: =RIGHT(N74,LEN(N74)-SEARCH("\",N74)) -> #VALUE! | AJ74: =RIGHT(O74,LEN(O74)-SEARCH("\",O74)) -> #VALUE! | AK74: =IFERROR(VLOOKUP(Z74,'PASTE-DL-ALARMS'!$Q$10:$W$2200,7,FALSE),"") | AL74: =IFERROR(VLOOKUP(Z74,'PASTE-DL-ALARMS'!$Q$10:$W$2200,3,FALSE),"") | AM74: =CONCATENATE(AE74,"_",AG74,"_",AI74) -> #VALUE! | AN74: =CONCATENATE(AF74,"_",AH74,"_",AJ74) -> #VALUE! | AO74: =$AL$3-AK74 -> #VALUE! | AP74: =IFERROR(VLOOKUP(Z74,'PASTE-DL-ALARMS'!$Q$10:$Z$2800,8,FALSE),"")
C75: =IF(D75="Critical",MAX($C$8:C74)+1,"") | D75: =TRIM(CLEAN(P75)) -> - | E75: =VLOOKUP('PASTE-DOWN-DL'!F75,'SSA-CODE'!$D$4:$E$56,2,FALSE) -> WTR RJ | F75: =TRIM(CLEAN(SUBSTITUTE(G75,CHAR(160)," "))) -> WTR RJ | G75: =MID(I75,1,SEARCH("-",I75)-1) -> WTR RJ | H75: 66 | I75: WTR RJ-10.121.17.66-BHUJ2(GNE)_6/7-10.121.17.65-BHUJ1(GNE)_6/7 | J75: Twisted-Pair | K75: GE | L75: Eth | M75: BI-DIR | N75: 10.121.17.66_BHUJ2(GNE)_TN725B_WTR_RJ_PH1\S6P7 | O75: 10.121.17.65_BHUJ1(GNE)_TN725B_WTR_RJ_PH1\S6P7 | P75: - | Q75: 59 | R75: 100 | T75: Pawan | V75: 1.0 | W75: 2019/08/06,12:08:51 | X75: 2023/06/14,15:01:51 | Z75: =TRIM(CLEAN(I75)) -> WTR RJ-10.121.17.66-BHUJ2(GNE)_6/7-10.121.17.65-BHUJ1(GNE)_6/7 | AA75: =SEARCH("_",N75) -> 14 | AB75: =SEARCH("_TN7",N75) -> 25 | AC75: =SEARCH("_",O75) -> 14 | AD75: =SEARCH("_TN7",O75) -> 25 | AE75: =TRIM(CLEAN(MID(N75,1,SEARCH("_",N75)-1))) -> 10.121.17.66 | AF75: =TRIM(CLEAN(MID(O75,1,SEARCH("_",O75)-1))) -> 10.121.17.65 | AG75: =MID(N75,AA75+1,AB75-AA75-1) -> BHUJ2(GNE) | AH75: =MID(O75,AC75+1,AD75-AC75-1) -> BHUJ1(GNE) | AI75: =RIGHT(N75,LEN(N75)-SEARCH("\",N75)) -> S6P7 | AJ75: =RIGHT(O75,LEN(O75)-SEARCH("\",O75)) -> S6P7 | AK75: =IFERROR(VLOOKUP(Z75,'PASTE-DL-ALARMS'!$Q$10:$W$2200,7,FALSE),"") | AL75: =IFERROR(VLOOKUP(Z75,'PASTE-DL-ALARMS'!$Q$10:$W$2200,3,FALSE),"") | AM75: =CONCATENATE(AE75,"_",AG75,"_",AI75) -> 10.121.17.66_BHUJ2(GNE)_S6P7 | AN75: =CONCATENATE(AF75,"_",AH75,"_",AJ75) -> 10.121.17.65_BHUJ1(GNE)_S6P7 | AO75: =$AL$3-AK75 -> #VALUE! | AP75: =IFERROR(VLOOKUP(Z75,'PASTE-DL-ALARMS'!$Q$10:$Z$2800,8,FALSE),"")
C76: =IF(D76="Critical",MAX($C$8:C75)+1,"") | D76: =TRIM(CLEAN(P76)) -> - | E76: =VLOOKUP('PASTE-DOWN-DL'!F76,'SSA-CODE'!$D$4:$E$56,2,FALSE) -> NDD | F76: =TRIM(CLEAN(SUBSTITUTE(G76,CHAR(160)," "))) -> SSA NAD | G76: =MID(I76,1,SEARCH("-",I76)-1) -> SSA NAD | H76: 67 | I76: SSA NAD-10.121.98.65-PETLAD_3/6-10.121.98.85-Vatav _1/5 | J76: Fiber | K76: GE | L76: Eth | M76: BI-DIR | N76: 10.121.98.85_Vatav _TN703B_GJ_SSA NAD_PH3\S2P6 | O76: 10.121.98.65_PETLAD_TN725B_GJ_SSA NAD_PH3\S3P6 | P76: - | Q76: 45 | R76: 100 | S76: Nadiad SSA GCS ID 45911 | T76: 200800716 | U76: Nadiad SSA GCS ID 45911 | V76: 1.0 | W76: 2025/10/16,00:14:07 | X76: 2026/01/17,13:05:20 | Z76: =TRIM(CLEAN(I76)) -> SSA NAD-10.121.98.65-PETLAD_3/6-10.121.98.85-Vatav _1/5 | AA76: =SEARCH("_",N76) -> 14 | AB76: =SEARCH("_TN7",N76) -> 21 | AC76: =SEARCH("_",O76) -> 14 | AD76: =SEARCH("_TN7",O76) -> 21 | AE76: =TRIM(CLEAN(MID(N76,1,SEARCH("_",N76)-1))) -> 10.121.98.85 | AF76: =TRIM(CLEAN(MID(O76,1,SEARCH("_",O76)-1))) -> 10.121.98.65 | AG76: =MID(N76,AA76+1,AB76-AA76-1) -> Vatav | AH76: =MID(O76,AC76+1,AD76-AC76-1) -> PETLAD | AI76: =RIGHT(N76,LEN(N76)-SEARCH("\",N76)) -> S2P6 | AJ76: =RIGHT(O76,LEN(O76)-SEARCH("\",O76)) -> S3P6 | AK76: =IFERROR(VLOOKUP(Z76,'PASTE-DL-ALARMS'!$Q$10:$W$2200,7,FALSE),"") | AL76: =IFERROR(VLOOKUP(Z76,'PASTE-DL-ALARMS'!$Q$10:$W$2200,3,FALSE),"") | AM76: =CONCATENATE(AE76,"_",AG76,"_",AI76) -> 10.121.98.85_Vatav _S2P6 | AN76: =CONCATENATE(AF76,"_",AH76,"_",AJ76) -> 10.121.98.65_PETLAD_S3P6 | AO76: =$AL$3-AK76 -> #VALUE! | AP76: =IFERROR(VLOOKUP(Z76,'PASTE-DL-ALARMS'!$Q$10:$Z$2800,8,FALSE),"")
C77: =IF(D77="Critical",MAX($C$8:C76)+1,"") -> 2 | D77: =TRIM(CLEAN(P77)) -> Critical | E77: =VLOOKUP('PASTE-DOWN-DL'!F77,'SSA-CODE'!$D$4:$E$56,2,FALSE) -> BCH | F77: =TRIM(CLEAN(SUBSTITUTE(G77,CHAR(160)," "))) -> SSA BCH | G77: =MID(I77,1,SEARCH("-",I77)-1) -> SSA BCH | H77: 68 | I77: SSA BCH-10.121.96.75-CHANCHVEL_S3P2-10.121.96.112-ACCHOD_S4P2 | J77: Fiber | K77: GE | L77: Eth | M77: BI-DIR | N77: 10.121.96.75_CHANCHVEL_TN705B_GJ_SSA BCH_PH3\S3P2 | O77: 10.121.96.112_ACCHOD_TN705B_GJ_SSA BCH_PH3\S4P2 | P77: Critical | Q77: 58 | R77: 100 | S77: GCS ID 29693 | T77: 200800022 | U77: BHARUCH SSA | V77: 1.0 | W77: 2025/11/28,12:37:56 | X77: 2026/04/23,09:04:37 | Y77: ACCHOD-CHANCHVEL 1G DL | Z77: =TRIM(CLEAN(I77)) -> SSA BCH-10.121.96.75-CHANCHVEL_S3P2-10.121.96.112-ACCHOD_S4P2 | AA77: =SEARCH("_",N77) -> 14 | AB77: =SEARCH("_TN7",N77) -> 24 | AC77: =SEARCH("_",O77) -> 15 | AD77: =SEARCH("_TN7",O77) -> 22 | AE77: =TRIM(CLEAN(MID(N77,1,SEARCH("_",N77)-1))) -> 10.121.96.75 | AF77: =TRIM(CLEAN(MID(O77,1,SEARCH("_",O77)-1))) -> 10.121.96.112 | AG77: =MID(N77,AA77+1,AB77-AA77-1) -> CHANCHVEL | AH77: =MID(O77,AC77+1,AD77-AC77-1) -> ACCHOD | AI77: =RIGHT(N77,LEN(N77)-SEARCH("\",N77)) -> S3P2 | AJ77: =RIGHT(O77,LEN(O77)-SEARCH("\",O77)) -> S4P2 | AK77: =IFERROR(VLOOKUP(Z77,'PASTE-DL-ALARMS'!$Q$10:$W$2200,7,FALSE),"") -> 18-04-2026 | AL77: =IFERROR(VLOOKUP(Z77,'PASTE-DL-ALARMS'!$Q$10:$W$2200,3,FALSE),"") -> 13:13:14 | AM77: =CONCATENATE(AE77,"_",AG77,"_",AI77) -> 10.121.96.75_CHANCHVEL_S3P2 | AN77: =CONCATENATE(AF77,"_",AH77,"_",AJ77) -> 10.121.96.112_ACCHOD_S4P2 | AO77: =$AL$3-AK77 -> 27 | AP77: =IFERROR(VLOOKUP(Z77,'PASTE-DL-ALARMS'!$Q$10:$Z$2800,8,FALSE),"") -> 2026/04/18,13:13:14
C78: =IF(D78="Critical",MAX($C$8:C77)+1,"") | D78: =TRIM(CLEAN(P78)) -> - | E78: =VLOOKUP('PASTE-DOWN-DL'!F78,'SSA-CODE'!$D$4:$E$56,2,FALSE) -> PLR | F78: =TRIM(CLEAN(SUBSTITUTE(G78,CHAR(160)," "))) -> SSA PNP | G78: =MID(I78,1,SEARCH("-",I78)-1) -> SSA PNP | H78: 69 | I78: SSA PNP-10.121.25.135-RAHA_2/5-10.121.15.207-THARAD B1_4/3 | J78: Fiber | K78: GE | L78: Eth | M78: BI-DIR | N78: 10.121.15.207_THARAD_TN705B_WTR_AM_PH2\S4P3 | O78: 10.121.25.135_RAHA A1_TN703B_GJ_SSA PNP_PH2\S2P5 | P78: - | Q78: 11 | R78: 100 | S78: Guj_Palanpur-SSA_GCS_ID-0026347 | T78: 200904043 | U78: Guj_Palanpur-SSA_GCS_ID-0026347 | V78: 1.0 | W78: 2023/10/15,14:23:57 | X78: 2025/09/08,11:11:43 | Z78: =TRIM(CLEAN(I78)) -> SSA PNP-10.121.25.135-RAHA_2/5-10.121.15.207-THARAD B1_4/3 | AA78: =SEARCH("_",N78) -> 15 | AB78: =SEARCH("_TN7",N78) -> 22 | AC78: =SEARCH("_",O78) -> 15 | AD78: =SEARCH("_TN7",O78) -> 23 | AE78: =TRIM(CLEAN(MID(N78,1,SEARCH("_",N78)-1))) -> 10.121.15.207 | AF78: =TRIM(CLEAN(MID(O78,1,SEARCH("_",O78)-1))) -> 10.121.25.135 | AG78: =MID(N78,AA78+1,AB78-AA78-1) -> THARAD | AH78: =MID(O78,AC78+1,AD78-AC78-1) -> RAHA A1 | AI78: =RIGHT(N78,LEN(N78)-SEARCH("\",N78)) -> S4P3 | AJ78: =RIGHT(O78,LEN(O78)-SEARCH("\",O78)) -> S2P5 | AK78: =IFERROR(VLOOKUP(Z78,'PASTE-DL-ALARMS'!$Q$10:$W$2200,7,FALSE),"") | AL78: =IFERROR(VLOOKUP(Z78,'PASTE-DL-ALARMS'!$Q$10:$W$2200,3,FALSE),"") | AM78: =CONCATENATE(AE78,"_",AG78,"_",AI78) -> 10.121.15.207_THARAD_S4P3 | AN78: =CONCATENATE(AF78,"_",AH78,"_",AJ78) -> 10.121.25.135_RAHA A1_S2P5 | AO78: =$AL$3-AK78 -> #VALUE! | AP78: =IFERROR(VLOOKUP(Z78,'PASTE-DL-ALARMS'!$Q$10:$Z$2800,8,FALSE),"")
C79: =IF(D79="Critical",MAX($C$8:C78)+1,"") | D79: =TRIM(CLEAN(P79)) -> - | E79: =VLOOKUP('PASTE-DOWN-DL'!F79,'SSA-CODE'!$D$4:$E$56,2,FALSE) -> SRT | F79: =TRIM(CLEAN(SUBSTITUTE(G79,CHAR(160)," "))) -> SSA SR | G79: =MID(I79,1,SEARCH("-",I79)-1) -> SSA SR | H79: 70 | I79: SSA SR-10.121.19.193-Market1(GNE)_6/1-10.121.19.196-Surat_Market2_6/1 | J79: Fiber | K79: 10GE | L79: Eth | M79: BI-DIR | N79: 10.121.19.196_SURAT-MARKET2_TN725B_GJ_SSA SR_PH2\S6P1 | O79: 10.121.19.193_MARKET1(GNE)_TN725B_GJ_SSA SR_PH2\S6P1 | P79: - | Q79: 51 | R79: 71 | S79: Surat SSA | T79: vishleshpatel | U79: Surat SSA | V79: 1.0 | W79: 2018/09/25,11:24:02 | X79: 2026/04/23,16:53:23 | Z79: =TRIM(CLEAN(I79)) -> SSA SR-10.121.19.193-Market1(GNE)_6/1-10.121.19.196-Surat_Market2_6/1 | AA79: =SEARCH("_",N79) -> 15 | AB79: =SEARCH("_TN7",N79) -> 29 | AC79: =SEARCH("_",O79) -> 15 | AD79: =SEARCH("_TN7",O79) -> 28 | AE79: =TRIM(CLEAN(MID(N79,1,SEARCH("_",N79)-1))) -> 10.121.19.196 | AF79: =TRIM(CLEAN(MID(O79,1,SEARCH("_",O79)-1))) -> 10.121.19.193 | AG79: =MID(N79,AA79+1,AB79-AA79-1) -> SURAT-MARKET2 | AH79: =MID(O79,AC79+1,AD79-AC79-1) -> MARKET1(GNE) | AI79: =RIGHT(N79,LEN(N79)-SEARCH("\",N79)) -> S6P1 | AJ79: =RIGHT(O79,LEN(O79)-SEARCH("\",O79)) -> S6P1 | AK79: =IFERROR(VLOOKUP(Z79,'PASTE-DL-ALARMS'!$Q$10:$W$2200,7,FALSE),"") | AL79: =IFERROR(VLOOKUP(Z79,'PASTE-DL-ALARMS'!$Q$10:$W$2200,3,FALSE),"") | AM79: =CONCATENATE(AE79,"_",AG79,"_",AI79) -> 10.121.19.196_SURAT-MARKET2_S6P1 | AN79: =CONCATENATE(AF79,"_",AH79,"_",AJ79) -> 10.121.19.193_MARKET1(GNE)_S6P1 | AO79: =$AL$3-AK79 -> #VALUE! | AP79: =IFERROR(VLOOKUP(Z79,'PASTE-DL-ALARMS'!$Q$10:$Z$2800,8,FALSE),"")
C80: =IF(D80="Critical",MAX($C$8:C79)+1,"") | D80: =TRIM(CLEAN(P80)) -> - | E80: =VLOOKUP('PASTE-DOWN-DL'!F80,'SSA-CODE'!$D$4:$E$56,2,FALSE) -> WTR RJ | F80: =TRIM(CLEAN(SUBSTITUTE(G80,CHAR(160)," "))) -> WTR RJ | G80: =MID(I80,1,SEARCH("-",I80)-1) -> WTR RJ | H80: 71 | I80: WTR RJ-10.121.17.9-Rj Bhaktinagar B2_5/1-10.121.17.1-RAJKOT KR(GNE) B2_5/1 | J80: Fiber | K80: 10GE | L80: Eth | M80: BI-DIR | N80: 10.121.17.9_RJ BHAKTINAGAR_TN725B_WTR_RJ_PH1\S5P1 | O80: 10.121.17.1_RAJKOT KR(GNE)_TN725B_WTR_RJ_PH1\S5P1 | P80: - | Q80: 28 | R80: 100 | T80: root | V80: 1.0 | W80: 2018/04/12,17:27:52 | X80: 2023/05/20,13:23:19 | Y80: ON DARK FIBER KR-BKT 24F F5,7 | Z80: =TRIM(CLEAN(I80)) -> WTR RJ-10.121.17.9-Rj Bhaktinagar B2_5/1-10.121.17.1-RAJKOT KR(GNE) B2_5/1 | AA80: =SEARCH("_",N80) -> 13 | AB80: =SEARCH("_TN7",N80) -> 28 | AC80: =SEARCH("_",O80) -> 13 | AD80: =SEARCH("_TN7",O80) -> 28 | AE80: =TRIM(CLEAN(MID(N80,1,SEARCH("_",N80)-1))) -> 10.121.17.9 | AF80: =TRIM(CLEAN(MID(O80,1,SEARCH("_",O80)-1))) -> 10.121.17.1 | AG80: =MID(N80,AA80+1,AB80-AA80-1) -> RJ BHAKTINAGAR | AH80: =MID(O80,AC80+1,AD80-AC80-1) -> RAJKOT KR(GNE) | AI80: =RIGHT(N80,LEN(N80)-SEARCH("\",N80)) -> S5P1 | AJ80: =RIGHT(O80,LEN(O80)-SEARCH("\",O80)) -> S5P1 | AK80: =IFERROR(VLOOKUP(Z80,'PASTE-DL-ALARMS'!$Q$10:$W$2200,7,FALSE),"") | AL80: =IFERROR(VLOOKUP(Z80,'PASTE-DL-ALARMS'!$Q$10:$W$2200,3,FALSE),"") | AM80: =CONCATENATE(AE80,"_",AG80,"_",AI80) -> 10.121.17.9_RJ BHAKTINAGAR_S5P1 | AN80: =CONCATENATE(AF80,"_",AH80,"_",AJ80) -> 10.121.17.1_RAJKOT KR(GNE)_S5P1 | AO80: =$AL$3-AK80 -> #VALUE! | AP80: =IFERROR(VLOOKUP(Z80,'PASTE-DL-ALARMS'!$Q$10:$Z$2800,8,FALSE),"")
C81: =IF(D81="Critical",MAX($C$8:C80)+1,"") | D81: =TRIM(CLEAN(P81)) -> - | E81: =VLOOKUP('PASTE-DOWN-DL'!F81,'SSA-CODE'!$D$4:$E$56,2,FALSE) -> WTR AM | F81: =TRIM(CLEAN(SUBSTITUTE(G81,CHAR(160)," "))) -> WTR AM | G81: =MID(I81,1,SEARCH("-",I81)-1) -> WTR AM | H81: 72 | I81: WTR AM-10.121.15.205-Vadgam_B2_PH2_5/1-10.121.15.206-Moriya_B1_3/1 | J81: Fiber | K81: 10GE | L81: Eth | M81: BI-DIR | N81: 10.121.15.205_Vadgam_TN725B_WTR_AM_PH2\S5P1 | O81: 10.121.15.206_MORIYA_TN705B_WTR_AM_PH3\S3P1 | P81: - | Q81: 19 | R81: 34 | S81: GUJ_PLR_GCS_ID_22937 | T81: 200800474 | U81: PALANPUR SSA | V81: 1.0 | W81: 2023/04/08,12:51:36 | X81: 2023/05/23,12:31:51 | Z81: =TRIM(CLEAN(I81)) -> WTR AM-10.121.15.205-Vadgam_B2_PH2_5/1-10.121.15.206-Moriya_B1_3/1 | AA81: =SEARCH("_",N81) -> 15 | AB81: =SEARCH("_TN7",N81) -> 22 | AC81: =SEARCH("_",O81) -> 15 | AD81: =SEARCH("_TN7",O81) -> 22 | AE81: =TRIM(CLEAN(MID(N81,1,SEARCH("_",N81)-1))) -> 10.121.15.205 | AF81: =TRIM(CLEAN(MID(O81,1,SEARCH("_",O81)-1))) -> 10.121.15.206 | AG81: =MID(N81,AA81+1,AB81-AA81-1) -> Vadgam | AH81: =MID(O81,AC81+1,AD81-AC81-1) -> MORIYA | AI81: =RIGHT(N81,LEN(N81)-SEARCH("\",N81)) -> S5P1 | AJ81: =RIGHT(O81,LEN(O81)-SEARCH("\",O81)) -> S3P1 | AK81: =IFERROR(VLOOKUP(Z81,'PASTE-DL-ALARMS'!$Q$10:$W$2200,7,FALSE),"") | AL81: =IFERROR(VLOOKUP(Z81,'PASTE-DL-ALARMS'!$Q$10:$W$2200,3,FALSE),"") | AM81: =CONCATENATE(AE81,"_",AG81,"_",AI81) -> 10.121.15.205_Vadgam_S5P1 | AN81: =CONCATENATE(AF81,"_",AH81,"_",AJ81) -> 10.121.15.206_MORIYA_S3P1 | AO81: =$AL$3-AK81 -> #VALUE! | AP81: =IFERROR(VLOOKUP(Z81,'PASTE-DL-ALARMS'!$Q$10:$Z$2800,8,FALSE),"")
C82: =IF(D82="Critical",MAX($C$8:C81)+1,"") | D82: =TRIM(CLEAN(P82)) -> - | E82: =VLOOKUP('PASTE-DOWN-DL'!F82,'SSA-CODE'!$D$4:$E$56,2,FALSE) -> MSN | F82: =TRIM(CLEAN(SUBSTITUTE(G82,CHAR(160)," "))) -> SSA MEH | G82: =MID(I82,1,SEARCH("-",I82)-1) -> SSA MEH | H82: 73 | I82: SSA MEH-10.121.15.193-GujMSN_WTR_Mehsana3 (GNE)_B2 / S4P8-10.121.15.129-GUjMSN_WTR_Mehsana1_B2 / S4P8 | J82: Twisted-Pair | K82: GE | L82: Eth | M82: BI-DIR | N82: 10.121.15.129_MEHSANA1_TN725B_WTR_AM_PH1\S4P8 | O82: 10.121.15.193_Mehsana3(GNE)_TN725B_WTR_AM_PH1\S4P8 | P82: - | Q82: 87 | R82: 100 | S82: Mehsana SSA - GSC ID 0001932 | T82: niharbhatt | U82: Mehsana SSA | V82: 1.0 | W82: 2019/04/04,13:47:04 | X82: 2023/01/09,16:58:16 | Z82: =TRIM(CLEAN(I82)) -> SSA MEH-10.121.15.193-GujMSN_WTR_Mehsana3 (GNE)_B2 / S4P8-10.121.15.129-GUjMSN_WTR_Mehsana1_B2 / S4P8 | AA82: =SEARCH("_",N82) -> 15 | AB82: =SEARCH("_TN7",N82) -> 24 | AC82: =SEARCH("_",O82) -> 15 | AD82: =SEARCH("_TN7",O82) -> 29 | AE82: =TRIM(CLEAN(MID(N82,1,SEARCH("_",N82)-1))) -> 10.121.15.129 | AF82: =TRIM(CLEAN(MID(O82,1,SEARCH("_",O82)-1))) -> 10.121.15.193 | AG82: =MID(N82,AA82+1,AB82-AA82-1) -> MEHSANA1 | AH82: =MID(O82,AC82+1,AD82-AC82-1) -> Mehsana3(GNE) | AI82: =RIGHT(N82,LEN(N82)-SEARCH("\",N82)) -> S4P8 | AJ82: =RIGHT(O82,LEN(O82)-SEARCH("\",O82)) -> S4P8 | AK82: =IFERROR(VLOOKUP(Z82,'PASTE-DL-ALARMS'!$Q$10:$W$2200,7,FALSE),"") | AL82: =IFERROR(VLOOKUP(Z82,'PASTE-DL-ALARMS'!$Q$10:$W$2200,3,FALSE),"") | AM82: =CONCATENATE(AE82,"_",AG82,"_",AI82) -> 10.121.15.129_MEHSANA1_S4P8 | AN82: =CONCATENATE(AF82,"_",AH82,"_",AJ82) -> 10.121.15.193_Mehsana3(GNE)_S4P8 | AO82: =$AL$3-AK82 -> #VALUE! | AP82: =IFERROR(VLOOKUP(Z82,'PASTE-DL-ALARMS'!$Q$10:$Z$2800,8,FALSE),"")
C83: =IF(D83="Critical",MAX($C$8:C82)+1,"") | D83: =TRIM(CLEAN(P83)) -> - | E83: =VLOOKUP('PASTE-DOWN-DL'!F83,'SSA-CODE'!$D$4:$E$56,2,FALSE) -> SRT | F83: =TRIM(CLEAN(SUBSTITUTE(G83,CHAR(160)," "))) -> SSA SR | G83: =MID(I83,1,SEARCH("-",I83)-1) -> SSA SR | H83: 74 | I83: SSA SR-10.121.19.226-AIRPORT_3/10-10.121.19.236-Airport2 A1_1/3 | J83: Twisted-Pair | K83: GE | L83: Eth | M83: BI-DIR | N83: 10.121.19.226_AIRPORT_TN705B_GJ_SSA SR_PH2\S3P10 | O83: 10.121.19.236_Airport2_TN703B_GJ_SSA SR_PH2\S1P3 | P83: - | Q83: 4 | R83: 95 | S83: GUJ_SR_GCSID_46928 | T83: 200300828 | U83: SURAT SSA | V83: 1.0 | W83: 2025/12/03,16:48:49 | X83: 2026/01/17,12:45:49 | Z83: =TRIM(CLEAN(I83)) -> SSA SR-10.121.19.226-AIRPORT_3/10-10.121.19.236-Airport2 A1_1/3 | AA83: =SEARCH("_",N83) -> 15 | AB83: =SEARCH("_TN7",N83) -> 23 | AC83: =SEARCH("_",O83) -> 15 | AD83: =SEARCH("_TN7",O83) -> 24 | AE83: =TRIM(CLEAN(MID(N83,1,SEARCH("_",N83)-1))) -> 10.121.19.226 | AF83: =TRIM(CLEAN(MID(O83,1,SEARCH("_",O83)-1))) -> 10.121.19.236 | AG83: =MID(N83,AA83+1,AB83-AA83-1) -> AIRPORT | AH83: =MID(O83,AC83+1,AD83-AC83-1) -> Airport2 | AI83: =RIGHT(N83,LEN(N83)-SEARCH("\",N83)) -> S3P10 | AJ83: =RIGHT(O83,LEN(O83)-SEARCH("\",O83)) -> S1P3 | AK83: =IFERROR(VLOOKUP(Z83,'PASTE-DL-ALARMS'!$Q$10:$W$2200,7,FALSE),"") | AL83: =IFERROR(VLOOKUP(Z83,'PASTE-DL-ALARMS'!$Q$10:$W$2200,3,FALSE),"") | AM83: =CONCATENATE(AE83,"_",AG83,"_",AI83) -> 10.121.19.226_AIRPORT_S3P10 | AN83: =CONCATENATE(AF83,"_",AH83,"_",AJ83) -> 10.121.19.236_Airport2_S1P3 | AO83: =$AL$3-AK83 -> #VALUE! | AP83: =IFERROR(VLOOKUP(Z83,'PASTE-DL-ALARMS'!$Q$10:$Z$2800,8,FALSE),"")
C84: =IF(D84="Critical",MAX($C$8:C83)+1,"") | D84: =TRIM(CLEAN(P84)) -> - | E84: =VLOOKUP('PASTE-DOWN-DL'!F84,'SSA-CODE'!$D$4:$E$56,2,FALSE) -> AMR | F84: =TRIM(CLEAN(SUBSTITUTE(G84,CHAR(160)," "))) -> SSA AMR | G84: =MID(I84,1,SEARCH("-",I84)-1) -> SSA AMR | H84: 75 | I84: SSA AMR-10.121.96.29-MOTA-SAMADHIYALA_1/6-10.121.96.5_KHAMBHA B2_3/2 | J84: Fiber | K84: GE | L84: Eth | M84: BI-DIR | N84: 10.121.96.29_Mota Samadhiyala_TN703B_GJ_SSA AMR_PH2\S1P6 | O84: 10.121.96.5_KHAMBHA_TN705B_GJ_SSA AMR_PH3\S3P2 | P84: - | Q84: 18 | R84: 100 | S84: GCS_ID-0038208 | T84: 60070238 | U84: Amreli_SSA | V84: 1.0 | W84: 2025/01/23,23:02:21 | X84: 2026/04/14,15:39:35 | Z84: =TRIM(CLEAN(I84)) -> SSA AMR-10.121.96.29-MOTA-SAMADHIYALA_1/6-10.121.96.5_KHAMBHA B2_3/2 | AA84: =SEARCH("_",N84) -> 14 | AB84: =SEARCH("_TN7",N84) -> 31 | AC84: =SEARCH("_",O84) -> 13 | AD84: =SEARCH("_TN7",O84) -> 21 | AE84: =TRIM(CLEAN(MID(N84,1,SEARCH("_",N84)-1))) -> 10.121.96.29 | AF84: =TRIM(CLEAN(MID(O84,1,SEARCH("_",O84)-1))) -> 10.121.96.5 | AG84: =MID(N84,AA84+1,AB84-AA84-1) -> Mota Samadhiyala | AH84: =MID(O84,AC84+1,AD84-AC84-1) -> KHAMBHA | AI84: =RIGHT(N84,LEN(N84)-SEARCH("\",N84)) -> S1P6 | AJ84: =RIGHT(O84,LEN(O84)-SEARCH("\",O84)) -> S3P2 | AK84: =IFERROR(VLOOKUP(Z84,'PASTE-DL-ALARMS'!$Q$10:$W$2200,7,FALSE),"") | AL84: =IFERROR(VLOOKUP(Z84,'PASTE-DL-ALARMS'!$Q$10:$W$2200,3,FALSE),"") | AM84: =CONCATENATE(AE84,"_",AG84,"_",AI84) -> 10.121.96.29_Mota Samadhiyala_S1P6 | AN84: =CONCATENATE(AF84,"_",AH84,"_",AJ84) -> 10.121.96.5_KHAMBHA_S3P2 | AO84: =$AL$3-AK84 -> #VALUE! | AP84: =IFERROR(VLOOKUP(Z84,'PASTE-DL-ALARMS'!$Q$10:$Z$2800,8,FALSE),"")
C85: =IF(D85="Critical",MAX($C$8:C84)+1,"") | D85: =TRIM(CLEAN(P85)) -> - | E85: =VLOOKUP('PASTE-DOWN-DL'!F85,'SSA-CODE'!$D$4:$E$56,2,FALSE) -> BUJ | F85: =TRIM(CLEAN(SUBSTITUTE(G85,CHAR(160)," "))) -> SSA BUJ | G85: =MID(I85,1,SEARCH("-",I85)-1) -> SSA BUJ | H85: 76 | I85: SSA BUJ-10.121.24.73-Bharat Nagar_3/2-10.121.17.77-Tx_Plot 1008_2/5 | J85: Fiber | K85: GE | L85: Eth | M85: BI-DIR | N85: 10.121.24.73_Bharat Nagar_TN705B_GJ_SSA BUJ_PH2\S3P2 | O85: 10.121.17.77_TXPlot 1008_TN703B_GJ_SSA BUJ_PH1\S2P5 | P85: - | Q85: 37 | R85: 100 | S85: Bhuj SSA | T85: vishleshpatel | U85: Bhuj SSA | V85: 1.0 | W85: 2018/11/22,16:59:41 | X85: 2026/04/25,15:15:14 | Z85: =TRIM(CLEAN(I85)) -> SSA BUJ-10.121.24.73-Bharat Nagar_3/2-10.121.17.77-Tx_Plot 1008_2/5 | AA85: =SEARCH("_",N85) -> 14 | AB85: =SEARCH("_TN7",N85) -> 27 | AC85: =SEARCH("_",O85) -> 14 | AD85: =SEARCH("_TN7",O85) -> 26 | AE85: =TRIM(CLEAN(MID(N85,1,SEARCH("_",N85)-1))) -> 10.121.24.73 | AF85: =TRIM(CLEAN(MID(O85,1,SEARCH("_",O85)-1))) -> 10.121.17.77 | AG85: =MID(N85,AA85+1,AB85-AA85-1) -> Bharat Nagar | AH85: =MID(O85,AC85+1,AD85-AC85-1) -> TXPlot 1008 | AI85: =RIGHT(N85,LEN(N85)-SEARCH("\",N85)) -> S3P2 | AJ85: =RIGHT(O85,LEN(O85)-SEARCH("\",O85)) -> S2P5 | AK85: =IFERROR(VLOOKUP(Z85,'PASTE-DL-ALARMS'!$Q$10:$W$2200,7,FALSE),"") | AL85: =IFERROR(VLOOKUP(Z85,'PASTE-DL-ALARMS'!$Q$10:$W$2200,3,FALSE),"") | AM85: =CONCATENATE(AE85,"_",AG85,"_",AI85) -> 10.121.24.73_Bharat Nagar_S3P2 | AN85: =CONCATENATE(AF85,"_",AH85,"_",AJ85) -> 10.121.17.77_TXPlot 1008_S2P5 | AO85: =$AL$3-AK85 -> #VALUE! | AP85: =IFERROR(VLOOKUP(Z85,'PASTE-DL-ALARMS'!$Q$10:$Z$2800,8,FALSE),"")
C86: =IF(D86="Critical",MAX($C$8:C85)+1,"") | D86: =TRIM(CLEAN(P86)) -> - | E86: =VLOOKUP('PASTE-DOWN-DL'!F86,'SSA-CODE'!$D$4:$E$56,2,FALSE) -> WTR AM | F86: =TRIM(CLEAN(SUBSTITUTE(G86,CHAR(160)," "))) -> WTR AM | G86: =MID(I86,1,SEARCH("-",I86)-1) -> WTR AM | H86: 77 | I86: WTR AM-10.121.15.141-TN725B_Sidhpur_B2\S4P1-10.121.15.142-TN725B_Patan B2\S3P1 | J86: Fiber | K86: 10GE | L86: Eth | M86: BI-DIR | N86: 10.121.15.141_Sidhpur_TN725B_WTR_AM_PH2\S4P1 | O86: 10.121.15.142_Patan_TN725B_WTR_AM_PH2\S3P1 | P86: - | Q86: 41 | R86: 90 | T86: root | V86: 1.0 | W86: 2018/12/04,20:39:57 | X86: 2023/01/09,17:26:46 | Z86: =TRIM(CLEAN(I86)) -> WTR AM-10.121.15.141-TN725B_Sidhpur_B2\S4P1-10.121.15.142-TN725B_Patan B2\S3P1 | AA86: =SEARCH("_",N86) -> 15 | AB86: =SEARCH("_TN7",N86) -> 23 | AC86: =SEARCH("_",O86) -> 15 | AD86: =SEARCH("_TN7",O86) -> 21 | AE86: =TRIM(CLEAN(MID(N86,1,SEARCH("_",N86)-1))) -> 10.121.15.141 | AF86: =TRIM(CLEAN(MID(O86,1,SEARCH("_",O86)-1))) -> 10.121.15.142 | AG86: =MID(N86,AA86+1,AB86-AA86-1) -> Sidhpur | AH86: =MID(O86,AC86+1,AD86-AC86-1) -> Patan | AI86: =RIGHT(N86,LEN(N86)-SEARCH("\",N86)) -> S4P1 | AJ86: =RIGHT(O86,LEN(O86)-SEARCH("\",O86)) -> S3P1 | AK86: =IFERROR(VLOOKUP(Z86,'PASTE-DL-ALARMS'!$Q$10:$W$2200,7,FALSE),"") | AL86: =IFERROR(VLOOKUP(Z86,'PASTE-DL-ALARMS'!$Q$10:$W$2200,3,FALSE),"") | AM86: =CONCATENATE(AE86,"_",AG86,"_",AI86) -> 10.121.15.141_Sidhpur_S4P1 | AN86: =CONCATENATE(AF86,"_",AH86,"_",AJ86) -> 10.121.15.142_Patan_S3P1 | AO86: =$AL$3-AK86 -> #VALUE! | AP86: =IFERROR(VLOOKUP(Z86,'PASTE-DL-ALARMS'!$Q$10:$Z$2800,8,FALSE),"")
C87: =IF(D87="Critical",MAX($C$8:C86)+1,"") | D87: =TRIM(CLEAN(P87)) -> - | E87: =VLOOKUP('PASTE-DOWN-DL'!F87,'SSA-CODE'!$D$4:$E$56,2,FALSE) -> BUJ | F87: =TRIM(CLEAN(SUBSTITUTE(G87,CHAR(160)," "))) -> SSA BUJ | G87: =MID(I87,1,SEARCH("-",I87)-1) -> SSA BUJ | H87: 78 | I87: SSA BUJ-10.121.96.158-TN705B _VAYOR_S3P2-10.121.96.135-TN725B_Naliya_S4P2 | J87: Fiber | K87: GE | L87: Eth | M87: BI-DIR | N87: 10.121.96.158_VAYOR_TN705B_GJ_SSA BUJ_PH3\S3P2 | O87: 10.121.96.135_Naliya_TN725B_GJ_SSA BUJ_PH2\S4P2 | P87: - | Q87: 63 | R87: 100 | T87: kanishk | V87: 1.0 | W87: 2019/05/25,13:18:22 | X87: 2023/01/09,17:26:57 | Z87: =TRIM(CLEAN(I87)) -> SSA BUJ-10.121.96.158-TN705B _VAYOR_S3P2-10.121.96.135-TN725B_Naliya_S4P2 | AA87: =SEARCH("_",N87) -> 15 | AB87: =SEARCH("_TN7",N87) -> 21 | AC87: =SEARCH("_",O87) -> 15 | AD87: =SEARCH("_TN7",O87) -> 22 | AE87: =TRIM(CLEAN(MID(N87,1,SEARCH("_",N87)-1))) -> 10.121.96.158 | AF87: =TRIM(CLEAN(MID(O87,1,SEARCH("_",O87)-1))) -> 10.121.96.135 | AG87: =MID(N87,AA87+1,AB87-AA87-1) -> VAYOR | AH87: =MID(O87,AC87+1,AD87-AC87-1) -> Naliya | AI87: =RIGHT(N87,LEN(N87)-SEARCH("\",N87)) -> S3P2 | AJ87: =RIGHT(O87,LEN(O87)-SEARCH("\",O87)) -> S4P2 | AK87: =IFERROR(VLOOKUP(Z87,'PASTE-DL-ALARMS'!$Q$10:$W$2200,7,FALSE),"") | AL87: =IFERROR(VLOOKUP(Z87,'PASTE-DL-ALARMS'!$Q$10:$W$2200,3,FALSE),"") | AM87: =CONCATENATE(AE87,"_",AG87,"_",AI87) -> 10.121.96.158_VAYOR_S3P2 | AN87: =CONCATENATE(AF87,"_",AH87,"_",AJ87) -> 10.121.96.135_Naliya_S4P2 | AO87: =$AL$3-AK87 -> #VALUE! | AP87: =IFERROR(VLOOKUP(Z87,'PASTE-DL-ALARMS'!$Q$10:$Z$2800,8,FALSE),"")
C88: =IF(D88="Critical",MAX($C$8:C87)+1,"") | D88: =TRIM(CLEAN(P88)) -> - | E88: =VLOOKUP('PASTE-DOWN-DL'!F88,'SSA-CODE'!$D$4:$E$56,2,FALSE) -> AHD | F88: =TRIM(CLEAN(SUBSTITUTE(G88,CHAR(160)," "))) -> SSA AM | G88: =MID(I88,1,SEARCH("-",I88)-1) -> SSA AM | H88: 79 | I88: SSA AM-10.121.18.104-Hotel Neeltop BTS_1/5-10.121.18.75-Vasna2_4/6 | J88: Fiber | K88: GE | L88: Eth | M88: BI-DIR | N88: 10.121.18.104_HOTEL NEELTOP BTS_TN703B_GJ_SSA AM_PH2\S1P5 | O88: 10.121.18.75_VASNA 2_TN725B_GJ_SSA AM_PH1\S4P6 | P88: - | Q88: 5 | R88: 98 | S88: Guj-Ahemdabad_GCS_ID_0003444 & 0012195 | T88: 199105665 | U88: Guj-Ahemdabad_GCS_ID_0003444 & 0012195 | V88: 1.0 | W88: 2021/08/24,15:57:12 | X88: 2026/01/20,17:13:19 | Z88: =TRIM(CLEAN(I88)) -> SSA AM-10.121.18.104-Hotel Neeltop BTS_1/5-10.121.18.75-Vasna2_4/6 | AA88: =SEARCH("_",N88) -> 15 | AB88: =SEARCH("_TN7",N88) -> 33 | AC88: =SEARCH("_",O88) -> 14 | AD88: =SEARCH("_TN7",O88) -> 22 | AE88: =TRIM(CLEAN(MID(N88,1,SEARCH("_",N88)-1))) -> 10.121.18.104 | AF88: =TRIM(CLEAN(MID(O88,1,SEARCH("_",O88)-1))) -> 10.121.18.75 | AG88: =MID(N88,AA88+1,AB88-AA88-1) -> HOTEL NEELTOP BTS | AH88: =MID(O88,AC88+1,AD88-AC88-1) -> VASNA 2 | AI88: =RIGHT(N88,LEN(N88)-SEARCH("\",N88)) -> S1P5 | AJ88: =RIGHT(O88,LEN(O88)-SEARCH("\",O88)) -> S4P6 | AK88: =IFERROR(VLOOKUP(Z88,'PASTE-DL-ALARMS'!$Q$10:$W$2200,7,FALSE),"") | AL88: =IFERROR(VLOOKUP(Z88,'PASTE-DL-ALARMS'!$Q$10:$W$2200,3,FALSE),"") | AM88: =CONCATENATE(AE88,"_",AG88,"_",AI88) -> 10.121.18.104_HOTEL NEELTOP BTS_S1P5 | AN88: =CONCATENATE(AF88,"_",AH88,"_",AJ88) -> 10.121.18.75_VASNA 2_S4P6 | AO88: =$AL$3-AK88 -> #VALUE! | AP88: =IFERROR(VLOOKUP(Z88,'PASTE-DL-ALARMS'!$Q$10:$Z$2800,8,FALSE),"")
C89: =IF(D89="Critical",MAX($C$8:C88)+1,"") | D89: =TRIM(CLEAN(P89)) -> - | E89: =VLOOKUP('PASTE-DOWN-DL'!F89,'SSA-CODE'!$D$4:$E$56,2,FALSE) -> VDA | F89: =TRIM(CLEAN(SUBSTITUTE(G89,CHAR(160)," "))) -> SSA VDR | G89: =MID(I89,1,SEARCH("-",I89)-1) -> SSA VDR | H89: 80 | I89: SSA VDR-10.121.19.147-VrujSidhi_BTS_S1P5-10.121.19.164-GujVMSS_Kanderao_S1P6 | J89: Fiber | K89: GE | L89: Eth | M89: BI-DIR | N89: 10.121.19.147_VRUJSIDDHI-BTS_TN703B_GJ_SSA VDR_PH2\S1P5 | O89: 10.121.19.164_VMSS Khanderao_TN703B_GJ_SSA VDR_PH2\S1P6 | P89: - | Q89: 54 | R89: 100 | S89: GCS Issue id : 17852 | T89: minaxikataria | V89: 1.0 | W89: 2022/08/03,14:10:26 | X89: 2022/08/04,14:11:46 | Z89: =TRIM(CLEAN(I89)) -> SSA VDR-10.121.19.147-VrujSidhi_BTS_S1P5-10.121.19.164-GujVMSS_Kanderao_S1P6 | AA89: =SEARCH("_",N89) -> 15 | AB89: =SEARCH("_TN7",N89) -> 30 | AC89: =SEARCH("_",O89) -> 15 | AD89: =SEARCH("_TN7",O89) -> 30 | AE89: =TRIM(CLEAN(MID(N89,1,SEARCH("_",N89)-1))) -> 10.121.19.147 | AF89: =TRIM(CLEAN(MID(O89,1,SEARCH("_",O89)-1))) -> 10.121.19.164 | AG89: =MID(N89,AA89+1,AB89-AA89-1) -> VRUJSIDDHI-BTS | AH89: =MID(O89,AC89+1,AD89-AC89-1) -> VMSS Khanderao | AI89: =RIGHT(N89,LEN(N89)-SEARCH("\",N89)) -> S1P5 | AJ89: =RIGHT(O89,LEN(O89)-SEARCH("\",O89)) -> S1P6 | AK89: =IFERROR(VLOOKUP(Z89,'PASTE-DL-ALARMS'!$Q$10:$W$2200,7,FALSE),"") | AL89: =IFERROR(VLOOKUP(Z89,'PASTE-DL-ALARMS'!$Q$10:$W$2200,3,FALSE),"") | AM89: =CONCATENATE(AE89,"_",AG89,"_",AI89) -> 10.121.19.147_VRUJSIDDHI-BTS_S1P5 | AN89: =CONCATENATE(AF89,"_",AH89,"_",AJ89) -> 10.121.19.164_VMSS Khanderao_S1P6 | AO89: =$AL$3-AK89 -> #VALUE! | AP89: =IFERROR(VLOOKUP(Z89,'PASTE-DL-ALARMS'!$Q$10:$Z$2800,8,FALSE),"")
C90: =IF(D90="Critical",MAX($C$8:C89)+1,"") | D90: =TRIM(CLEAN(P90)) -> - | E90: =VLOOKUP('PASTE-DOWN-DL'!F90,'SSA-CODE'!$D$4:$E$56,2,FALSE) -> AMR | F90: =TRIM(CLEAN(SUBSTITUTE(G90,CHAR(160)," "))) -> SSA AMR | G90: =MID(I90,1,SEARCH("-",I90)-1) -> SSA AMR | H90: 81 | I90: SSA AMR-10.121.96.3-AMBARDI B1_4/1-10.121.96.33-THORDI B1_3/1 | J90: Fiber | K90: 10GE | L90: Eth | M90: BI-DIR | N90: 10.121.96.3_AMBARDI_TN705B_GJ_SSA AMR_PH3\S4P1 | O90: 10.121.96.33_THORDI_TN705B_WTR_RJ_PH2\S3P1 | P90: - | Q90: 21 | R90: 30 | S90: Guj_Amreli-SSA_GCS_ID-0008557 | T90: 200904043 | U90: Guj_Amreli-SSA_GCS_ID-0008557 | V90: 1.0 | W90: 2020/11/07,13:18:56 | X90: 2026/04/14,15:41:15 | Z90: =TRIM(CLEAN(I90)) -> SSA AMR-10.121.96.3-AMBARDI B1_4/1-10.121.96.33-THORDI B1_3/1 | AA90: =SEARCH("_",N90) -> 13 | AB90: =SEARCH("_TN7",N90) -> 21 | AC90: =SEARCH("_",O90) -> 14 | AD90: =SEARCH("_TN7",O90) -> 21 | AE90: =TRIM(CLEAN(MID(N90,1,SEARCH("_",N90)-1))) -> 10.121.96.3 | AF90: =TRIM(CLEAN(MID(O90,1,SEARCH("_",O90)-1))) -> 10.121.96.33 | AG90: =MID(N90,AA90+1,AB90-AA90-1) -> AMBARDI | AH90: =MID(O90,AC90+1,AD90-AC90-1) -> THORDI | AI90: =RIGHT(N90,LEN(N90)-SEARCH("\",N90)) -> S4P1 | AJ90: =RIGHT(O90,LEN(O90)-SEARCH("\",O90)) -> S3P1 | AK90: =IFERROR(VLOOKUP(Z90,'PASTE-DL-ALARMS'!$Q$10:$W$2200,7,FALSE),"") | AL90: =IFERROR(VLOOKUP(Z90,'PASTE-DL-ALARMS'!$Q$10:$W$2200,3,FALSE),"") | AM90: =CONCATENATE(AE90,"_",AG90,"_",AI90) -> 10.121.96.3_AMBARDI_S4P1 | AN90: =CONCATENATE(AF90,"_",AH90,"_",AJ90) -> 10.121.96.33_THORDI_S3P1 | AO90: =$AL$3-AK90 -> #VALUE! | AP90: =IFERROR(VLOOKUP(Z90,'PASTE-DL-ALARMS'!$Q$10:$Z$2800,8,FALSE),"")
C91: =IF(D91="Critical",MAX($C$8:C90)+1,"") | D91: =TRIM(CLEAN(P91)) -> - | E91: =VLOOKUP('PASTE-DOWN-DL'!F91,'SSA-CODE'!$D$4:$E$56,2,FALSE) -> MSN | F91: =TRIM(CLEAN(SUBSTITUTE(G91,CHAR(160)," "))) -> SSA MEH | G91: =MID(I91,1,SEARCH("-",I91)-1) -> SSA MEH | H91: 82 | I91: SSA MEH-10.121.25.79-GujMehsana_DNE_A1 / S1P5-10.121.15.14-Patan_B2 / S6P6 | J91: Fiber | K91: GE | L91: Eth | M91: BI-DIR | N91: 10.121.15.142_Patan_TN725B_WTR_AM_PH2\S6P6 | O91: 10.121.25.79_DNE_TN703B_GJ_SSA MEH_PH2\S1P5 | P91: - | Q91: 5 | R91: 96 | S91: Mehsana SSA - GCS ID 0001090 | T91: niharbhatt | U91: Mehsana SSA | V91: 1.0 | W91: 2019/01/08,12:46:45 | X91: 2023/01/09,17:27:17 | Z91: =TRIM(CLEAN(I91)) -> SSA MEH-10.121.25.79-GujMehsana_DNE_A1 / S1P5-10.121.15.14-Patan_B2 / S6P6 | AA91: =SEARCH("_",N91) -> 15 | AB91: =SEARCH("_TN7",N91) -> 21 | AC91: =SEARCH("_",O91) -> 14 | AD91: =SEARCH("_TN7",O91) -> 18 | AE91: =TRIM(CLEAN(MID(N91,1,SEARCH("_",N91)-1))) -> 10.121.15.142 | AF91: =TRIM(CLEAN(MID(O91,1,SEARCH("_",O91)-1))) -> 10.121.25.79 | AG91: =MID(N91,AA91+1,AB91-AA91-1) -> Patan | AH91: =MID(O91,AC91+1,AD91-AC91-1) -> DNE | AI91: =RIGHT(N91,LEN(N91)-SEARCH("\",N91)) -> S6P6 | AJ91: =RIGHT(O91,LEN(O91)-SEARCH("\",O91)) -> S1P5 | AK91: =IFERROR(VLOOKUP(Z91,'PASTE-DL-ALARMS'!$Q$10:$W$2200,7,FALSE),"") | AL91: =IFERROR(VLOOKUP(Z91,'PASTE-DL-ALARMS'!$Q$10:$W$2200,3,FALSE),"") | AM91: =CONCATENATE(AE91,"_",AG91,"_",AI91) -> 10.121.15.142_Patan_S6P6 | AN91: =CONCATENATE(AF91,"_",AH91,"_",AJ91) -> 10.121.25.79_DNE_S1P5 | AO91: =$AL$3-AK91 -> #VALUE! | AP91: =IFERROR(VLOOKUP(Z91,'PASTE-DL-ALARMS'!$Q$10:$Z$2800,8,FALSE),"")
C92: =IF(D92="Critical",MAX($C$8:C91)+1,"") | D92: =TRIM(CLEAN(P92)) -> - | E92: =VLOOKUP('PASTE-DOWN-DL'!F92,'SSA-CODE'!$D$4:$E$56,2,FALSE) -> WTR RJ | F92: =TRIM(CLEAN(SUBSTITUTE(G92,CHAR(160)," "))) -> WTR RJ | G92: =MID(I92,1,SEARCH("-",I92)-1) -> WTR RJ | H92: 83 | I92: WTR RJ-10.121.17.27-RAJKOT-KR B2_4/1-10.121.68.203-KALAWAD B2_5/1 | J92: Fiber | K92: 10GE | L92: Eth | M92: BI-DIR | N92: 10.121.17.27_RAJKOT KR_TN725B_WTR_RJ_PH3\S4P1 | O92: 10.121.68.203_KALAWAD_TN725B_WTR_RJ_PH3\S5P1 | P92: - | Q92: 64 | R92: 100 | T92: kanishk | V92: 1.0 | W92: 2019/06/10,16:10:50 | X92: 2026/04/14,15:44:05 | Y92: KR-BKT 96F/2,6 + BKT-KALAWAD UTL LAMBDA 14 | Z92: =TRIM(CLEAN(I92)) -> WTR RJ-10.121.17.27-RAJKOT-KR B2_4/1-10.121.68.203-KALAWAD B2_5/1 | AA92: =SEARCH("_",N92) -> 14 | AB92: =SEARCH("_TN7",N92) -> 24 | AC92: =SEARCH("_",O92) -> 15 | AD92: =SEARCH("_TN7",O92) -> 23 | AE92: =TRIM(CLEAN(MID(N92,1,SEARCH("_",N92)-1))) -> 10.121.17.27 | AF92: =TRIM(CLEAN(MID(O92,1,SEARCH("_",O92)-1))) -> 10.121.68.203 | AG92: =MID(N92,AA92+1,AB92-AA92-1) -> RAJKOT KR | AH92: =MID(O92,AC92+1,AD92-AC92-1) -> KALAWAD | AI92: =RIGHT(N92,LEN(N92)-SEARCH("\",N92)) -> S4P1 | AJ92: =RIGHT(O92,LEN(O92)-SEARCH("\",O92)) -> S5P1 | AK92: =IFERROR(VLOOKUP(Z92,'PASTE-DL-ALARMS'!$Q$10:$W$2200,7,FALSE),"") | AL92: =IFERROR(VLOOKUP(Z92,'PASTE-DL-ALARMS'!$Q$10:$W$2200,3,FALSE),"") | AM92: =CONCATENATE(AE92,"_",AG92,"_",AI92) -> 10.121.17.27_RAJKOT KR_S4P1 | AN92: =CONCATENATE(AF92,"_",AH92,"_",AJ92) -> 10.121.68.203_KALAWAD_S5P1 | AO92: =$AL$3-AK92 -> #VALUE! | AP92: =IFERROR(VLOOKUP(Z92,'PASTE-DL-ALARMS'!$Q$10:$Z$2800,8,FALSE),"")
C93: =IF(D93="Critical",MAX($C$8:C92)+1,"") | D93: =TRIM(CLEAN(P93)) -> - | E93: =VLOOKUP('PASTE-DOWN-DL'!F93,'SSA-CODE'!$D$4:$E$56,2,FALSE) -> VAL | F93: =TRIM(CLEAN(SUBSTITUTE(G93,CHAR(160)," "))) -> SSA VAL | G93: =MID(I93,1,SEARCH("-",I93)-1) -> SSA VAL | H93: 84 | I93: SSA VAL-10.121.68.97-GST-BHAVAN-1/6-10.121.16.99-DAMAN_3/5 | J93: Fiber | K93: GE | L93: Eth | M93: BI-DIR | N93: 10.121.68.91_GST Bhavan_TN703B_GJ_SSA VAL_PH3\S1P6 | O93: 10.121.16.99_Daman_TN725B_GJ_SSA VAL_PH2\S3P5 | P93: - | Q93: 12 | R93: 100 | S93: GCS-48422 | T93: 200800474 | U93: GCS-48422 | V93: 1.0 | W93: 2026/01/27,13:49:48 | X93: 2026/02/12,15:38:50 | Z93: =TRIM(CLEAN(I93)) -> SSA VAL-10.121.68.97-GST-BHAVAN-1/6-10.121.16.99-DAMAN_3/5 | AA93: =SEARCH("_",N93) -> 14 | AB93: =SEARCH("_TN7",N93) -> 25 | AC93: =SEARCH("_",O93) -> 14 | AD93: =SEARCH("_TN7",O93) -> 20 | AE93: =TRIM(CLEAN(MID(N93,1,SEARCH("_",N93)-1))) -> 10.121.68.91 | AF93: =TRIM(CLEAN(MID(O93,1,SEARCH("_",O93)-1))) -> 10.121.16.99 | AG93: =MID(N93,AA93+1,AB93-AA93-1) -> GST Bhavan | AH93: =MID(O93,AC93+1,AD93-AC93-1) -> Daman | AI93: =RIGHT(N93,LEN(N93)-SEARCH("\",N93)) -> S1P6 | AJ93: =RIGHT(O93,LEN(O93)-SEARCH("\",O93)) -> S3P5 | AK93: =IFERROR(VLOOKUP(Z93,'PASTE-DL-ALARMS'!$Q$10:$W$2200,7,FALSE),"") | AL93: =IFERROR(VLOOKUP(Z93,'PASTE-DL-ALARMS'!$Q$10:$W$2200,3,FALSE),"") | AM93: =CONCATENATE(AE93,"_",AG93,"_",AI93) -> 10.121.68.91_GST Bhavan_S1P6 | AN93: =CONCATENATE(AF93,"_",AH93,"_",AJ93) -> 10.121.16.99_Daman_S3P5 | AO93: =$AL$3-AK93 -> #VALUE! | AP93: =IFERROR(VLOOKUP(Z93,'PASTE-DL-ALARMS'!$Q$10:$Z$2800,8,FALSE),"")
C94: =IF(D94="Critical",MAX($C$8:C93)+1,"") | D94: =TRIM(CLEAN(P94)) -> - | E94: =VLOOKUP('PASTE-DOWN-DL'!F94,'SSA-CODE'!$D$4:$E$56,2,FALSE) -> WTR RJ | F94: =TRIM(CLEAN(SUBSTITUTE(G94,CHAR(160)," "))) -> WTR RJ | G94: =MID(I94,1,SEARCH("-",I94)-1) -> WTR RJ | H94: 85 | I94: WTR RJ-10.121.17.4-Wakaner_3/1-10.121.17.5-Morbi_4/1 | J94: Fiber | K94: 10GE | L94: Eth | M94: BI-DIR | N94: 10.121.17.5_MORBI_TN725B_WTR_RJ_PH1\S4P1 | O94: 10.121.17.4_WAKANER_TN705B_WTR_RJ_PH1\S3P1 | P94: - | Q94: 14 | R94: 23 | T94: root | V94: 1.0 | W94: 2018/04/11,14:52:30 | X94: 2026/04/23,16:58:54 | Y94: FIBER | Z94: =TRIM(CLEAN(I94)) -> WTR RJ-10.121.17.4-Wakaner_3/1-10.121.17.5-Morbi_4/1 | AA94: =SEARCH("_",N94) -> 13 | AB94: =SEARCH("_TN7",N94) -> 19 | AC94: =SEARCH("_",O94) -> 13 | AD94: =SEARCH("_TN7",O94) -> 21 | AE94: =TRIM(CLEAN(MID(N94,1,SEARCH("_",N94)-1))) -> 10.121.17.5 | AF94: =TRIM(CLEAN(MID(O94,1,SEARCH("_",O94)-1))) -> 10.121.17.4 | AG94: =MID(N94,AA94+1,AB94-AA94-1) -> MORBI | AH94: =MID(O94,AC94+1,AD94-AC94-1) -> WAKANER | AI94: =RIGHT(N94,LEN(N94)-SEARCH("\",N94)) -> S4P1 | AJ94: =RIGHT(O94,LEN(O94)-SEARCH("\",O94)) -> S3P1 | AK94: =IFERROR(VLOOKUP(Z94,'PASTE-DL-ALARMS'!$Q$10:$W$2200,7,FALSE),"") | AL94: =IFERROR(VLOOKUP(Z94,'PASTE-DL-ALARMS'!$Q$10:$W$2200,3,FALSE),"") | AM94: =CONCATENATE(AE94,"_",AG94,"_",AI94) -> 10.121.17.5_MORBI_S4P1 | AN94: =CONCATENATE(AF94,"_",AH94,"_",AJ94) -> 10.121.17.4_WAKANER_S3P1 | AO94: =$AL$3-AK94 -> #VALUE! | AP94: =IFERROR(VLOOKUP(Z94,'PASTE-DL-ALARMS'!$Q$10:$Z$2800,8,FALSE),"")
C95: =IF(D95="Critical",MAX($C$8:C94)+1,"") | D95: =TRIM(CLEAN(P95)) -> - | E95: =VLOOKUP('PASTE-DOWN-DL'!F95,'SSA-CODE'!$D$4:$E$56,2,FALSE) -> WTR AM | F95: =TRIM(CLEAN(SUBSTITUTE(G95,CHAR(160)," "))) -> WTR AM | G95: =MID(I95,1,SEARCH("-",I95)-1) -> WTR AM | H95: 86 | I95: WTR AM-10.121.16.226-BARODA CITY_B2\S3P7-10.121.16.8-BARODA CITY_B2\S3P7 | J95: Twisted-Pair | K95: GE | L95: Eth | M95: BI-DIR | N95: 10.121.16.226_BARODA CITY 3 GNE_TN725B_WTR_AM_PH1\S3P7 | O95: 10.121.16.8_BARODA CITY 1_TN725B_WTR_AM_PH1\S3P7 | P95: - | Q95: 38 | R95: 100 | T95: 200303555 | V95: 1.0 | W95: 2018/08/24,13:36:00 | X95: 2023/08/22,11:27:35 | Z95: =TRIM(CLEAN(I95)) -> WTR AM-10.121.16.226-BARODA CITY_B2\S3P7-10.121.16.8-BARODA CITY_B2\S3P7 | AA95: =SEARCH("_",N95) -> 15 | AB95: =SEARCH("_TN7",N95) -> 33 | AC95: =SEARCH("_",O95) -> 13 | AD95: =SEARCH("_TN7",O95) -> 27 | AE95: =TRIM(CLEAN(MID(N95,1,SEARCH("_",N95)-1))) -> 10.121.16.226 | AF95: =TRIM(CLEAN(MID(O95,1,SEARCH("_",O95)-1))) -> 10.121.16.8 | AG95: =MID(N95,AA95+1,AB95-AA95-1) -> BARODA CITY 3 GNE | AH95: =MID(O95,AC95+1,AD95-AC95-1) -> BARODA CITY 1 | AI95: =RIGHT(N95,LEN(N95)-SEARCH("\",N95)) -> S3P7 | AJ95: =RIGHT(O95,LEN(O95)-SEARCH("\",O95)) -> S3P7 | AK95: =IFERROR(VLOOKUP(Z95,'PASTE-DL-ALARMS'!$Q$10:$W$2200,7,FALSE),"") | AL95: =IFERROR(VLOOKUP(Z95,'PASTE-DL-ALARMS'!$Q$10:$W$2200,3,FALSE),"") | AM95: =CONCATENATE(AE95,"_",AG95,"_",AI95) -> 10.121.16.226_BARODA CITY 3 GNE_S3P7 | AN95: =CONCATENATE(AF95,"_",AH95,"_",AJ95) -> 10.121.16.8_BARODA CITY 1_S3P7 | AO95: =$AL$3-AK95 -> #VALUE! | AP95: =IFERROR(VLOOKUP(Z95,'PASTE-DL-ALARMS'!$Q$10:$Z$2800,8,FALSE),"")
C96: =IF(D96="Critical",MAX($C$8:C95)+1,"") | D96: =TRIM(CLEAN(P96)) -> - | E96: =VLOOKUP('PASTE-DOWN-DL'!F96,'SSA-CODE'!$D$4:$E$56,2,FALSE) -> VAL | F96: =TRIM(CLEAN(SUBSTITUTE(G96,CHAR(160)," "))) -> SSA VAL | G96: =MID(I96,1,SEARCH("-",I96)-1) -> SSA VAL | H96: 87 | I96: SSA VAL-10.121.68.81-JAMBURI CHECKPOST_1/6-10.121.68.69-UPL NAHULI_1/5 | J96: Fiber | K96: GE | L96: Eth | M96: BI-DIR | N96: 10.121.68.81_JAMBURI CHECKPOST_TN703B_GJ_SSA VAL_PH2\S1P6 | O96: 10.121.68.69_UPL NAHULI_TN703B_GJ_SSA VAL_PH2\S1P5 | P96: - | Q96: 5 | R96: 96 | S96: GUJ_VAL_GCSID_48499 | T96: 200300828 | U96: VALSAD SSA | V96: 1.0 | W96: 2026/01/29,18:39:20 | X96: 2026/02/12,15:44:59 | Z96: =TRIM(CLEAN(I96)) -> SSA VAL-10.121.68.81-JAMBURI CHECKPOST_1/6-10.121.68.69-UPL NAHULI_1/5 | AA96: =SEARCH("_",N96) -> 14 | AB96: =SEARCH("_TN7",N96) -> 32 | AC96: =SEARCH("_",O96) -> 14 | AD96: =SEARCH("_TN7",O96) -> 25 | AE96: =TRIM(CLEAN(MID(N96,1,SEARCH("_",N96)-1))) -> 10.121.68.81 | AF96: =TRIM(CLEAN(MID(O96,1,SEARCH("_",O96)-1))) -> 10.121.68.69 | AG96: =MID(N96,AA96+1,AB96-AA96-1) -> JAMBURI CHECKPOST | AH96: =MID(O96,AC96+1,AD96-AC96-1) -> UPL NAHULI | AI96: =RIGHT(N96,LEN(N96)-SEARCH("\",N96)) -> S1P6 | AJ96: =RIGHT(O96,LEN(O96)-SEARCH("\",O96)) -> S1P5 | AK96: =IFERROR(VLOOKUP(Z96,'PASTE-DL-ALARMS'!$Q$10:$W$2200,7,FALSE),"") | AL96: =IFERROR(VLOOKUP(Z96,'PASTE-DL-ALARMS'!$Q$10:$W$2200,3,FALSE),"") | AM96: =CONCATENATE(AE96,"_",AG96,"_",AI96) -> 10.121.68.81_JAMBURI CHECKPOST_S1P6 | AN96: =CONCATENATE(AF96,"_",AH96,"_",AJ96) -> 10.121.68.69_UPL NAHULI_S1P5 | AO96: =$AL$3-AK96 -> #VALUE! | AP96: =IFERROR(VLOOKUP(Z96,'PASTE-DL-ALARMS'!$Q$10:$Z$2800,8,FALSE),"")
C97: =IF(D97="Critical",MAX($C$8:C96)+1,"") | D97: =TRIM(CLEAN(P97)) -> - | E97: =VLOOKUP('PASTE-DOWN-DL'!F97,'SSA-CODE'!$D$4:$E$56,2,FALSE) -> AHD | F97: =TRIM(CLEAN(SUBSTITUTE(G97,CHAR(160)," "))) -> SSA AM | G97: =MID(I97,1,SEARCH("-",I97)-1) -> SSA AM | H97: 88 | I97: SSA AM-10.121.18.65-Navrangpura(GNE)_6/1-10.121.17.200-Naranpura_School_4/1 | J97: Fiber | K97: 10GE | L97: Eth | M97: BI-DIR | N97: 10.121.17.200_NARANPURA SCHOOL_TN705B_GJ_SSA AM_PH1\S4P1 | O97: 10.121.18.65_NAVRANGPURA (GNE)_TN725B_GJ_SSA AM_PH1\S6P1 | P97: - | Q97: 19 | R97: 28 | S97: Ahmedabad SSA GCS Issue id : 0000924 | T97: minaxikataria | U97: Ahmedabad SSA =Navrangpura(GNE) to Naranpura School | V97: 1.0 | W97: 2018/11/06,12:28:37 | X97: 2026/01/20,15:07:26 | Y97: (NVP-ARD 96F 2/2/1&2 at NRP-STD 96F 1/6/1&2) to ( NRP-STD 96F 1/8/3&4...F3&3 AT NRP SCHOOL) | Z97: =TRIM(CLEAN(I97)) -> SSA AM-10.121.18.65-Navrangpura(GNE)_6/1-10.121.17.200-Naranpura_School_4/1 | AA97: =SEARCH("_",N97) -> 15 | AB97: =SEARCH("_TN7",N97) -> 32 | AC97: =SEARCH("_",O97) -> 14 | AD97: =SEARCH("_TN7",O97) -> 32 | AE97: =TRIM(CLEAN(MID(N97,1,SEARCH("_",N97)-1))) -> 10.121.17.200 | AF97: =TRIM(CLEAN(MID(O97,1,SEARCH("_",O97)-1))) -> 10.121.18.65 | AG97: =MID(N97,AA97+1,AB97-AA97-1) -> NARANPURA SCHOOL | AH97: =MID(O97,AC97+1,AD97-AC97-1) -> NAVRANGPURA (GNE) | AI97: =RIGHT(N97,LEN(N97)-SEARCH("\",N97)) -> S4P1 | AJ97: =RIGHT(O97,LEN(O97)-SEARCH("\",O97)) -> S6P1 | AK97: =IFERROR(VLOOKUP(Z97,'PASTE-DL-ALARMS'!$Q$10:$W$2200,7,FALSE),"") | AL97: =IFERROR(VLOOKUP(Z97,'PASTE-DL-ALARMS'!$Q$10:$W$2200,3,FALSE),"") | AM97: =CONCATENATE(AE97,"_",AG97,"_",AI97) -> 10.121.17.200_NARANPURA SCHOOL_S4P1 | AN97: =CONCATENATE(AF97,"_",AH97,"_",AJ97) -> 10.121.18.65_NAVRANGPURA (GNE)_S6P1 | AO97: =$AL$3-AK97 -> #VALUE! | AP97: =IFERROR(VLOOKUP(Z97,'PASTE-DL-ALARMS'!$Q$10:$Z$2800,8,FALSE),"")
C98: =IF(D98="Critical",MAX($C$8:C97)+1,"") | D98: =TRIM(CLEAN(P98)) -> - | E98: =VLOOKUP('PASTE-DOWN-DL'!F98,'SSA-CODE'!$D$4:$E$56,2,FALSE) -> VAL | F98: =TRIM(CLEAN(SUBSTITUTE(G98,CHAR(160)," "))) -> SSA VAL | G98: =MID(I98,1,SEARCH("-",I98)-1) -> SSA VAL | H98: 89 | I98: SSA VAL-10.121.68.85-SAPUTARA_S4P2-10.121.8.23-WANI_S4P5 | J98: Fiber | K98: GE | L98: Eth | M98: BI-DIR | N98: 10.121.68.85_SAPUTARA_TN705B_GJ_SSA VAL_PH3\S4P2 | O98: 10.121.8.23_WANI_TN705B_WTR_MBI_PH2\S4P5 | P98: - | Q98: 24 | R98: 100 | T98: 60330080 | V98: 1.0 | W98: 2020/12/19,16:39:33 | X98: 2026/04/20,15:00:07 | Z98: =TRIM(CLEAN(I98)) -> SSA VAL-10.121.68.85-SAPUTARA_S4P2-10.121.8.23-WANI_S4P5 | AA98: =SEARCH("_",N98) -> 14 | AB98: =SEARCH("_TN7",N98) -> 23 | AC98: =SEARCH("_",O98) -> 13 | AD98: =SEARCH("_TN7",O98) -> 18 | AE98: =TRIM(CLEAN(MID(N98,1,SEARCH("_",N98)-1))) -> 10.121.68.85 | AF98: =TRIM(CLEAN(MID(O98,1,SEARCH("_",O98)-1))) -> 10.121.8.23 | AG98: =MID(N98,AA98+1,AB98-AA98-1) -> SAPUTARA | AH98: =MID(O98,AC98+1,AD98-AC98-1) -> WANI | AI98: =RIGHT(N98,LEN(N98)-SEARCH("\",N98)) -> S4P2 | AJ98: =RIGHT(O98,LEN(O98)-SEARCH("\",O98)) -> S4P5 | AK98: =IFERROR(VLOOKUP(Z98,'PASTE-DL-ALARMS'!$Q$10:$W$2200,7,FALSE),"") | AL98: =IFERROR(VLOOKUP(Z98,'PASTE-DL-ALARMS'!$Q$10:$W$2200,3,FALSE),"") | AM98: =CONCATENATE(AE98,"_",AG98,"_",AI98) -> 10.121.68.85_SAPUTARA_S4P2 | AN98: =CONCATENATE(AF98,"_",AH98,"_",AJ98) -> 10.121.8.23_WANI_S4P5 | AO98: =$AL$3-AK98 -> #VALUE! | AP98: =IFERROR(VLOOKUP(Z98,'PASTE-DL-ALARMS'!$Q$10:$Z$2800,8,FALSE),"")
C99: =IF(D99="Critical",MAX($C$8:C98)+1,"") | D99: =TRIM(CLEAN(P99)) -> - | E99: =VLOOKUP('PASTE-DOWN-DL'!F99,'SSA-CODE'!$D$4:$E$56,2,FALSE) -> AHD | F99: =TRIM(CLEAN(SUBSTITUTE(G99,CHAR(160)," "))) -> SSA AM | G99: =MID(I99,1,SEARCH("-",I99)-1) -> SSA AM | H99: 90 | I99: SSA AM-10.121.18.67-Naranpura3_4/11-10.121.17.204-Naranpura_4/11 | J99: Twisted-Pair | K99: GE | L99: Eth | M99: BI-DIR | N99: 10.121.18.67_NARANPURA 3_TN725B_GJ_SSA AM_PH1\S4P11 | O99: 10.121.17.204_NARANPURA_TN725B_GJ_SSA AM_PH1\S4P11 | P99: - | Q99: 82 | R99: 100 | T99: shivcharan | V99: 1.0 | W99: 2018/12/06,22:53:49 | X99: 2026/01/20,15:38:22 | Z99: =TRIM(CLEAN(I99)) -> SSA AM-10.121.18.67-Naranpura3_4/11-10.121.17.204-Naranpura_4/11 | AA99: =SEARCH("_",N99) -> 14 | AB99: =SEARCH("_TN7",N99) -> 26 | AC99: =SEARCH("_",O99) -> 15 | AD99: =SEARCH("_TN7",O99) -> 25 | AE99: =TRIM(CLEAN(MID(N99,1,SEARCH("_",N99)-1))) -> 10.121.18.67 | AF99: =TRIM(CLEAN(MID(O99,1,SEARCH("_",O99)-1))) -> 10.121.17.204 | AG99: =MID(N99,AA99+1,AB99-AA99-1) -> NARANPURA 3 | AH99: =MID(O99,AC99+1,AD99-AC99-1) -> NARANPURA | AI99: =RIGHT(N99,LEN(N99)-SEARCH("\",N99)) -> S4P11 | AJ99: =RIGHT(O99,LEN(O99)-SEARCH("\",O99)) -> S4P11 | AK99: =IFERROR(VLOOKUP(Z99,'PASTE-DL-ALARMS'!$Q$10:$W$2200,7,FALSE),"") | AL99: =IFERROR(VLOOKUP(Z99,'PASTE-DL-ALARMS'!$Q$10:$W$2200,3,FALSE),"") | AM99: =CONCATENATE(AE99,"_",AG99,"_",AI99) -> 10.121.18.67_NARANPURA 3_S4P11 | AN99: =CONCATENATE(AF99,"_",AH99,"_",AJ99) -> 10.121.17.204_NARANPURA_S4P11 | AO99: =$AL$3-AK99 -> #VALUE! | AP99: =IFERROR(VLOOKUP(Z99,'PASTE-DL-ALARMS'!$Q$10:$Z$2800,8,FALSE),"")
C100: =IF(D100="Critical",MAX($C$8:C99)+1,"") | D100: =TRIM(CLEAN(P100)) -> - | E100: =VLOOKUP('PASTE-DOWN-DL'!F100,'SSA-CODE'!$D$4:$E$56,2,FALSE) -> AHD | F100: =TRIM(CLEAN(SUBSTITUTE(G100,CHAR(160)," "))) -> SSA AM | G100: =MID(I100,1,SEARCH("-",I100)-1) -> SSA AM | H100: 91 | I100: SSA AM-10.121.18.235-Container Corporation_A1_1/5-10.121.18.245-Sector_11_B2_6/6 | J100: Fiber | K100: GE | L100: Eth | M100: BI-DIR | N100: 10.121.18.235_COLLECTOR OFFICE GNR_TN703B_GJ_SSA AM_PH3\S1P5 | O100: 10.121.18.245_SECTOR 11 GNE_TN725B_GJ_SSA AM_PH1\S6P6 | P100: - | Q100: 68 | R100: 100 | S100: Guj_Ahmedabad-SSA_GCS_ID-0023426 | T100: ritesh | U100: Guj_Ahmedabad-SSA_GCS_ID-0023426 | V100: 1.0 | W100: 2023/05/09,18:47:54 | X100: 2023/05/20,11:45:47 | Z100: =TRIM(CLEAN(I100)) -> SSA AM-10.121.18.235-Container Corporation_A1_1/5-10.121.18.245-Sector_11_B2_6/6 | AA100: =SEARCH("_",N100) -> 15 | AB100: =SEARCH("_TN7",N100) -> 36 | AC100: =SEARCH("_",O100) -> 15 | AD100: =SEARCH("_TN7",O100) -> 29 | AE100: =TRIM(CLEAN(MID(N100,1,SEARCH("_",N100)-1))) -> 10.121.18.235 | AF100: =TRIM(CLEAN(MID(O100,1,SEARCH("_",O100)-1))) -> 10.121.18.245 | AG100: =MID(N100,AA100+1,AB100-AA100-1) -> COLLECTOR OFFICE GNR | AH100: =MID(O100,AC100+1,AD100-AC100-1) -> SECTOR 11 GNE | AI100: =RIGHT(N100,LEN(N100)-SEARCH("\",N100)) -> S1P5 | AJ100: =RIGHT(O100,LEN(O100)-SEARCH("\",O100)) -> S6P6 | AK100: =IFERROR(VLOOKUP(Z100,'PASTE-DL-ALARMS'!$Q$10:$W$2200,7,FALSE),"") | AL100: =IFERROR(VLOOKUP(Z100,'PASTE-DL-ALARMS'!$Q$10:$W$2200,3,FALSE),"") | AM100: =CONCATENATE(AE100,"_",AG100,"_",AI100) -> 10.121.18.235_COLLECTOR OFFICE GNR_S1P5 | AN100: =CONCATENATE(AF100,"_",AH100,"_",AJ100) -> 10.121.18.245_SECTOR 11 GNE_S6P6 | AO100: =$AL$3-AK100 -> #VALUE! | AP100: =IFERROR(VLOOKUP(Z100,'PASTE-DL-ALARMS'!$Q$10:$Z$2800,8,FALSE),"")
C101: =IF(D101="Critical",MAX($C$8:C100)+1,"") -> 3 | D101: =TRIM(CLEAN(P101)) -> Critical | E101: =VLOOKUP('PASTE-DOWN-DL'!F101,'SSA-CODE'!$D$4:$E$56,2,FALSE) -> BCH | F101: =TRIM(CLEAN(SUBSTITUTE(G101,CHAR(160)," "))) -> SSA BCH | G101: =MID(I101,1,SEARCH("-",I101)-1) -> SSA BCH | H101: 92 | I101: SSA BCH-10.121.96.91-Kharetha_BTS_1/5-10.121.96.82-Dediapada_ BCH_3/3 | J101: Fiber | K101: GE | L101: Eth | M101: BI-DIR | N101: 10.121.96.82_Dediapada_TN725B_GJ_SSA BCH_PH3\S3P3 | O101: 10.121.96.91_KharethaBTSA1_TN703B_GJ_SSA BCH_PH3\S1P5 | P101: Critical | Q101: 56 | R101: 100 | S101: Bharuch SSA- GCS ID-0007514 | T101: ritesh | U101: Bharuch SSA- | V101: 1.0 | W101: 2020/08/28,15:30:26 | X101: 2025/11/24,11:06:43 | Z101: =TRIM(CLEAN(I101)) -> SSA BCH-10.121.96.91-Kharetha_BTS_1/5-10.121.96.82-Dediapada_ BCH_3/3 | AA101: =SEARCH("_",N101) -> 14 | AB101: =SEARCH("_TN7",N101) -> 24 | AC101: =SEARCH("_",O101) -> 14 | AD101: =SEARCH("_TN7",O101) -> 28 | AE101: =TRIM(CLEAN(MID(N101,1,SEARCH("_",N101)-1))) -> 10.121.96.82 | AF101: =TRIM(CLEAN(MID(O101,1,SEARCH("_",O101)-1))) -> 10.121.96.91 | AG101: =MID(N101,AA101+1,AB101-AA101-1) -> Dediapada | AH101: =MID(O101,AC101+1,AD101-AC101-1) -> KharethaBTSA1 | AI101: =RIGHT(N101,LEN(N101)-SEARCH("\",N101)) -> S3P3 | AJ101: =RIGHT(O101,LEN(O101)-SEARCH("\",O101)) -> S1P5 | AK101: =IFERROR(VLOOKUP(Z101,'PASTE-DL-ALARMS'!$Q$10:$W$2200,7,FALSE),"") -> 15-05-2026 | AL101: =IFERROR(VLOOKUP(Z101,'PASTE-DL-ALARMS'!$Q$10:$W$2200,3,FALSE),"") -> 16:03:00 | AM101: =CONCATENATE(AE101,"_",AG101,"_",AI101) -> 10.121.96.82_Dediapada_S3P3 | AN101: =CONCATENATE(AF101,"_",AH101,"_",AJ101) -> 10.121.96.91_KharethaBTSA1_S1P5 | AO101: =$AL$3-AK101 -> 0 | AP101: =IFERROR(VLOOKUP(Z101,'PASTE-DL-ALARMS'!$Q$10:$Z$2800,8,FALSE),"") -> 2026/05/15,16:03:00
C102: =IF(D102="Critical",MAX($C$8:C101)+1,"") | D102: =TRIM(CLEAN(P102)) -> - | E102: =VLOOKUP('PASTE-DOWN-DL'!F102,'SSA-CODE'!$D$4:$E$56,2,FALSE) -> VAL | F102: =TRIM(CLEAN(SUBSTITUTE(G102,CHAR(160)," "))) -> SSA VAL | G102: =MID(I102,1,SEARCH("-",I102)-1) -> SSA VAL | H102: 93 | I102: SSA VAL-10.121.16.67-Navasari B1_3/2-10.121.68.70_NVS-BOB-RO_2/5 | J102: Fiber | K102: GE | L102: Eth | M102: BI-DIR | N102: 10.121.16.67_NAVASARI_TN725B_WTR_AM_PH2\S3P2 | O102: 10.121.68.70_NMC_TN703B_GJ_SSA VAL_PH2\S2P5 | P102: - | Q102: 29 | R102: 100 | S102: GCS_ID-0047017 | T102: 60070238 | U102: Valsad_SSA | V102: 1.0 | W102: 2025/12/05,21:57:36 | X102: ----/--/--,--:--:-- | Z102: =TRIM(CLEAN(I102)) -> SSA VAL-10.121.16.67-Navasari B1_3/2-10.121.68.70_NVS-BOB-RO_2/5 | AA102: =SEARCH("_",N102) -> 14 | AB102: =SEARCH("_TN7",N102) -> 23 | AC102: =SEARCH("_",O102) -> 14 | AD102: =SEARCH("_TN7",O102) -> 18 | AE102: =TRIM(CLEAN(MID(N102,1,SEARCH("_",N102)-1))) -> 10.121.16.67 | AF102: =TRIM(CLEAN(MID(O102,1,SEARCH("_",O102)-1))) -> 10.121.68.70 | AG102: =MID(N102,AA102+1,AB102-AA102-1) -> NAVASARI | AH102: =MID(O102,AC102+1,AD102-AC102-1) -> NMC | AI102: =RIGHT(N102,LEN(N102)-SEARCH("\",N102)) -> S3P2 | AJ102: =RIGHT(O102,LEN(O102)-SEARCH("\",O102)) -> S2P5 | AK102: =IFERROR(VLOOKUP(Z102,'PASTE-DL-ALARMS'!$Q$10:$W$2200,7,FALSE),"") | AL102: =IFERROR(VLOOKUP(Z102,'PASTE-DL-ALARMS'!$Q$10:$W$2200,3,FALSE),"") | AM102: =CONCATENATE(AE102,"_",AG102,"_",AI102) -> 10.121.16.67_NAVASARI_S3P2 | AN102: =CONCATENATE(AF102,"_",AH102,"_",AJ102) -> 10.121.68.70_NMC_S2P5 | AO102: =$AL$3-AK102 -> #VALUE! | AP102: =IFERROR(VLOOKUP(Z102,'PASTE-DL-ALARMS'!$Q$10:$Z$2800,8,FALSE),"")
C103: =IF(D103="Critical",MAX($C$8:C102)+1,"") | D103: =TRIM(CLEAN(P103)) -> - | E103: =VLOOKUP('PASTE-DOWN-DL'!F103,'SSA-CODE'!$D$4:$E$56,2,FALSE) -> AHD | F103: =TRIM(CLEAN(SUBSTITUTE(G103,CHAR(160)," "))) -> SSA AM | G103: =MID(I103,1,SEARCH("-",I103)-1) -> SSA AM | H103: 94 | I103: SSA AM-10.121.18.241-SECTOR-3-1/5-to-10.121.18.244-Old-Kudasan B1_3/4 | J103: Fiber | K103: GE | L103: Eth | M103: BI-DIR | N103: 10.121.18.244_Old Kudasan_TN705B_GJ_SSA AM_PH3\S3P4 | O103: 10.121.18.241_PDPU_TN703B_GJ_SSA AM_PH2\S1P5 | P103: - | Q103: 5 | R103: 96 | S103: Guj_Ahmedabad-SSA_GCS_ID-0051619 | T103: 00202746 | U103: Guj_Ahmedabad-SSA_GCS_ID-0051619 | V103: 1.0 | W103: 2026/03/20,14:09:29 | X103: 2026/04/04,10:02:36 | Z103: =TRIM(CLEAN(I103)) -> SSA AM-10.121.18.241-SECTOR-3-1/5-to-10.121.18.244-Old-Kudasan B1_3/4 | AA103: =SEARCH("_",N103) -> 15 | AB103: =SEARCH("_TN7",N103) -> 27 | AC103: =SEARCH("_",O103) -> 15 | AD103: =SEARCH("_TN7",O103) -> 20 | AE103: =TRIM(CLEAN(MID(N103,1,SEARCH("_",N103)-1))) -> 10.121.18.244 | AF103: =TRIM(CLEAN(MID(O103,1,SEARCH("_",O103)-1))) -> 10.121.18.241 | AG103: =MID(N103,AA103+1,AB103-AA103-1) -> Old Kudasan | AH103: =MID(O103,AC103+1,AD103-AC103-1) -> PDPU | AI103: =RIGHT(N103,LEN(N103)-SEARCH("\",N103)) -> S3P4 | AJ103: =RIGHT(O103,LEN(O103)-SEARCH("\",O103)) -> S1P5 | AK103: =IFERROR(VLOOKUP(Z103,'PASTE-DL-ALARMS'!$Q$10:$W$2200,7,FALSE),"") | AL103: =IFERROR(VLOOKUP(Z103,'PASTE-DL-ALARMS'!$Q$10:$W$2200,3,FALSE),"") | AM103: =CONCATENATE(AE103,"_",AG103,"_",AI103) -> 10.121.18.244_Old Kudasan_S3P4 | AN103: =CONCATENATE(AF103,"_",AH103,"_",AJ103) -> 10.121.18.241_PDPU_S1P5 | AO103: =$AL$3-AK103 -> #VALUE! | AP103: =IFERROR(VLOOKUP(Z103,'PASTE-DL-ALARMS'!$Q$10:$Z$2800,8,FALSE),"")
...

Sheet PASTE-DL-ALARMS
Q1: 14 | R1: 15 | S1: 16 | T1: 17 | U1: 18 | V1: 19 | W1: 20 | X1: 21 | Y1: 22 | Z1: 23 | AA1: 24 | AB1: 25 | AC1: 26
A2: Don't do any change in GREY colored cells | I2: Paste here --- > CPAN DL Alarms | Q2: 1 | R2: 2 | S2: 3 | T2: 4 | U2: 5 | V2: 6 | W2: 7 | X2: 8 | Y2: 9 | Z2: 10 | AA2: 11 | AB2: 12 | AC2: 13
I4: Alarms | J4: =MAX(D10:D1800) -> 88 | L4: =TEXT(TODAY(),"yyyy/mm/dd") -> 2026/05/15 | M4: Choose Days DOWN | N4: 1
D8: 0 | F8: SN | G8: Alarm ID | H8: Severity | I8: Category | J8: Service Type | K8: Service ID | L8: Create Time | M8: Ack User | N8: Ack Time | O8: Description | P8: Memo
D9: 0 | E9: SN | F9: SN | G9: Alarm ID | H9: Severity | I9: Category | J9: Service Type | K9: Service ID | L9: Create Time | M9: Ack User | N9: Ack Time | O9: Description | P9: Memo | Q9: DL name | R9: Full Date | S9: time | T9: Date | U9: Month | V9: Year | W9: Date -MIX | X9: Date-time mix
D10: =IF(F10="","",MAX($D$8:D9)+1) -> 1 | E10: 1 | F10: 2586278 | G10: Signal_DL_Failure | H10: Critical | I10: QoS | J10: DL | K10: \\\DL=SSA BCH-10.121.16.2-Ankleshwar_S5P1-10.121.100.10-Pipodara_S4P1 | L10: 2026/05/15,16:23:40 | N10: ----/--/--,--:--:-- | O10: Digital Link Layer Failure | Q10: =TRIM(CLEAN(MID(K10,SEARCH("=",K10)+1,LEN(K10)-SEARCH("=",K10)))) -> SSA BCH-10.121.16.2-Ankleshwar_S5P1-10.121.100.10-Pipodara_S4P1 | R10: =TRIM(CLEAN(LEFT(L10,SEARCH(",",L10)-1))) -> 2026/05/15 | S10: =TRIM(CLEAN(RIGHT(L10,LEN(L10)-SEARCH(",",L10)))) -> 16:23:40 | T10: =RIGHT(R10,2) -> 15 | U10: =MID(R10,6,2) -> 05 | V10: =LEFT(R10,4) -> 2026 | W10: =CONCATENATE(T10,"-",U10,"-",V10) -> 15-05-2026 | X10: =L10 -> 2026/05/15,16:23:40
D11: =IF(F11="","",MAX($D$8:D10)+1) -> 2 | E11: 2 | F11: 2586211 | G11: Signal_DL_Failure | H11: Critical | I11: QoS | J11: DL | K11: \\\DL=WTR AM-10.121.26.67-Piplod_4/6-10.121.26.73-Devgadh Baria_3/2 | L11: 2026/05/15,16:23:36 | N11: ----/--/--,--:--:-- | O11: Digital Link Layer Failure | Q11: =TRIM(CLEAN(MID(K11,SEARCH("=",K11)+1,LEN(K11)-SEARCH("=",K11)))) -> WTR AM-10.121.26.67-Piplod_4/6-10.121.26.73-Devgadh Baria_3/2 | R11: =TRIM(CLEAN(LEFT(L11,SEARCH(",",L11)-1))) -> 2026/05/15 | S11: =TRIM(CLEAN(RIGHT(L11,LEN(L11)-SEARCH(",",L11)))) -> 16:23:36 | T11: =RIGHT(R11,2) -> 15 | U11: =MID(R11,6,2) -> 05 | V11: =LEFT(R11,4) -> 2026 | W11: =CONCATENATE(T11,"-",U11,"-",V11) -> 15-05-2026 | X11: =L11 -> 2026/05/15,16:23:36
D12: =IF(F12="","",MAX($D$8:D11)+1) -> 3 | E12: 3 | F12: 2586211 | G12: Signal_DL_Failure | H12: Critical | I12: QoS | J12: DL | K12: \\\DL=WTR AM-10.121.26.67-Piplod_4/6-10.121.26.73-Devgadh Baria_3/2 | L12: 2026/05/15,16:23:36 | N12: ----/--/--,--:--:-- | O12: Digital Link Layer Failure | Q12: =TRIM(CLEAN(MID(K12,SEARCH("=",K12)+1,LEN(K12)-SEARCH("=",K12)))) -> WTR AM-10.121.26.67-Piplod_4/6-10.121.26.73-Devgadh Baria_3/2 | R12: =TRIM(CLEAN(LEFT(L12,SEARCH(",",L12)-1))) -> 2026/05/15 | S12: =TRIM(CLEAN(RIGHT(L12,LEN(L12)-SEARCH(",",L12)))) -> 16:23:36 | T12: =RIGHT(R12,2) -> 15 | U12: =MID(R12,6,2) -> 05 | V12: =LEFT(R12,4) -> 2026 | W12: =CONCATENATE(T12,"-",U12,"-",V12) -> 15-05-2026 | X12: =L12 -> 2026/05/15,16:23:36
D13: =IF(F13="","",MAX($D$8:D12)+1) -> 4 | E13: 4 | F13: 2585894 | G13: Signal_DL_Failure | H13: Critical | I13: QoS | J13: DL | K13: \\\DL=SSA VAL-10.121.16.107-KAPRADA_4/3-10.121.24.167-DAPADA_4/2 | L13: 2026/05/15,16:22:47 | N13: ----/--/--,--:--:-- | O13: Digital Link Layer Failure | Q13: =TRIM(CLEAN(MID(K13,SEARCH("=",K13)+1,LEN(K13)-SEARCH("=",K13)))) -> SSA VAL-10.121.16.107-KAPRADA_4/3-10.121.24.167-DAPADA_4/2 | R13: =TRIM(CLEAN(LEFT(L13,SEARCH(",",L13)-1))) -> 2026/05/15 | S13: =TRIM(CLEAN(RIGHT(L13,LEN(L13)-SEARCH(",",L13)))) -> 16:22:47 | T13: =RIGHT(R13,2) -> 15 | U13: =MID(R13,6,2) -> 05 | V13: =LEFT(R13,4) -> 2026 | W13: =CONCATENATE(T13,"-",U13,"-",V13) -> 15-05-2026 | X13: =L13 -> 2026/05/15,16:22:47
D14: =IF(F14="","",MAX($D$8:D13)+1) -> 5 | E14: 5 | F14: 2584696 | G14: Signal_DL_Failure | H14: Critical | I14: QoS | J14: DL | K14: \\\DL=WTR AM-10.121.26.70-Dahod B2_5/1-10.121.16.193-Bhadra(GNE)3 B2_5/1 | L14: 2026/05/15,16:21:33 | N14: ----/--/--,--:--:-- | O14: Digital Link Layer Failure | Q14: =TRIM(CLEAN(MID(K14,SEARCH("=",K14)+1,LEN(K14)-SEARCH("=",K14)))) -> WTR AM-10.121.26.70-Dahod B2_5/1-10.121.16.193-Bhadra(GNE)3 B2_5/1 | R14: =TRIM(CLEAN(LEFT(L14,SEARCH(",",L14)-1))) -> 2026/05/15 | S14: =TRIM(CLEAN(RIGHT(L14,LEN(L14)-SEARCH(",",L14)))) -> 16:21:33 | T14: =RIGHT(R14,2) -> 15 | U14: =MID(R14,6,2) -> 05 | V14: =LEFT(R14,4) -> 2026 | W14: =CONCATENATE(T14,"-",U14,"-",V14) -> 15-05-2026 | X14: =L14 -> 2026/05/15,16:21:33
D15: =IF(F15="","",MAX($D$8:D14)+1) -> 6 | E15: 6 | F15: 2583052 | G15: Signal_DL_Failure | H15: Critical | I15: QoS | J15: DL | K15: \\\DL=SSA HMR-10.121.25.164-Mahavirnagar B1_4/9-10.121.97.81-Mahavirnagar-1 A1_1/3 | L15: 2026/05/15,16:18:27 | N15: ----/--/--,--:--:-- | O15: Digital Link Layer Failure | Q15: =TRIM(CLEAN(MID(K15,SEARCH("=",K15)+1,LEN(K15)-SEARCH("=",K15)))) -> SSA HMR-10.121.25.164-Mahavirnagar B1_4/9-10.121.97.81-Mahavirnagar-1 A1_1/3 | R15: =TRIM(CLEAN(LEFT(L15,SEARCH(",",L15)-1))) -> 2026/05/15 | S15: =TRIM(CLEAN(RIGHT(L15,LEN(L15)-SEARCH(",",L15)))) -> 16:18:27 | T15: =RIGHT(R15,2) -> 15 | U15: =MID(R15,6,2) -> 05 | V15: =LEFT(R15,4) -> 2026 | W15: =CONCATENATE(T15,"-",U15,"-",V15) -> 15-05-2026 | X15: =L15 -> 2026/05/15,16:18:27
D16: =IF(F16="","",MAX($D$8:D15)+1) -> 7 | E16: 7 | F16: 2581780 | G16: Signal_DL_Failure | H16: Critical | I16: QoS | J16: DL | K16: \\\DL=SSA PNP-10.121.25.152-Sutharnesadi A1_2/5-10.121.25.153-Madka A1_1/5 | L16: 2026/05/15,16:15:52 | N16: ----/--/--,--:--:-- | O16: Digital Link Layer Failure | Q16: =TRIM(CLEAN(MID(K16,SEARCH("=",K16)+1,LEN(K16)-SEARCH("=",K16)))) -> SSA PNP-10.121.25.152-Sutharnesadi A1_2/5-10.121.25.153-Madka A1_1/5 | R16: =TRIM(CLEAN(LEFT(L16,SEARCH(",",L16)-1))) -> 2026/05/15 | S16: =TRIM(CLEAN(RIGHT(L16,LEN(L16)-SEARCH(",",L16)))) -> 16:15:52 | T16: =RIGHT(R16,2) -> 15 | U16: =MID(R16,6,2) -> 05 | V16: =LEFT(R16,4) -> 2026 | W16: =CONCATENATE(T16,"-",U16,"-",V16) -> 15-05-2026 | X16: =L16 -> 2026/05/15,16:15:52
D17: =IF(F17="","",MAX($D$8:D16)+1) -> 8 | E17: 8 | F17: 2579426 | G17: Signal_DL_Failure | H17: Critical | I17: QoS | J17: DL | K17: \\\DL=WTR RJ-10.121.17.43-RIBDA_B1_S3P1-10.121.17.9-Bhakti_Nagar_B2_PH1_S4P1 | L17: 2026/05/15,16:10:42 | N17: ----/--/--,--:--:-- | O17: Digital Link Layer Failure | Q17: =TRIM(CLEAN(MID(K17,SEARCH("=",K17)+1,LEN(K17)-SEARCH("=",K17)))) -> WTR RJ-10.121.17.43-RIBDA_B1_S3P1-10.121.17.9-Bhakti_Nagar_B2_PH1_S4P1 | R17: =TRIM(CLEAN(LEFT(L17,SEARCH(",",L17)-1))) -> 2026/05/15 | S17: =TRIM(CLEAN(RIGHT(L17,LEN(L17)-SEARCH(",",L17)))) -> 16:10:42 | T17: =RIGHT(R17,2) -> 15 | U17: =MID(R17,6,2) -> 05 | V17: =LEFT(R17,4) -> 2026 | W17: =CONCATENATE(T17,"-",U17,"-",V17) -> 15-05-2026 | X17: =L17 -> 2026/05/15,16:10:42
D18: =IF(F18="","",MAX($D$8:D17)+1) -> 9 | E18: 9 | F18: 2579486 | G18: Signal_DL_Failure | H18: Critical | I18: QoS | J18: DL | K18: \\\DL=SSA RJK-10.121.17.9-RJ BHAKTINAGAR_4/6-TO-10.121.17.52-SHAPAR_4/6 | L18: 2026/05/15,16:10:39 | N18: ----/--/--,--:--:-- | O18: Digital Link Layer Failure | Q18: =TRIM(CLEAN(MID(K18,SEARCH("=",K18)+1,LEN(K18)-SEARCH("=",K18)))) -> SSA RJK-10.121.17.9-RJ BHAKTINAGAR_4/6-TO-10.121.17.52-SHAPAR_4/6 | R18: =TRIM(CLEAN(LEFT(L18,SEARCH(",",L18)-1))) -> 2026/05/15 | S18: =TRIM(CLEAN(RIGHT(L18,LEN(L18)-SEARCH(",",L18)))) -> 16:10:39 | T18: =RIGHT(R18,2) -> 15 | U18: =MID(R18,6,2) -> 05 | V18: =LEFT(R18,4) -> 2026 | W18: =CONCATENATE(T18,"-",U18,"-",V18) -> 15-05-2026 | X18: =L18 -> 2026/05/15,16:10:39
D19: =IF(F19="","",MAX($D$8:D18)+1) -> 10 | E19: 10 | F19: 2579239 | G19: Signal_DL_Failure | H19: Critical | I19: QoS | J19: DL | K19: \\\DL=SSA BV-10.121.96.200-GHOGHA B1_4/2-10.121.96.212-KOLIYAK A1_2/5 | L19: 2026/05/15,16:10:03 | N19: ----/--/--,--:--:-- | O19: Digital Link Layer Failure | Q19: =TRIM(CLEAN(MID(K19,SEARCH("=",K19)+1,LEN(K19)-SEARCH("=",K19)))) -> SSA BV-10.121.96.200-GHOGHA B1_4/2-10.121.96.212-KOLIYAK A1_2/5 | R19: =TRIM(CLEAN(LEFT(L19,SEARCH(",",L19)-1))) -> 2026/05/15 | S19: =TRIM(CLEAN(RIGHT(L19,LEN(L19)-SEARCH(",",L19)))) -> 16:10:03 | T19: =RIGHT(R19,2) -> 15 | U19: =MID(R19,6,2) -> 05 | V19: =LEFT(R19,4) -> 2026 | W19: =CONCATENATE(T19,"-",U19,"-",V19) -> 15-05-2026 | X19: =L19 -> 2026/05/15,16:10:03
D20: =IF(F20="","",MAX($D$8:D19)+1) -> 11 | E20: 11 | F20: 2577203 | G20: Signal_DL_Failure | H20: Critical | I20: QoS | J20: DL | K20: \\\DL=SSA BCH-10.121.96.74-IKHAR_4/1-10.121.16.15-Palej_5/1 | L20: 2026/05/15,16:05:53 | N20: ----/--/--,--:--:-- | O20: Digital Link Layer Failure | Q20: =TRIM(CLEAN(MID(K20,SEARCH("=",K20)+1,LEN(K20)-SEARCH("=",K20)))) -> SSA BCH-10.121.96.74-IKHAR_4/1-10.121.16.15-Palej_5/1 | R20: =TRIM(CLEAN(LEFT(L20,SEARCH(",",L20)-1))) -> 2026/05/15 | S20: =TRIM(CLEAN(RIGHT(L20,LEN(L20)-SEARCH(",",L20)))) -> 16:05:53 | T20: =RIGHT(R20,2) -> 15 | U20: =MID(R20,6,2) -> 05 | V20: =LEFT(R20,4) -> 2026 | W20: =CONCATENATE(T20,"-",U20,"-",V20) -> 15-05-2026 | X20: =L20 -> 2026/05/15,16:05:53
D21: =IF(F21="","",MAX($D$8:D20)+1) -> 12 | E21: 12 | F21: 2575691 | G21: Signal_DL_Failure | H21: Critical | I21: QoS | J21: DL | K21: \\\DL=SSA BCH-10.121.96.91-Kharetha_BTS_1/5-10.121.96.82-Dediapada_ BCH_3/3 | L21: 2026/05/15,16:03:00 | N21: ----/--/--,--:--:-- | O21: Digital Link Layer Failure | Q21: =TRIM(CLEAN(MID(K21,SEARCH("=",K21)+1,LEN(K21)-SEARCH("=",K21)))) -> SSA BCH-10.121.96.91-Kharetha_BTS_1/5-10.121.96.82-Dediapada_ BCH_3/3 | R21: =TRIM(CLEAN(LEFT(L21,SEARCH(",",L21)-1))) -> 2026/05/15 | S21: =TRIM(CLEAN(RIGHT(L21,LEN(L21)-SEARCH(",",L21)))) -> 16:03:00 | T21: =RIGHT(R21,2) -> 15 | U21: =MID(R21,6,2) -> 05 | V21: =LEFT(R21,4) -> 2026 | W21: =CONCATENATE(T21,"-",U21,"-",V21) -> 15-05-2026 | X21: =L21 -> 2026/05/15,16:03:00
... D30: =IF(F30="","",MAX($D$8:D29)+1) -> 21 | E30: 21 | F30: 2542112 | G30: Signal_DL_Failure | H30: Critical | I30: QoS | J30: DL | K30: \\\DL=SSA SR-10.121.100.22-NIZER_4/3-10.121.100.19-SONGADH FORT_3/3 | L30: 2026/05/15,14:54:09 | N30: ----/--/--,--:--:-- | O30: Digital Link Layer Failure | Q30: =TRIM(CLEAN(MID(K30,SEARCH("=",K30)+1,LEN(K30)-SEARCH("=",K30)))) -> SSA SR-10.121.100.22-NIZER_4/3-10.121.100.19-SONGADH FORT_3/3 | R30: =TRIM(CLEAN(LEFT(L30,SEARCH(",",L30)-1))) -> 2026/05/15 | S30: =TRIM(CLEAN(RIGHT(L30,LEN(L30)-SEARCH(",",L30)))) -> 14:54:09 | T30: =RIGHT(R30,2) -> 15 | U30: =MID(R30,6,2) -> 05 | V30: =LEFT(R30,4) -> 2026 | W30: =CONCATENATE(T30,"-",U30,"-",V30) -> 15-05-2026 | X30: =L30 -> 2026/05/15,14:54:09
D31: =IF(F31="","",MAX($D$8:D30)+1) -> 22 | E31: 22 | F31: 2530086 | G31: Signal_DL_Failure | H31: Critical | I31: QoS | J31: DL | K31: \\\DL=WTR RJ-10.121.17.44-Gondal_B2 / S4P1-10.121.17.43-Ribda_B1 / S4P1 | L31: 2026/05/15,14:33:04 | M31: 201300343 | N31: 2026/05/15,14:39:44 | O31: Digital Link Layer Failure | Q31: =TRIM(CLEAN(MID(K31,SEARCH("=",K31)+1,LEN(K31)-SEARCH("=",K31)))) -> WTR RJ-10.121.17.44-Gondal_B2 / S4P1-10.121.17.43-Ribda_B1 / S4P1 | R31: =TRIM(CLEAN(LEFT(L31,SEARCH(",",L31)-1))) -> 2026/05/15 | S31: =TRIM(CLEAN(RIGHT(L31,LEN(L31)-SEARCH(",",L31)))) -> 14:33:04 | T31: =RIGHT(R31,2) -> 15 | U31: =MID(R31,6,2) -> 05 | V31: =LEFT(R31,4) -> 2026 | W31: =CONCATENATE(T31,"-",U31,"-",V31) -> 15-05-2026 | X31: =L31 -> 2026/05/15,14:33:04
D32: =IF(F32="","",MAX($D$8:D31)+1) -> 23 | E32: 23 | F32: 2527003 | G32: Signal_DL_Failure | H32: Critical | I32: QoS | J32: DL | K32: \\\DL=SSA BCH-10.121.24.202-AMIDHARA_BTS_A1-10.121.24.193-GUjBharuch_bharuch town | L32: 2026/05/15,14:26:52 | N32: ----/--/--,--:--:-- | O32: Digital Link Layer Failure | Q32: =TRIM(CLEAN(MID(K32,SEARCH("=",K32)+1,LEN(K32)-SEARCH("=",K32)))) -> SSA BCH-10.121.24.202-AMIDHARA_BTS_A1-10.121.24.193-GUjBharuch_bharuch town | R32: =TRIM(CLEAN(LEFT(L32,SEARCH(",",L32)-1))) -> 2026/05/15 | S32: =TRIM(CLEAN(RIGHT(L32,LEN(L32)-SEARCH(",",L32)))) -> 14:26:52 | T32: =RIGHT(R32,2) -> 15 | U32: =MID(R32,6,2) -> 05 | V32: =LEFT(R32,4) -> 2026 | W32: =CONCATENATE(T32,"-",U32,"-",V32) -> 15-05-2026 | X32: =L32 -> 2026/05/15,14:26:52
D33: =IF(F33="","",MAX($D$8:D32)+1) -> 24 | E33: 24 | F33: 2509030 | G33: Signal_DL_Failure | H33: Critical | I33: QoS | J33: DL | K33: \\\DL=SSA MEH-10.121.98.1-Kadi Ex B2_3/1-10.121.25.115-JOTANA_S4P1 | L33: 2026/05/15,13:52:27 | N33: ----/--/--,--:--:-- | O33: Digital Link Layer Failure | Q33: =TRIM(CLEAN(MID(K33,SEARCH("=",K33)+1,LEN(K33)-SEARCH("=",K33)))) -> SSA MEH-10.121.98.1-Kadi Ex B2_3/1-10.121.25.115-JOTANA_S4P1 | R33: =TRIM(CLEAN(LEFT(L33,SEARCH(",",L33)-1))) -> 2026/05/15 | S33: =TRIM(CLEAN(RIGHT(L33,LEN(L33)-SEARCH(",",L33)))) -> 13:52:27 | T33: =RIGHT(R33,2) -> 15 | U33: =MID(R33,6,2) -> 05 | V33: =LEFT(R33,4) -> 2026 | W33: =CONCATENATE(T33,"-",U33,"-",V33) -> 15-05-2026 | X33: =L33 -> 2026/05/15,13:52:27
D34: =IF(F34="","",MAX($D$8:D33)+1) -> 25 | E34: 25 | F34: 2456406 | G34: Signal_DL_Failure | H34: Critical | I34: QoS | J34: DL | K34: \\\DL=SSA NAD-10.121.16.152-TRAJ A1_1/5-10.121.24.245-MATAR B1_3/4 | L34: 2026/05/15,12:02:41 | N34: ----/--/--,--:--:-- | O34: Digital Link Layer Failure | Q34: =TRIM(CLEAN(MID(K34,SEARCH("=",K34)+1,LEN(K34)-SEARCH("=",K34)))) -> SSA NAD-10.121.16.152-TRAJ A1_1/5-10.121.24.245-MATAR B1_3/4 | R34: =TRIM(CLEAN(LEFT(L34,SEARCH(",",L34)-1))) -> 2026/05/15 | S34: =TRIM(CLEAN(RIGHT(L34,LEN(L34)-SEARCH(",",L34)))) -> 12:02:41 | T34: =RIGHT(R34,2) -> 15 | U34: =MID(R34,6,2) -> 05 | V34: =LEFT(R34,4) -> 2026 | W34: =CONCATENATE(T34,"-",U34,"-",V34) -> 15-05-2026 | X34: =L34 -> 2026/05/15,12:02:41
D35: =IF(F35="","",MAX($D$8:D34)+1) -> 26 | E35: 26 | F35: 2456154 | G35: Signal_DL_Failure | H35: Critical | I35: QoS | J35: DL | K35: \\\DL=SSA JND-10.121.97.218-MANAVADAR_S3P1-10.121.97.201-TN725B_VANTHALI_S5P1 | L35: 2026/05/15,12:01:59 | N35: ----/--/--,--:--:-- | O35: Digital Link Layer Failure | Q35: =TRIM(CLEAN(MID(K35,SEARCH("=",K35)+1,LEN(K35)-SEARCH("=",K35)))) -> SSA JND-10.121.97.218-MANAVADAR_S3P1-10.121.97.201-TN725B_VANTHALI_S5P1 | R35: =TRIM(CLEAN(LEFT(L35,SEARCH(",",L35)-1))) -> 2026/05/15 | S35: =TRIM(CLEAN(RIGHT(L35,LEN(L35)-SEARCH(",",L35)))) -> 12:01:59 | T35: =RIGHT(R35,2) -> 15 | U35: =MID(R35,6,2) -> 05 | V35: =LEFT(R35,4) -> 2026 | W35: =CONCATENATE(T35,"-",U35,"-",V35) -> 15-05-2026 | X35: =L35 -> 2026/05/15,12:01:59
D36: =IF(F36="","",MAX($D$8:D35)+1) -> 27 | E36: 27 | F36: 2443637 | G36: Signal_DL_Failure | H36: Critical | I36: QoS | J36: DL | K36: \\\DL=SSA RJ-10.121.17.38-Ramod_1_1/5-10.121.17.51-KOTADA_3/6 | L36: 2026/05/15,11:37:45 | N36: ----/--/--,--:--:-- | O36: Digital Link Layer Failure | Q36: =TRIM(CLEAN(MID(K36,SEARCH("=",K36)+1,LEN(K36)-SEARCH("=",K36)))) -> SSA RJ-10.121.17.38-Ramod_1_1/5-10.121.17.51-KOTADA_3/6 | R36: =TRIM(CLEAN(LEFT(L36,SEARCH(",",L36)-1))) -> 2026/05/15 | S36: =TRIM(CLEAN(RIGHT(L36,LEN(L36)-SEARCH(",",L36)))) -> 11:37:45 | T36: =RIGHT(R36,2) -> 15 | U36: =MID(R36,6,2) -> 05 | V36: =LEFT(R36,4) -> 2026 | W36: =CONCATENATE(T36,"-",U36,"-",V36) -> 15-05-2026 | X36: =L36 -> 2026/05/15,11:37:45
D37: =IF(F37="","",MAX($D$8:D36)+1) -> 28 | E37: 28 | F37: 2439927 | G37: Signal_DL_Failure | H37: Critical | I37: QoS | J37: DL | K37: \\\DL=SSA SR-10.121.100.19-SONGADH FORT_6/1-10.121.68.6-Mandvi_5/1 | L37: 2026/05/15,11:30:14 | N37: ----/--/--,--:--:-- | O37: Digital Link Layer Failure | Q37: =TRIM(CLEAN(MID(K37,SEARCH("=",K37)+1,LEN(K37)-SEARCH("=",K37)))) -> SSA SR-10.121.100.19-SONGADH FORT_6/1-10.121.68.6-Mandvi_5/1 | R37: =TRIM(CLEAN(LEFT(L37,SEARCH(",",L37)-1))) -> 2026/05/15 | S37: =TRIM(CLEAN(RIGHT(L37,LEN(L37)-SEARCH(",",L37)))) -> 11:30:14 | T37: =RIGHT(R37,2) -> 15 | U37: =MID(R37,6,2) -> 05 | V37: =LEFT(R37,4) -> 2026 | W37: =CONCATENATE(T37,"-",U37,"-",V37) -> 15-05-2026 | X37: =L37 -> 2026/05/15,11:30:14
D38: =IF(F38="","",MAX($D$8:D37)+1) -> 29 | E38: 29 | F38: 2406125 | G38: Signal_DL_Failure | H38: Critical | I38: QoS | J38: DL | K38: \\\DL=SSA VAL-10.121.68.65-VALSAD OLD GNE B2_3/1-10.121.16.81-SUTHARPADA B1_4/1 | L38: 2026/05/15,09:58:50 | N38: ----/--/--,--:--:-- | O38: Digital Link Layer Failure | Q38: =TRIM(CLEAN(MID(K38,SEARCH("=",K38)+1,LEN(K38)-SEARCH("=",K38)))) -> SSA VAL-10.121.68.65-VALSAD OLD GNE B2_3/1-10.121.16.81-SUTHARPADA B1_4/1 | R38: =TRIM(CLEAN(LEFT(L38,SEARCH(",",L38)-1))) -> 2026/05/15 | S38: =TRIM(CLEAN(RIGHT(L38,LEN(L38)-SEARCH(",",L38)))) -> 09:58:50 | T38: =RIGHT(R38,2) -> 15 | U38: =MID(R38,6,2) -> 05 | V38: =LEFT(R38,4) -> 2026 | W38: =CONCATENATE(T38,"-",U38,"-",V38) -> 15-05-2026 | X38: =L38 -> 2026/05/15,09:58:50
D39: =IF(F39="","",MAX($D$8:D38)+1) -> 30 | E39: 30 | F39: 2402064 | G39: Signal_DL_Failure | H39: Critical | I39: QoS | J39: DL | K39: \\\DL=SSA BV-10.121.17.138-BHANDARIYA(PALITANA)_1/5-10.121.17.158-PALITANA_5/3 | L39: 2026/05/15,09:48:16 | N39: ----/--/--,--:--:-- | O39: Digital Link Layer Failure | Q39: =TRIM(CLEAN(MID(K39,SEARCH("=",K39)+1,LEN(K39)-SEARCH("=",K39)))) -> SSA BV-10.121.17.138-BHANDARIYA(PALITANA)_1/5-10.121.17.158-PALITANA_5/3 | R39: =TRIM(CLEAN(LEFT(L39,SEARCH(",",L39)-1))) -> 2026/05/15 | S39: =TRIM(CLEAN(RIGHT(L39,LEN(L39)-SEARCH(",",L39)))) -> 09:48:16 | T39: =RIGHT(R39,2) -> 15 | U39: =MID(R39,6,2) -> 05 | V39: =LEFT(R39,4) -> 2026 | W39: =CONCATENATE(T39,"-",U39,"-",V39) -> 15-05-2026 | X39: =L39 -> 2026/05/15,09:48:16
D40: =IF(F40="","",MAX($D$8:D39)+1) -> 31 | E40: 31 | F40: 2400672 | G40: Signal_DL_Failure | H40: Critical | I40: QoS | J40: DL | K40: \\\DL=SSA VAL-10.121.68.66-VAPI 2_6/1-10.121.68.103-VALVADA2_3/1 | L40: 2026/05/15,09:44:08 | N40: ----/--/--,--:--:-- | O40: Digital Link Layer Failure | Q40: =TRIM(CLEAN(MID(K40,SEARCH("=",K40)+1,LEN(K40)-SEARCH("=",K40)))) -> SSA VAL-10.121.68.66-VAPI 2_6/1-10.121.68.103-VALVADA2_3/1 | R40: =TRIM(CLEAN(LEFT(L40,SEARCH(",",L40)-1))) -> 2026/05/15 | S40: =TRIM(CLEAN(RIGHT(L40,LEN(L40)-SEARCH(",",L40)))) -> 09:44:08 | T40: =RIGHT(R40,2) -> 15 | U40: =MID(R40,6,2) -> 05 | V40: =LEFT(R40,4) -> 2026 | W40: =CONCATENATE(T40,"-",U40,"-",V40) -> 15-05-2026 | X40: =L40 -> 2026/05/15,09:44:08
D41: =IF(F41="","",MAX($D$8:D40)+1) -> 32 | E41: 32 | F41: 2397688 | G41: Signal_DL_Failure | H41: Critical | I41: QoS | J41: DL | K41: \\\DL=SSA BCH-10.121.24.207-OBHA_SSA BCH_2/5-10.121.24.209-Kharach_SSA BCH_1/5 | L41: 2026/05/15,09:35:08 | N41: ----/--/--,--:--:-- | O41: Digital Link Layer Failure | Q41: =TRIM(CLEAN(MID(K41,SEARCH("=",K41)+1,LEN(K41)-SEARCH("=",K41)))) -> SSA BCH-10.121.24.207-OBHA_SSA BCH_2/5-10.121.24.209-Kharach_SSA BCH_1/5 | R41: =TRIM(CLEAN(LEFT(L41,SEARCH(",",L41)-1))) -> 2026/05/15 | S41: =TRIM(CLEAN(RIGHT(L41,LEN(L41)-SEARCH(",",L41)))) -> 09:35:08 | T41: =RIGHT(R41,2) -> 15 | U41: =MID(R41,6,2) -> 05 | V41: =LEFT(R41,4) -> 2026 | W41: =CONCATENATE(T41,"-",U41,"-",V41) -> 15-05-2026 | X41: =L41 -> 2026/05/15,09:35:08
D42: =IF(F42="","",MAX($D$8:D41)+1) -> 33 | E42: 33 | F42: 2396180 | G42: Signal_DL_Failure | H42: Critical | I42: QoS | J42: DL | K42: \\\DL=SSA NAD-10.121.16.247-Nenpur A1_2/5-10.121.16.248-Ghodasar A1_1/5 | L42: 2026/05/15,09:30:28 | N42: ----/--/--,--:--:-- | O42: Digital Link Layer Failure | Q42: =TRIM(CLEAN(MID(K42,SEARCH("=",K42)+1,LEN(K42)-SEARCH("=",K42)))) -> SSA NAD-10.121.16.247-Nenpur A1_2/5-10.121.16.248-Ghodasar A1_1/5 | R42: =TRIM(CLEAN(LEFT(L42,SEARCH(",",L42)-1))) -> 2026/05/15 | S42: =TRIM(CLEAN(RIGHT(L42,LEN(L42)-SEARCH(",",L42)))) -> 09:30:28 | T42: =RIGHT(R42,2) -> 15 | U42: =MID(R42,6,2) -> 05 | V42: =LEFT(R42,4) -> 2026 | W42: =CONCATENATE(T42,"-",U42,"-",V42) -> 15-05-2026 | X42: =L42 -> 2026/05/15,09:30:28
D43: =IF(F43="","",MAX($D$8:D42)+1) -> 34 | E43: 34 | F43: 2344379 | G43: Signal_DL_Failure | H43: Critical | I43: QoS | J43: DL | K43: \\\DL=SSA JND-10.121.24.34-NAGOA A1_2/6-10.121.97.233-Wanakbara A1_1/5 | L43: 2026/05/15,09:28:45 | N43: ----/--/--,--:--:-- | O43: Digital Link Layer Failure | Q43: =TRIM(CLEAN(MID(K43,SEARCH("=",K43)+1,LEN(K43)-SEARCH("=",K43)))) -> SSA JND-10.121.24.34-NAGOA A1_2/6-10.121.97.233-Wanakbara A1_1/5 | R43: =TRIM(CLEAN(LEFT(L43,SEARCH(",",L43)-1))) -> 2026/05/15 | S43: =TRIM(CLEAN(RIGHT(L43,LEN(L43)-SEARCH(",",L43)))) -> 09:28:45 | T43: =RIGHT(R43,2) -> 15 | U43: =MID(R43,6,2) -> 05 | V43: =LEFT(R43,4) -> 2026 | W43: =CONCATENATE(T43,"-",U43,"-",V43) -> 15-05-2026 | X43: =L43 -> 2026/05/15,09:28:45
... D49: =IF(F49="","",MAX($D$8:D48)+1) -> 40 | E49: 40 | F49: 2195713 | G49: Signal_DL_Failure | H49: Critical | I49: QoS | J49: DL | K49: \\\DL=WTR AM-10.121.26.71-Dhanpur B1_4/1-10.121.26.72-Vedrampur B1_3/1 | L49: 2026/05/14,23:05:32 | N49: ----/--/--,--:--:-- | O49: Digital Link Layer Failure | Q49: =TRIM(CLEAN(MID(K49,SEARCH("=",K49)+1,LEN(K49)-SEARCH("=",K49)))) -> WTR AM-10.121.26.71-Dhanpur B1_4/1-10.121.26.72-Vedrampur B1_3/1 | R49: =TRIM(CLEAN(LEFT(L49,SEARCH(",",L49)-1))) -> 2026/05/14 | S49: =TRIM(CLEAN(RIGHT(L49,LEN(L49)-SEARCH(",",L49)))) -> 23:05:32 | T49: =RIGHT(R49,2) -> 14 | U49: =MID(R49,6,2) -> 05 | V49: =LEFT(R49,4) -> 2026 | W49: =CONCATENATE(T49,"-",U49,"-",V49) -> 14-05-2026 | X49: =L49 -> 2026/05/14,23:05:32
D50: =IF(F50="","",MAX($D$8:D49)+1) -> 41 | E50: 41 | F50: 2171271 | G50: Signal_DL_Failure | H50: Critical | I50: QoS | J50: DL | K50: \\\DL=WTR RJ-10.121.99.8-Sayla_4/3-10.121.99.3-Limbdi_3/3 | L50: 2026/05/14,21:46:06 | M50: 201300343 | N50: 2026/05/15,13:03:15 | O50: Digital Link Layer Failure | Q50: =TRIM(CLEAN(MID(K50,SEARCH("=",K50)+1,LEN(K50)-SEARCH("=",K50)))) -> WTR RJ-10.121.99.8-Sayla_4/3-10.121.99.3-Limbdi_3/3 | R50: =TRIM(CLEAN(LEFT(L50,SEARCH(",",L50)-1))) -> 2026/05/14 | S50: =TRIM(CLEAN(RIGHT(L50,LEN(L50)-SEARCH(",",L50)))) -> 21:46:06 | T50: =RIGHT(R50,2) -> 14 | U50: =MID(R50,6,2) -> 05 | V50: =LEFT(R50,4) -> 2026 | W50: =CONCATENATE(T50,"-",U50,"-",V50) -> 14-05-2026 | X50: =L50 -> 2026/05/14,21:46:06
D51: =IF(F51="","",MAX($D$8:D50)+1) -> 42 | E51: 42 | F51: 2125353 | G51: Signal_DL_Failure | H51: Critical | I51: QoS | J51: DL | K51: \\\DL=SSA SR-10.121.68.4-Vyara 6/3-10.121.100.44-KAKRAPAR DAM1/6 | L51: 2026/05/14,19:33:24 | N51: ----/--/--,--:--:-- | O51: Digital Link Layer Failure | Q51: =TRIM(CLEAN(MID(K51,SEARCH("=",K51)+1,LEN(K51)-SEARCH("=",K51)))) -> SSA SR-10.121.68.4-Vyara 6/3-10.121.100.44-KAKRAPAR DAM1/6 | R51: =TRIM(CLEAN(LEFT(L51,SEARCH(",",L51)-1))) -> 2026/05/14 | S51: =TRIM(CLEAN(RIGHT(L51,LEN(L51)-SEARCH(",",L51)))) -> 19:33:24 | T51: =RIGHT(R51,2) -> 14 | U51: =MID(R51,6,2) -> 05 | V51: =LEFT(R51,4) -> 2026 | W51: =CONCATENATE(T51,"-",U51,"-",V51) -> 14-05-2026 | X51: =L51 -> 2026/05/14,19:33:24
D52: =IF(F52="","",MAX($D$8:D51)+1) -> 43 | E52: 43 | F52: 2125352 | G52: Signal_DL_Failure | H52: Critical | I52: QoS | J52: DL | K52: \\\DL=SSA SR-10.121.68.4-Vyara_4/6-10.121.100.47-ANUMALA TE_1/5 | L52: 2026/05/14,19:33:24 | N52: ----/--/--,--:--:-- | O52: Digital Link Layer Failure | Q52: =TRIM(CLEAN(MID(K52,SEARCH("=",K52)+1,LEN(K52)-SEARCH("=",K52)))) -> SSA SR-10.121.68.4-Vyara_4/6-10.121.100.47-ANUMALA TE_1/5 | R52: =TRIM(CLEAN(LEFT(L52,SEARCH(",",L52)-1))) -> 2026/05/14 | S52: =TRIM(CLEAN(RIGHT(L52,LEN(L52)-SEARCH(",",L52)))) -> 19:33:24 | T52: =RIGHT(R52,2) -> 14 | U52: =MID(R52,6,2) -> 05 | V52: =LEFT(R52,4) -> 2026 | W52: =CONCATENATE(T52,"-",U52,"-",V52) -> 14-05-2026 | X52: =L52 -> 2026/05/14,19:33:24
D53: =IF(F53="","",MAX($D$8:D52)+1) -> 44 | E53: 44 | F53: 2097887 | G53: Signal_DL_Failure | H53: Critical | I53: QoS | J53: DL | K53: \\\DL=WTR AM-10.121.15.196-DEODAR_S5P1-10.121.15.211-SHIHORI_S4P1 | L53: 2026/05/14,18:22:02 | N53: ----/--/--,--:--:-- | O53: Digital Link Layer Failure | Q53: =TRIM(CLEAN(MID(K53,SEARCH("=",K53)+1,LEN(K53)-SEARCH("=",K53)))) -> WTR AM-10.121.15.196-DEODAR_S5P1-10.121.15.211-SHIHORI_S4P1 | R53: =TRIM(CLEAN(LEFT(L53,SEARCH(",",L53)-1))) -> 2026/05/14 | S53: =TRIM(CLEAN(RIGHT(L53,LEN(L53)-SEARCH(",",L53)))) -> 18:22:02 | T53: =RIGHT(R53,2) -> 14 | U53: =MID(R53,6,2) -> 05 | V53: =LEFT(R53,4) -> 2026 | W53: =CONCATENATE(T53,"-",U53,"-",V53) -> 14-05-2026 | X53: =L53 -> 2026/05/14,18:22:02
D54: =IF(F54="","",MAX($D$8:D53)+1) -> 45 | E54: 45 | F54: 2097873 | G54: Signal_DL_Failure | H54: Critical | I54: QoS | J54: DL | K54: \\\DL=WTR AM-10.121.15.198-TN725B_Deesa_B2_4/5-10.121.15.196-TN725B_Deodar_B2_3/5 | L54: 2026/05/14,18:22:01 | N54: ----/--/--,--:--:-- | O54: Digital Link Layer Failure | Q54: =TRIM(CLEAN(MID(K54,SEARCH("=",K54)+1,LEN(K54)-SEARCH("=",K54)))) -> WTR AM-10.121.15.198-TN725B_Deesa_B2_4/5-10.121.15.196-TN725B_Deodar_B2_3/5 | R54: =TRIM(CLEAN(LEFT(L54,SEARCH(",",L54)-1))) -> 2026/05/14 | S54: =TRIM(CLEAN(RIGHT(L54,LEN(L54)-SEARCH(",",L54)))) -> 18:22:01 | T54: =RIGHT(R54,2) -> 14 | U54: =MID(R54,6,2) -> 05 | V54: =LEFT(R54,4) -> 2026 | W54: =CONCATENATE(T54,"-",U54,"-",V54) -> 14-05-2026 | X54: =L54 -> 2026/05/14,18:22:01
D55: =IF(F55="","",MAX($D$8:D54)+1) -> 46 | E55: 46 | F55: 2085867 | G55: Signal_DL_Failure | H55: Critical | I55: QoS | J55: DL | K55: \\\DL=SSA AMR-10.121.25.209-Sajiyavadar_2/6-10.121.25.211-Sarambhada_1/6 | L55: 2026/05/14,17:57:09 | N55: ----/--/--,--:--:-- | O55: Digital Link Layer Failure | Q55: =TRIM(CLEAN(MID(K55,SEARCH("=",K55)+1,LEN(K55)-SEARCH("=",K55)))) -> SSA AMR-10.121.25.209-Sajiyavadar_2/6-10.121.25.211-Sarambhada_1/6 | R55: =TRIM(CLEAN(LEFT(L55,SEARCH(",",L55)-1))) -> 2026/05/14 | S55: =TRIM(CLEAN(RIGHT(L55,LEN(L55)-SEARCH(",",L55)))) -> 17:57:09 | T55: =RIGHT(R55,2) -> 14 | U55: =MID(R55,6,2) -> 05 | V55: =LEFT(R55,4) -> 2026 | W55: =CONCATENATE(T55,"-",U55,"-",V55) -> 14-05-2026 | X55: =L55 -> 2026/05/14,17:57:09
D56: =IF(F56="","",MAX($D$8:D55)+1) -> 47 | E56: 47 | F56: 2047196 | G56: Signal_DL_Failure | H56: Critical | I56: QoS | J56: DL | K56: \\\DL=SSA BCH-10.121.96.98-CHINA STEEL_1/5-10.121.96.67-PIPALIYA_4/2 | L56: 2026/05/14,16:46:14 | N56: ----/--/--,--:--:-- | O56: Digital Link Layer Failure | Q56: =TRIM(CLEAN(MID(K56,SEARCH("=",K56)+1,LEN(K56)-SEARCH("=",K56)))) -> SSA BCH-10.121.96.98-CHINA STEEL_1/5-10.121.96.67-PIPALIYA_4/2 | R56: =TRIM(CLEAN(LEFT(L56,SEARCH(",",L56)-1))) -> 2026/05/14 | S56: =TRIM(CLEAN(RIGHT(L56,LEN(L56)-SEARCH(",",L56)))) -> 16:46:14 | T56: =RIGHT(R56,2) -> 14 | U56: =MID(R56,6,2) -> 05 | V56: =LEFT(R56,4) -> 2026 | W56: =CONCATENATE(T56,"-",U56,"-",V56) -> 14-05-2026 | X56: =L56 -> 2026/05/14,16:46:14
D57: =IF(F57="","",MAX($D$8:D56)+1) -> 48 | E57: 48 | F57: 1919366 | G57: Signal_DL_Failure | H57: Critical | I57: QoS | J57: DL | K57: \\\DL=SSA VDR-10.121.19.140-VASANA_6/1-10.121.19.139-ATLADRA_5/1 | L57: 2026/05/14,12:22:17 | N57: ----/--/--,--:--:-- | O57: Digital Link Layer Failure | Q57: =TRIM(CLEAN(MID(K57,SEARCH("=",K57)+1,LEN(K57)-SEARCH("=",K57)))) -> SSA VDR-10.121.19.140-VASANA_6/1-10.121.19.139-ATLADRA_5/1 | R57: =TRIM(CLEAN(LEFT(L57,SEARCH(",",L57)-1))) -> 2026/05/14 | S57: =TRIM(CLEAN(RIGHT(L57,LEN(L57)-SEARCH(",",L57)))) -> 12:22:17 | T57: =RIGHT(R57,2) -> 14 | U57: =MID(R57,6,2) -> 05 | V57: =LEFT(R57,4) -> 2026 | W57: =CONCATENATE(T57,"-",U57,"-",V57) -> 14-05-2026 | X57: =L57 -> 2026/05/14,12:22:17
D58: =IF(F58="","",MAX($D$8:D57)+1) -> 49 | E58: 49 | F58: 1904759 | G58: Signal_DL_Failure | H58: Critical | I58: QoS | J58: DL | K58: \\\DL=WTR AM-10.121.16.13-TN705B POR_B1_S3P1-10.121.16.14-TN705B Miagoam_B1 S4P1 | L58: 2026/05/14,11:51:54 | N58: ----/--/--,--:--:-- | O58: Digital Link Layer Failure | Q58: =TRIM(CLEAN(MID(K58,SEARCH("=",K58)+1,LEN(K58)-SEARCH("=",K58)))) -> WTR AM-10.121.16.13-TN705B POR_B1_S3P1-10.121.16.14-TN705B Miagoam_B1 S4P1 | R58: =TRIM(CLEAN(LEFT(L58,SEARCH(",",L58)-1))) -> 2026/05/14 | S58: =TRIM(CLEAN(RIGHT(L58,LEN(L58)-SEARCH(",",L58)))) -> 11:51:54 | T58: =RIGHT(R58,2) -> 14 | U58: =MID(R58,6,2) -> 05 | V58: =LEFT(R58,4) -> 2026 | W58: =CONCATENATE(T58,"-",U58,"-",V58) -> 14-05-2026 | X58: =L58 -> 2026/05/14,11:51:54
D59: =IF(F59="","",MAX($D$8:D58)+1) -> 50 | E59: 50 | F59: 1834732 | G59: Signal_DL_Failure | H59: Critical | I59: QoS | J59: DL | K59: \\\DL=SSA BCH-10.121.96.72-Hinglot_4/1-10.121.96.73-Civil lines_3/1 | L59: 2026/05/14,08:57:55 | N59: ----/--/--,--:--:-- | O59: Digital Link Layer Failure | Q59: =TRIM(CLEAN(MID(K59,SEARCH("=",K59)+1,LEN(K59)-SEARCH("=",K59)))) -> SSA BCH-10.121.96.72-Hinglot_4/1-10.121.96.73-Civil lines_3/1 | R59: =TRIM(CLEAN(LEFT(L59,SEARCH(",",L59)-1))) -> 2026/05/14 | S59: =TRIM(CLEAN(RIGHT(L59,LEN(L59)-SEARCH(",",L59)))) -> 08:57:55 | T59: =RIGHT(R59,2) -> 14 | U59: =MID(R59,6,2) -> 05 | V59: =LEFT(R59,4) -> 2026 | W59: =CONCATENATE(T59,"-",U59,"-",V59) -> 14-05-2026 | X59: =L59 -> 2026/05/14,08:57:55
D60: =IF(F60="","",MAX($D$8:D59)+1) -> 51 | E60: 51 | F60: 1692446 | G60: Signal_DL_Failure | H60: Critical | I60: QoS | J60: DL | K60: \\\DL=SSA VAL-10.121.68.73-Vansda B2_5/6-10.121.24.164-Vandervela A1_1/5 | L60: 2026/05/14,01:32:42 | N60: ----/--/--,--:--:-- | O60: Digital Link Layer Failure | Q60: =TRIM(CLEAN(MID(K60,SEARCH("=",K60)+1,LEN(K60)-SEARCH("=",K60)))) -> SSA VAL-10.121.68.73-Vansda B2_5/6-10.121.24.164-Vandervela A1_1/5 | R60: =TRIM(CLEAN(LEFT(L60,SEARCH(",",L60)-1))) -> 2026/05/14 | S60: =TRIM(CLEAN(RIGHT(L60,LEN(L60)-SEARCH(",",L60)))) -> 01:32:42 | T60: =RIGHT(R60,2) -> 14 | U60: =MID(R60,6,2) -> 05 | V60: =LEFT(R60,4) -> 2026 | W60: =CONCATENATE(T60,"-",U60,"-",V60) -> 14-05-2026 | X60: =L60 -> 2026/05/14,01:32:42
D61: =IF(F61="","",MAX($D$8:D60)+1) -> 52 | E61: 52 | F61: 1575919 | G61: Signal_DL_Failure | H61: Critical | I61: QoS | J61: DL | K61: \\\DL=SSA BUJ-10.121.24.67-Gandhidham_3/3-10.121.24.116-Manali Tower_1/5 | L61: 2026/05/13,19:10:12 | N61: ----/--/--,--:--:-- | O61: Digital Link Layer Failure | Q61: =TRIM(CLEAN(MID(K61,SEARCH("=",K61)+1,LEN(K61)-SEARCH("=",K61)))) -> SSA BUJ-10.121.24.67-Gandhidham_3/3-10.121.24.116-Manali Tower_1/5 | R61: =TRIM(CLEAN(LEFT(L61,SEARCH(",",L61)-1))) -> 2026/05/13 | S61: =TRIM(CLEAN(RIGHT(L61,LEN(L61)-SEARCH(",",L61)))) -> 19:10:12 | T61: =RIGHT(R61,2) -> 13 | U61: =MID(R61,6,2) -> 05 | V61: =LEFT(R61,4) -> 2026 | W61: =CONCATENATE(T61,"-",U61,"-",V61) -> 13-05-2026 | X61: =L61 -> 2026/05/13,19:10:12
D62: =IF(F62="","",MAX($D$8:D61)+1) -> 53 | E62: 53 | F62: 1419291 | G62: Signal_DL_Failure | H62: Critical | I62: QoS | J62: DL | K62: \\\DL=WTR RJ-10.121.68.206-TN725B_JAM JODHPUR_PH3\S4P1-10.121.68.197-TN725B_BHANVAD_PH3\S5P1 | L62: 2026/05/13,14:16:24 | M62: 201300343 | N62: 2026/05/13,16:53:53 | O62: Digital Link Layer Failure | Q62: =TRIM(CLEAN(MID(K62,SEARCH("=",K62)+1,LEN(K62)-SEARCH("=",K62)))) -> WTR RJ-10.121.68.206-TN725B_JAM JODHPUR_PH3\S4P1-10.121.68.197-TN725B_BHANVAD_PH3\S5P1 | R62: =TRIM(CLEAN(LEFT(L62,SEARCH(",",L62)-1))) -> 2026/05/13 | S62: =TRIM(CLEAN(RIGHT(L62,LEN(L62)-SEARCH(",",L62)))) -> 14:16:24 | T62: =RIGHT(R62,2) -> 13 | U62: =MID(R62,6,2) -> 05 | V62: =LEFT(R62,4) -> 2026 | W62: =CONCATENATE(T62,"-",U62,"-",V62) -> 13-05-2026 | X62: =L62 -> 2026/05/13,14:16:24
D63: =IF(F63="","",MAX($D$8:D62)+1) -> 54 | E63: 54 | F63: 1348523 | G63: Signal_DL_Failure | H63: Critical | I63: QoS | J63: DL | K63: \\\DL=SSA AM-10.121.18.234-Shretha_1/5-10.121.18.231-Uvarsad_A1_2/5 | L63: 2026/05/13,11:56:16 | N63: ----/--/--,--:--:-- | O63: Digital Link Layer Failure | Q63: =TRIM(CLEAN(MID(K63,SEARCH("=",K63)+1,LEN(K63)-SEARCH("=",K63)))) -> SSA AM-10.121.18.234-Shretha_1/5-10.121.18.231-Uvarsad_A1_2/5 | R63: =TRIM(CLEAN(LEFT(L63,SEARCH(",",L63)-1))) -> 2026/05/13 | S63: =TRIM(CLEAN(RIGHT(L63,LEN(L63)-SEARCH(",",L63)))) -> 11:56:16 | T63: =RIGHT(R63,2) -> 13 | U63: =MID(R63,6,2) -> 05 | V63: =LEFT(R63,4) -> 2026 | W63: =CONCATENATE(T63,"-",U63,"-",V63) -> 13-05-2026 | X63: =L63 -> 2026/05/13,11:56:16
D64: =IF(F64="","",MAX($D$8:D63)+1) -> 55 | E64: 55 | F64: 1321100 | G64: Signal_DL_Failure | H64: Critical | I64: QoS | J64: DL | K64: \\\DL=SSA BCH-10.121.24.193-Bharuch TE(GNE) B2_4/1-10.121.24.195-Jadeshwar B1_3/1 | L64: 2026/05/13,11:03:32 | N64: ----/--/--,--:--:-- | O64: Digital Link Layer Failure | Q64: =TRIM(CLEAN(MID(K64,SEARCH("=",K64)+1,LEN(K64)-SEARCH("=",K64)))) -> SSA BCH-10.121.24.193-Bharuch TE(GNE) B2_4/1-10.121.24.195-Jadeshwar B1_3/1 | R64: =TRIM(CLEAN(LEFT(L64,SEARCH(",",L64)-1))) -> 2026/05/13 | S64: =TRIM(CLEAN(RIGHT(L64,LEN(L64)-SEARCH(",",L64)))) -> 11:03:32 | T64: =RIGHT(R64,2) -> 13 | U64: =MID(R64,6,2) -> 05 | V64: =LEFT(R64,4) -> 2026 | W64: =CONCATENATE(T64,"-",U64,"-",V64) -> 13-05-2026 | X64: =L64 -> 2026/05/13,11:03:32
D65: =IF(F65="","",MAX($D$8:D64)+1) -> 56 | E65: 56 | F65: 1316332 | G65: Signal_DL_Failure | H65: Critical | I65: QoS | J65: DL | K65: \\\DL=SSA SR-10.121.16.3-PipodaraB2_5/1-10.121.68.10-KosambaB1_3/1 | L65: 2026/05/13,10:55:09 | N65: ----/--/--,--:--:-- | O65: Digital Link Layer Failure | Q65: =TRIM(CLEAN(MID(K65,SEARCH("=",K65)+1,LEN(K65)-SEARCH("=",K65)))) -> SSA SR-10.121.16.3-PipodaraB2_5/1-10.121.68.10-KosambaB1_3/1 | R65: =TRIM(CLEAN(LEFT(L65,SEARCH(",",L65)-1))) -> 2026/05/13 | S65: =TRIM(CLEAN(RIGHT(L65,LEN(L65)-SEARCH(",",L65)))) -> 10:55:09 | T65: =RIGHT(R65,2) -> 13 | U65: =MID(R65,6,2) -> 05 | V65: =LEFT(R65,4) -> 2026 | W65: =CONCATENATE(T65,"-",U65,"-",V65) -> 13-05-2026 | X65: =L65 -> 2026/05/13,10:55:09
D66: =IF(F66="","",MAX($D$8:D65)+1) -> 57 | E66: 57 | F66: 1212212 | G66: Signal_DL_Failure | H66: Critical | I66: QoS | J66: DL | K66: \\\DL=SSA BUJ-10.121.17.78-Palasava_1/5-10.121.17.76-Aadesar_6/3 | L66: 2026/05/13,07:36:32 | N66: ----/--/--,--:--:-- | O66: Digital Link Layer Failure | Q66: =TRIM(CLEAN(MID(K66,SEARCH("=",K66)+1,LEN(K66)-SEARCH("=",K66)))) -> SSA BUJ-10.121.17.78-Palasava_1/5-10.121.17.76-Aadesar_6/3 | R66: =TRIM(CLEAN(LEFT(L66,SEARCH(",",L66)-1))) -> 2026/05/13 | S66: =TRIM(CLEAN(RIGHT(L66,LEN(L66)-SEARCH(",",L66)))) -> 07:36:32 | T66: =RIGHT(R66,2) -> 13 | U66: =MID(R66,6,2) -> 05 | V66: =LEFT(R66,4) -> 2026 | W66: =CONCATENATE(T66,"-",U66,"-",V66) -> 13-05-2026 | X66: =L66 -> 2026/05/13,07:36:32
D67: =IF(F67="","",MAX($D$8:D66)+1) -> 58 | E67: 58 | F67: 1043851 | G67: Signal_DL_Failure | H67: Critical | I67: QoS | J67: DL | K67: \\\DL=SSA BCH-10.121.96.99-Gnfc Suva Vill A1_1/5-10.121.98.68-Dharmaj B1_2/5 | L67: 2026/05/13,01:04:09 | N67: ----/--/--,--:--:-- | O67: Digital Link Layer Failure | Q67: =TRIM(CLEAN(MID(K67,SEARCH("=",K67)+1,LEN(K67)-SEARCH("=",K67)))) -> SSA BCH-10.121.96.99-Gnfc Suva Vill A1_1/5-10.121.98.68-Dharmaj B1_2/5 | R67: =TRIM(CLEAN(LEFT(L67,SEARCH(",",L67)-1))) -> 2026/05/13 | S67: =TRIM(CLEAN(RIGHT(L67,LEN(L67)-SEARCH(",",L67)))) -> 01:04:09 | T67: =RIGHT(R67,2) -> 13 | U67: =MID(R67,6,2) -> 05 | V67: =LEFT(R67,4) -> 2026 | W67: =CONCATENATE(T67,"-",U67,"-",V67) -> 13-05-2026 | X67: =L67 -> 2026/05/13,01:04:09
D68: =IF(F68="","",MAX($D$8:D67)+1) -> 59 | E68: 59 | F68: 852860 | G68: Signal_DL_Failure | H68: Critical | I68: QoS | J68: DL | K68: \\\DL=SSA BCH-10.121.16.10-Jambusar_S5P8-10.121.96.114-SCHOTT GLASS JBSR_2/3 | L68: 2026/05/12,18:16:15 | N68: ----/--/--,--:--:-- | O68: Digital Link Layer Failure | Q68: =TRIM(CLEAN(MID(K68,SEARCH("=",K68)+1,LEN(K68)-SEARCH("=",K68)))) -> SSA BCH-10.121.16.10-Jambusar_S5P8-10.121.96.114-SCHOTT GLASS JBSR_2/3 | R68: =TRIM(CLEAN(LEFT(L68,SEARCH(",",L68)-1))) -> 2026/05/12 | S68: =TRIM(CLEAN(RIGHT(L68,LEN(L68)-SEARCH(",",L68)))) -> 18:16:15 | T68: =RIGHT(R68,2) -> 12 | U68: =MID(R68,6,2) -> 05 | V68: =LEFT(R68,4) -> 2026 | W68: =CONCATENATE(T68,"-",U68,"-",V68) -> 12-05-2026 | X68: =L68 -> 2026/05/12,18:16:15
D69: =IF(F69="","",MAX($D$8:D68)+1) -> 60 | E69: 60 | F69: 648500 | G69: Signal_DL_Failure | H69: Critical | I69: QoS | J69: DL | K69: \\\DL=SSA VAL-10.121.68.73-Vansda B2_6/1-10.121.68.84-WAGHAI B2_6/1 | L69: 2026/05/12,11:31:11 | N69: ----/--/--,--:--:-- | O69: Digital Link Layer Failure | Q69: =TRIM(CLEAN(MID(K69,SEARCH("=",K69)+1,LEN(K69)-SEARCH("=",K69)))) -> SSA VAL-10.121.68.73-Vansda B2_6/1-10.121.68.84-WAGHAI B2_6/1 | R69: =TRIM(CLEAN(LEFT(L69,SEARCH(",",L69)-1))) -> 2026/05/12 | S69: =TRIM(CLEAN(RIGHT(L69,LEN(L69)-SEARCH(",",L69)))) -> 11:31:11 | T69: =RIGHT(R69,2) -> 12 | U69: =MID(R69,6,2) -> 05 | V69: =LEFT(R69,4) -> 2026 | W69: =CONCATENATE(T69,"-",U69,"-",V69) -> 12-05-2026 | X69: =L69 -> 2026/05/12,11:31:11
D70: =IF(F70="","",MAX($D$8:D69)+1) -> 61 | E70: 61 | F70: 646914 | G70: Signal_DL_Failure | H70: Critical | I70: QoS | J70: DL | K70: \\\DL=SSA VAL-10.121.68.86-SAMGAHAN-10.121.68.83-AHWA | L70: 2026/05/12,11:28:49 | N70: ----/--/--,--:--:-- | O70: Digital Link Layer Failure | Q70: =TRIM(CLEAN(MID(K70,SEARCH("=",K70)+1,LEN(K70)-SEARCH("=",K70)))) -> SSA VAL-10.121.68.86-SAMGAHAN-10.121.68.83-AHWA | R70: =TRIM(CLEAN(LEFT(L70,SEARCH(",",L70)-1))) -> 2026/05/12 | S70: =TRIM(CLEAN(RIGHT(L70,LEN(L70)-SEARCH(",",L70)))) -> 11:28:49 | T70: =RIGHT(R70,2) -> 12 | U70: =MID(R70,6,2) -> 05 | V70: =LEFT(R70,4) -> 2026 | W70: =CONCATENATE(T70,"-",U70,"-",V70) -> 12-05-2026 | X70: =L70 -> 2026/05/12,11:28:49
D71: =IF(F71="","",MAX($D$8:D70)+1) -> 62 | E71: 62 | F71: 604193 | G71: Signal_DL_Failure | H71: Critical | I71: QoS | J71: DL | K71: \\\DL=SSA BUJ-10.121.24.71-Gandhidham II_4/1-10.121.24.73-Bharat Nagar_3/1 | L71: 2026/05/12,10:04:40 | N71: ----/--/--,--:--:-- | O71: Digital Link Layer Failure | Q71: =TRIM(CLEAN(MID(K71,SEARCH("=",K71)+1,LEN(K71)-SEARCH("=",K71)))) -> SSA BUJ-10.121.24.71-Gandhidham II_4/1-10.121.24.73-Bharat Nagar_3/1 | R71: =TRIM(CLEAN(LEFT(L71,SEARCH(",",L71)-1))) -> 2026/05/12 | S71: =TRIM(CLEAN(RIGHT(L71,LEN(L71)-SEARCH(",",L71)))) -> 10:04:40 | T71: =RIGHT(R71,2) -> 12 | U71: =MID(R71,6,2) -> 05 | V71: =LEFT(R71,4) -> 2026 | W71: =CONCATENATE(T71,"-",U71,"-",V71) -> 12-05-2026 | X71: =L71 -> 2026/05/12,10:04:40
D72: =IF(F72="","",MAX($D$8:D71)+1) -> 63 | E72: 63 | F72: 563536 | G72: Signal_DL_Failure | H72: Critical | I72: QoS | J72: DL | K72: \\\DL=SSA MEH-10.121.15.142-TN725B_Patan_B2\S3P2-10.121.25.103-TN705B_Ranuj_B1\S3P3 | L72: 2026/05/12,08:33:14 | N72: ----/--/--,--:--:-- | O72: Digital Link Layer Failure | Q72: =TRIM(CLEAN(MID(K72,SEARCH("=",K72)+1,LEN(K72)-SEARCH("=",K72)))) -> SSA MEH-10.121.15.142-TN725B_Patan_B2\S3P2-10.121.25.103-TN705B_Ranuj_B1\S3P3 | R72: =TRIM(CLEAN(LEFT(L72,SEARCH(",",L72)-1))) -> 2026/05/12 | S72: =TRIM(CLEAN(RIGHT(L72,LEN(L72)-SEARCH(",",L72)))) -> 08:33:14 | T72: =RIGHT(R72,2) -> 12 | U72: =MID(R72,6,2) -> 05 | V72: =LEFT(R72,4) -> 2026 | W72: =CONCATENATE(T72,"-",U72,"-",V72) -> 12-05-2026 | X72: =L72 -> 2026/05/12,08:33:14
D73: =IF(F73="","",MAX($D$8:D72)+1) -> 64 | E73: 64 | F73: 243478 | G73: Signal_DL_Failure | H73: Critical | I73: QoS | J73: DL | K73: \\\DL=SSA GDH-10.121.19.14-Simaliya A1_1/5-10.121.26.90-Ghoghmba B1_3/2 | L73: 2026/05/11,17:35:43 | N73: ----/--/--,--:--:-- | O73: Digital Link Layer Failure | Q73: =TRIM(CLEAN(MID(K73,SEARCH("=",K73)+1,LEN(K73)-SEARCH("=",K73)))) -> SSA GDH-10.121.19.14-Simaliya A1_1/5-10.121.26.90-Ghoghmba B1_3/2 | R73: =TRIM(CLEAN(LEFT(L73,SEARCH(",",L73)-1))) -> 2026/05/11 | S73: =TRIM(CLEAN(RIGHT(L73,LEN(L73)-SEARCH(",",L73)))) -> 17:35:43 | T73: =RIGHT(R73,2) -> 11 | U73: =MID(R73,6,2) -> 05 | V73: =LEFT(R73,4) -> 2026 | W73: =CONCATENATE(T73,"-",U73,"-",V73) -> 11-05-2026 | X73: =L73 -> 2026/05/11,17:35:43
D74: =IF(F74="","",MAX($D$8:D73)+1) -> 65 | E74: 65 | F74: 92863 | G74: Signal_DL_Failure | H74: Critical | I74: QoS | J74: DL | K74: \\\DL=SSA VDR-10.121.16.41-SAMIYALA A1_2/5-10.121.16.27-CITY B2_5/6 | L74: 2026/05/11,12:32:06 | N74: ----/--/--,--:--:-- | O74: Digital Link Layer Failure | Q74: =TRIM(CLEAN(MID(K74,SEARCH("=",K74)+1,LEN(K74)-SEARCH("=",K74)))) -> SSA VDR-10.121.16.41-SAMIYALA A1_2/5-10.121.16.27-CITY B2_5/6 | R74: =TRIM(CLEAN(LEFT(L74,SEARCH(",",L74)-1))) -> 2026/05/11 | S74: =TRIM(CLEAN(RIGHT(L74,LEN(L74)-SEARCH(",",L74)))) -> 12:32:06 | T74: =RIGHT(R74,2) -> 11 | U74: =MID(R74,6,2) -> 05 | V74: =LEFT(R74,4) -> 2026 | W74: =CONCATENATE(T74,"-",U74,"-",V74) -> 11-05-2026 | X74: =L74 -> 2026/05/11,12:32:06
... D77: =IF(F77="","",MAX($D$8:D76)+1) -> 68 | E77: 68 | F77: 80909 | G77: Signal_DL_Failure | H77: Critical | I77: QoS | J77: DL | K77: \\\DL=SSA VAL-10.121.16.104-POLYCAB KADAIYA A1_1/6-10.121.16.101-HUBER GROUP JANI A1_1/5 | L77: 2026/05/10,11:11:12 | N77: ----/--/--,--:--:-- | O77: Digital Link Layer Failure | Q77: =TRIM(CLEAN(MID(K77,SEARCH("=",K77)+1,LEN(K77)-SEARCH("=",K77)))) -> SSA VAL-10.121.16.104-POLYCAB KADAIYA A1_1/6-10.121.16.101-HUBER GROUP JANI A1_1/5 | R77: =TRIM(CLEAN(LEFT(L77,SEARCH(",",L77)-1))) -> 2026/05/10 | S77: =TRIM(CLEAN(RIGHT(L77,LEN(L77)-SEARCH(",",L77)))) -> 11:11:12 | T77: =RIGHT(R77,2) -> 10 | U77: =MID(R77,6,2) -> 05 | V77: =LEFT(R77,4) -> 2026 | W77: =CONCATENATE(T77,"-",U77,"-",V77) -> 10-05-2026 | X77: =L77 -> 2026/05/10,11:11:12
D78: =IF(F78="","",MAX($D$8:D77)+1) -> 69 | E78: 69 | F78: 79047 | G78: Signal_DL_Failure | H78: Critical | I78: QoS | J78: DL | K78: \\\DL=WTR RJ-10.121.69.12-Thordi_4/1-10.121.96.12-Rajula Rsu_4/1 | L78: 2026/05/09,09:11:24 | M78: 201300343 | N78: 2026/05/11,14:04:07 | O78: Digital Link Layer Failure | Q78: =TRIM(CLEAN(MID(K78,SEARCH("=",K78)+1,LEN(K78)-SEARCH("=",K78)))) -> WTR RJ-10.121.69.12-Thordi_4/1-10.121.96.12-Rajula Rsu_4/1 | R78: =TRIM(CLEAN(LEFT(L78,SEARCH(",",L78)-1))) -> 2026/05/09 | S78: =TRIM(CLEAN(RIGHT(L78,LEN(L78)-SEARCH(",",L78)))) -> 09:11:24 | T78: =RIGHT(R78,2) -> 09 | U78: =MID(R78,6,2) -> 05 | V78: =LEFT(R78,4) -> 2026 | W78: =CONCATENATE(T78,"-",U78,"-",V78) -> 09-05-2026 | X78: =L78 -> 2026/05/09,09:11:24
D79: =IF(F79="","",MAX($D$8:D78)+1) -> 70 | E79: 70 | F79: 77875 | G79: Signal_DL_Failure | H79: Critical | I79: QoS | J79: DL | K79: \\\DL=WTR RJ-10.121.68.214-Banugar B2_4/1-10.121.68.215-Jodia B1_3/1 | L79: 2026/05/07,11:34:05 | M79: 201300343 | N79: 2026/05/07,13:07:35 | O79: Digital Link Layer Failure | Q79: =TRIM(CLEAN(MID(K79,SEARCH("=",K79)+1,LEN(K79)-SEARCH("=",K79)))) -> WTR RJ-10.121.68.214-Banugar B2_4/1-10.121.68.215-Jodia B1_3/1 | R79: =TRIM(CLEAN(LEFT(L79,SEARCH(",",L79)-1))) -> 2026/05/07 | S79: =TRIM(CLEAN(RIGHT(L79,LEN(L79)-SEARCH(",",L79)))) -> 11:34:05 | T79: =RIGHT(R79,2) -> 07 | U79: =MID(R79,6,2) -> 05 | V79: =LEFT(R79,4) -> 2026 | W79: =CONCATENATE(T79,"-",U79,"-",V79) -> 07-05-2026 | X79: =L79 -> 2026/05/07,11:34:05
D80: =IF(F80="","",MAX($D$8:D79)+1) -> 71 | E80: 71 | F80: 77411 | G80: Signal_DL_Failure | H80: Critical | I80: QoS | J80: DL | K80: \\\DL=SSA VDR-10.121.99.179-Urban 2 BTS_1/5-10.121.99.164-Navrachana BTS_1/6 | L80: 2026/05/07,09:04:38 | N80: ----/--/--,--:--:-- | O80: Digital Link Layer Failure | Q80: =TRIM(CLEAN(MID(K80,SEARCH("=",K80)+1,LEN(K80)-SEARCH("=",K80)))) -> SSA VDR-10.121.99.179-Urban 2 BTS_1/5-10.121.99.164-Navrachana BTS_1/6 | R80: =TRIM(CLEAN(LEFT(L80,SEARCH(",",L80)-1))) -> 2026/05/07 | S80: =TRIM(CLEAN(RIGHT(L80,LEN(L80)-SEARCH(",",L80)))) -> 09:04:38 | T80: =RIGHT(R80,2) -> 07 | U80: =MID(R80,6,2) -> 05 | V80: =LEFT(R80,4) -> 2026 | W80: =CONCATENATE(T80,"-",U80,"-",V80) -> 07-05-2026 | X80: =L80 -> 2026/05/07,09:04:38
D81: =IF(F81="","",MAX($D$8:D80)+1) -> 72 | E81: 72 | F81: 96339 | G81: Signal_DL_Failure | H81: Critical | I81: QoS | J81: DL | K81: \\\DL=SSA BCH-10.121.96.70-Rahiyad B2-10.121.96.71-Bhensli B1 3/1 | L81: 2026/05/06,16:26:18 | N81: ----/--/--,--:--:-- | O81: Digital Link Layer Failure | Q81: =TRIM(CLEAN(MID(K81,SEARCH("=",K81)+1,LEN(K81)-SEARCH("=",K81)))) -> SSA BCH-10.121.96.70-Rahiyad B2-10.121.96.71-Bhensli B1 3/1 | R81: =TRIM(CLEAN(LEFT(L81,SEARCH(",",L81)-1))) -> 2026/05/06 | S81: =TRIM(CLEAN(RIGHT(L81,LEN(L81)-SEARCH(",",L81)))) -> 16:26:18 | T81: =RIGHT(R81,2) -> 06 | U81: =MID(R81,6,2) -> 05 | V81: =LEFT(R81,4) -> 2026 | W81: =CONCATENATE(T81,"-",U81,"-",V81) -> 06-05-2026 | X81: =L81 -> 2026/05/06,16:26:18
D82: =IF(F82="","",MAX($D$8:D81)+1) -> 73 | E82: 73 | F82: 254464 | G82: Signal_DL_Failure | H82: Critical | I82: QoS | J82: DL | K82: \\\DL=SSA AMR-10.121.96.38-VIJAPADI-TE_4/2-10.121.96.27-Gadhakada-Exch_2/6 | L82: 2026/05/06,10:58:34 | N82: ----/--/--,--:--:-- | O82: Digital Link Layer Failure | Q82: =TRIM(CLEAN(MID(K82,SEARCH("=",K82)+1,LEN(K82)-SEARCH("=",K82)))) -> SSA AMR-10.121.96.38-VIJAPADI-TE_4/2-10.121.96.27-Gadhakada-Exch_2/6 | R82: =TRIM(CLEAN(LEFT(L82,SEARCH(",",L82)-1))) -> 2026/05/06 | S82: =TRIM(CLEAN(RIGHT(L82,LEN(L82)-SEARCH(",",L82)))) -> 10:58:34 | T82: =RIGHT(R82,2) -> 06 | U82: =MID(R82,6,2) -> 05 | V82: =LEFT(R82,4) -> 2026 | W82: =CONCATENATE(T82,"-",U82,"-",V82) -> 06-05-2026 | X82: =L82 -> 2026/05/06,10:58:34
D83: =IF(F83="","",MAX($D$8:D82)+1) -> 74 | E83: 74 | F83: 66919 | G83: Signal_DL_Failure | H83: Critical | I83: QoS | J83: DL | K83: \\\DL=SSA VAL-10.121.68.78-GEB BALITHA_1/6-10.121.68.66-Vapi_5/3 | L83: 2026/05/05,22:02:35 | N83: ----/--/--,--:--:-- | O83: Digital Link Layer Failure | Q83: =TRIM(CLEAN(MID(K83,SEARCH("=",K83)+1,LEN(K83)-SEARCH("=",K83)))) -> SSA VAL-10.121.68.78-GEB BALITHA_1/6-10.121.68.66-Vapi_5/3 | R83: =TRIM(CLEAN(LEFT(L83,SEARCH(",",L83)-1))) -> 2026/05/05 | S83: =TRIM(CLEAN(RIGHT(L83,LEN(L83)-SEARCH(",",L83)))) -> 22:02:35 | T83: =RIGHT(R83,2) -> 05 | U83: =MID(R83,6,2) -> 05 | V83: =LEFT(R83,4) -> 2026 | W83: =CONCATENATE(T83,"-",U83,"-",V83) -> 05-05-2026 | X83: =L83 -> 2026/05/05,22:02:35
